Workbook

Sheet Телефония
A1: http://yealink.review.ipmatika.kz/ | H1: ПРАВСИМВ(Подбор!R1C7;21) | I1: ПРАВСИМВ(Подбор!R1C7;19)
A2: Наименование товара | B2: Артикул | C2: РРЦ | F2: Цена Сайт | G2: . | H2: Я бы купил!
A3: 1. SIP-телефоны
A4: Yealink SIP-T30 SIP-телефон, 1 линия, С БП замена T19 | B4: SIP-T30 | C4: 27960 | F4: =C4*0.93 -> 26002.8 | H4: add
A5: Yealink SIP-T30P SIP-телефон, 1 линия, Poe c БП замена T19P | B5: SIP-T30P | C5: 31370 | F5: =C5*0.93 -> 29174.1 | H5: add
A6: Yealink SIP-T31 SIP-телефон, 2 линии, с БП замена T21 | B6: SIP-T31 | C6: 29810 | F6: =C6*0.93 -> 27723.3 | H6: add
A7: Yealink SIP-T31P SIP-телефон, 2 линии, Poe, с БП замена T21P | B7: SIP-T31P | C7: 35000 | F7: =C7*0.93 -> 32550 | H7: add
A8: Yealink SIP-T31P, цвет светло-серый, 2 аккаунта, PoE | B8: SIP-T31P Light Gray | C8: 42120 | F8: =C8*0.93 -> 39171.6 | H8: add
A9: Yealink SIP-T31G SIP-телефон, 2 линии, PoE, GigE, с БП замена T23G | B9: SIP-T31G | C9: 40170 | F9: =C9*0.93 -> 37358.1 | H9: add
A10: Yealink SIP-T33G,4 линии,цветной экран, PoE, GigE, с БП замена T40G | B10: SIP-T33G | C10: 52530 | F10: =C10*0.93 -> 48852.9 | H10: add
A11: Yealink SIP-T31W, 2 аккаунта, Wi-Fi, PoE | B11: SIP-T31W | C11: 45360 | F11: =C11*0.93 -> 42184.8 | H11: add
A12: Yealink SIP-T34W, 4 аккаунта, Wi-Fi, USB, цветной экран, PoE, GigE | B12: SIP-T34W | C12: 61880 | F12: =C12*0.93 -> 57548.4 | H12: add
A13: Yealink SIP-T42G,3 аккаунта,BLF,PoE, GigE, без БП | B13: SIP-T42G sale | C13: 63420 | F13: =C13*0.93 -> 58980.6 | H13: add
A14: Yealink SIP-T43U (12 аккаунтов, 2 порта USB, BLF, PoE, GigE) без БП | B14: SIP-T43U | C14: 85360 | F14: =C14*0.93 -> 79384.8 | H14: add
A15: Yealink SIP-T44U, 12 аккаунтов, 2 порта USB, цветной экран, BLF, PoE, GigE, без БП | B15: SIP-T44U | C15: 93180 | F15: =C15*0.93 -> 86657.4 | H15: add
... A26: Yealink MP50 USB-телефон, Bluetooth, сенсорный экран | B26: MP50 | C26: 105370 | F26: =C26*0.93 -> 97994.1 | H26: add
A27: Yealink SIP-T73U, 12 аккаунтов, 2,8" цветной экран, порт USB, BLF, PoE, GigE, без БП | B27: SIP-T73U | C27: 88480 | F27: =C27*0.93 -> 82286.4
A28: Yealink SIP-T73W, 12 аккаунтов, Wi-Fi, 2,8" цветной экран, порт USB, BLF, PoE, GigE, без БП | B28: SIP-T73W | C28: 100060 | F28: =C28*0.93 -> 93055.8
A29: Yealink SIP-T74U, 16 аккаунтов, 4,3" цветной экран, порт USB, BLF, PoE, GigE, без БП | B29: SIP-T74U | C29: 140760 | F29: =C29*0.93 -> 130906.8
A30: Yealink SIP-T74W, 16 аккаунтов, Wi-Fi, 4,3" цветной экран, порт USB, BLF, PoE, GigE, без БП | B30: SIP-T74W | C30: 154830 | F30: =C30*0.93 -> 143991.9
A31: Yealink SIP-T77U, 7" цветной сенсорный экран, 2 порта USB, 16 аккаунтов, BLF, PoE, GigE, без БП | B31: SIP-T77U | C31: 192970 | F31: =C31*0.93 -> 179462.1
A32: Yealink AX83H, экран 2.4", Wi-Fi 6, виброоповещение, Bluetooth, 3.5 mm, Type-C, SNC, звук HD | B32: AX83H | C32: 90010 | F32: =C32*0.93 -> 83709.3
A33: Yealink AX86R, экран 2.4", Wi-Fi 6, IP67, Alarm, виброоповещение, Bluetooth, 3.5 mm, Type-C, SNC, звук HD | B33: AX86R | C33: 142980 | F33: =C33*0.93 -> 132971.4
A34: Yealink W56H DECT SIP-трубка | B34: W56H | C34: 70360 | F34: =C34*0.93 -> 65434.8 | H34: add
A35: Yealink W59R DECT SIP-трубка | B35: W59R | C35: 124080 | F35: =C35*0.93 -> 115394.4 | H35: add
A36: Yealink W57R, степень защиты IP54, HD звук, вибросигнал, FNR, быстрая зарядка, для W70B/W80B/W90B | B36: W57R | C36: 112710 | F36: =C36*0.93 -> 104820.3 | H36: add
A37: Yealink W70B DECT, базовая станция, до 10 SIP-аккаунтов, до 10 трубок на базу, до 20 одновременных вызовов | B37: W70B | C37: 54110 | F37: =C37*0.93 -> 50322.3 | H37: add
A38: Yealink W74H, экран 1.8", виброоповещение, FNR, BT, 3.5 mm, для W70B/W71P/W73P/W74P/W76P/W79P/W75/W80/W90 | B38: W74H | C38: 68810 | F38: =C38*0.93 -> 63993.3 | H38: add
A39: Yealink W73H DECT SIP-трубка для W70B/W73P/W76P//W79P/W80B/W90B | B39: W73H | C39: 61930 | F39: =C39*0.93 -> 57594.9 | H39: add
A40: Yealink W71H, экран 1.8", FNR, для W70B/W71P/W73P/W74P/W76P/W79P/W75/W80/W90 | B40: W71H | C40: 49910 | F40: =C40*0.93 -> 46416.3 | H40: add
A41: Yealink W78H, HD звук, экран 2.4", виброоповещение, 3.5 мм, для W70B/W80B/W90B | B41: W78H | C41: 93050 | F41: =C41*0.93 -> 86536.5 | H41: add
A42: Yealink W79P DECT (база W70B +трубка W59R ) до 10 SIP-аккаунтов, до 10 трубок на базу, до 20 одноврем. Вызовов | B42: W79P | C42: 173970 | F42: =C42*0.93 -> 161792.1 | H42: add
A43: Yealink W78P (база W70B+трубка W78H) до 10 SIP-аккаунтов, до 10 трубок на базу, до 20 одновременных вызовов | B43: W78P | C43: 132370 | F43: =C43*0.93 -> 123104.1 | H43: add
A44: Yealink W77P (база W70B+трубка W57R) до 10 SIP-аккаунтов, до 10 трубок на базу, до 20 одновременных вызовов | B44: W77P | C44: 158580 | F44: =C44*0.93 -> 147479.4 | H44: add
A45: Yealink W76P DECT (база W70B+трубка W56H) до 10 SIP-аккаунтов, до 10 трубок на базу, до 20 одноврем. вызовов | B45: W76P | C45: 111290 | F45: =C45*0.93 -> 103499.7 | H45: add
... A70: Yealink SP96 with Dongle USB-C/A, USB, Bluetooth, Экран, встроенная батарея, 6 встроенных микрофонов | B70: SP96 with Dongle USB-C/A | C70: 134080 | F70: =C70*0.93 -> 124694.4 | H70: add
A71: Телефоны для Teams/Skype for Business | F71: =C71*0.93 -> 0
A72: Yealink MP50 USB-телефон, Bluetooth, сенсорный экран | B72: MP50 | C72: 105370 | F72: =C72*0.93 -> 97994.1 | H72: add
A73: Yealink SIP MP54, Teams/Skype for Business, цветной сенсорный экран, Звук Optima HD, USB, PoE, GigE, без БП | B73: MP54-TEAMS | C73: 218260 | F73: =C73*0.93 -> 202981.8 | H73: add
A74: Yealink SIP-MP56, Teams/Skype for Business, цветной сенсорный экран, PoE, GigE, без БП | B74: MP56-Teams | C74: 276460 | F74: =C74*0.93 -> 257107.8 | H74: add
A75: Yealink SIP-MP58, Teams/Skype for Business, Цветной сенсорный экран, Звук Optima HD, WiFi, Bluetooth, USB, PoE, GigE, без БП | B75: MP58-TEAMS | C75: 294840 | F75: =C75*0.93 -> 274201.2 | H75: add
A76: Yealink SIP-MP58-WH, Teams/Skype for Business, Беспроводная трубка, Цветной экран, Optima HD, WiFi, Bluetooth, PoE, GigE, без БП | B76: MP58-WH-TEAMS | C76: 337940 | F76: =C76*0.93 -> 314284.2 | H76: add
A77: 2.Аксессуары | F77: =C77*0.93 -> 0
A78: Yealink BT41 Bluetooth V4.1 USB-адаптер | B78: BT41 | C78: 23380 | F78: =C78*0.93 -> 21743.4 | H78: add
A79: Yealink BTH58 беспроводная Bluetooth-трубка для SIP-T58W/MP58 | B79: BTH58 | C79: 38040 | F79: =C79*0.93 -> 35377.2
A80: Yealink CPN10 для телефона CP860, шт переходник | B80: CPN10 | C80: 39350 | F80: =C80*0.93 -> 36595.5 | H80: add
A81: Yealink CAM50 USB-камера для телефонов SIP-T58V(A), шт | B81: CAM50-updated | C81: 79880 | F81: =C81*0.93 -> 74288.4 | H81: add
A82: Yealink WF50 WiFi-адаптер Yealink | B82: WF50 | C82: 22560 | F82: =C82*0.93 -> 20980.8 | H82: add
A83: Yealink WF50 WiFi-адаптер Yealink | B83: WF50 sale | C83: 29990 | F83: =C83*0.93 -> 27890.7 | H83: add
A84: Yealink EXP43 модуль расширения с LCD для телефонов | B84: EXP43 | C84: 77060 | F84: =C84*0.93 -> 71665.8 | H84: add
A85: Yealink EXP50 с LCD для телефонов SIP-T58V(A), SIP-T56A | B85: EXP50 | C85: 96650 | F85: =C85*0.93 -> 89884.5 | H85: add
A86: Yealink EXP55, цветной LCD дисплей, BLF-клавиши, для SIP-телефонов T7X /T8X | B86: EXP55 | C86: 96650 | F86: =C86*0.93 -> 89884.5 | H86: add
A87: Yealink RT10 DECT-репитер для телефонов W52P и W56P | B87: RT10 sale | C87: 75510 | F87: =C87*0.93 -> 70224.3 | H87: add
A88: Yealink RT30 DECT-репитер для SIP- телефонов W52P/W60P/W41P | B88: RT30 | C88: 98330 | F88: =C88*0.93 -> 91446.9 | H88: add
A89: Yealink CPW65-DECT-Duo дополнительные беспроводные DECT-микрофоны 2шт. для CP965 | B89: CPW65-DECT-Duo | C89: 272720 | F89: =C89*0.93 -> 253629.6 | H89: add
A90: Yealink CPE90 дополнительные проводные микрофоны 2шт. для CP960 | B90: CPE90 | F90: =C90*0.93 -> #VALUE! | H90: add
A91: Yealink CPE80, дополнительный микрофон для CP860 | B91: CPE80 | F91: =C91*0.93 -> #VALUE! | H91: add
A92: Yealink DD10K — DECT-адаптер для SIP-T41S и SIP-T42S | B92: DD10K | C92: 17580 | F92: =C92*0.93 -> 16349.4 | H92: add
A93: Yealink EHS36 адаптер для беспроводных гарнитур Plantronics/Jabra для телефонов T28P/T26P | B93: EHS36 | C93: 54270 | F93: =C93*0.93 -> 50471.1 | H93: add
A94: Yealink EHS36 адаптер для беспроводных гарнитур Plantronics/Jabra для телефонов T28P/T26P | B94: EHS36 sale | C94: 53210 | F94: =C94*0.93 -> 49485.3 | H94: add
A95: Yealink EHS40 USB адаптер для беспроводных гарнитур Plantronics/Jabra | B95: EHS40 | C95: 54270 | F95: =C95*0.93 -> 50471.1 | H95: add
A96: Yealink Защитный чехол для W53H | B96: Protective case for W53H | C96: 20390 | F96: =C96*0.93 -> 18962.7 | H96: add
A97: Блок питания 5VDC, 600mA для W53P(H)/W56H/W60P/W73P(H)/W76P/W79P/W59R/T30(P)/T31(P,G)/T33P(G) | B97: 5VDC.600mA | C97: 7080 | F97: =C97*0.93 -> 6584.4 | H97: add
A98: Yealink Блок питания 5VDC, 1.2A для SIP-T27G/T41S/T42S/T43U/T53(W)/W80B/W80DM | B98: 5VDC.1.2A | C98: 9230 | F98: =C98*0.93 -> 8583.9 | H98: add
A99: Yealink Блок питания 5VDC, 2A для SIP-T29G/T46U(S)/T48U(S)/T58A/T57W/T54W | B99: 5VDC.2A | C99: 12310 | F99: =C99*0.93 -> 11448.3 | H99: add
A100: Arlight Блок питания ARDV-10-5A (5V, 2A) для EXP50/EXP43/SIP-T46U(S)/T48U(S)/T58W(A)/T57W/T54W | B100: 5VDC,2A-ARDV | F100: =C100*0.93 -> #VALUE! | H100: add
A101: Yealink Блок питания 12VDC, 1A для VP59, CP920 | B101: 12VDC.1A | C101: 12310 | F101: =C101*0.93 -> 11448.3 | H101: add
A102: Yealink Кронштейн для крепления на стену модуля расширения EXP40 | B102: Wall mount EXP40 | C102: 5240 | F102: =C102*0.93 -> 4873.2 | H102: add
A103: Yealink Кронштейн для крепления на стену телефона SIP-T46G/SIP-T48G | B103: Wall mount SIP-T46U(S) | C103: 5240 | F103: =C103*0.93 -> 4873.2 | H103: add
A104: Yealink Кронштейн для крепления на стену телефонов SIP-T42G и SIP-T41P | B104: Кронштейн для T42X/T41X | F104: =C104*0.93 -> #VALUE! | H104: add
A105: YDMP Basic Package (100 licenses), стартовый пакет лицензий на 100 устройств | B105: YDMP Basic Package | C105: 427930 | F105: =C105*0.93 -> 397974.9 | H105: add
A106: YDMP Add-on package (10 licenses), дополнительный пакет лицензий на 10 устройств | B106: YDMP Add-on package | C106: 42800 | F106: =C106*0.93 -> 39804 | H106: add
A107: YVIM Basic Package (2 licenses for DM), стартовый пакет лицензий управляет до 2 DM и 120 баз W90 | B107: YVIM Basic Package (2 licenses for DM) | F107: =C107*0.93 -> #VALUE!
A108: YVIM Add-on (1 license for DM), дополнительный пакет лицензий управляет 1 DM и до 60 баз W90 | B108: YVIM Add-on (1 license for DM) | F108: =C108*0.93 -> #VALUE!
A109: Уличный короб ТША511-25.35.15-50-У1-9720 | B109: ТША511 | F109: =C109*0.93 -> #VALUE!
A110: Крепление на опору для уличного короба ТША511 | B110: КМА1 | F110: =C110*0.93 -> #VALUE!
A111: VT V100 USB веб-камера Full HD | B111: V100 | C111: 38500 | F111: =C111*0.93 -> 35805
A112: 3. ГАРНИТУРЫ | F112: =C112*0.93 -> 0
A113: Гарнитуры RJ9 | F113: =C113*0.93 -> 0
A114: VT Проводная гарнитура VT1000 RJ9(03), Моно, Узкополосный звук | B114: VT1000 RJ9(03) | C114: =VLOOKUP(B114,VT!B:E,3,0) -> 10000 | F114: =C114*0.93 -> 9300 | H114: add
A115: VT Проводная гарнитура VT1000-D RJ9(03), Дуо, Узкополосный звук | B115: VT1000-D RJ9(03) | C115: =VLOOKUP(B115,VT!B:E,3,0) -> 11610 | F115: =C115*0.93 -> 10797.3 | H115: add
A116: VT Проводная гарнитура VT5000 QD(P)-RJ9(03), Моно, Узкополосный звук, QD, переходник QD-RJ09(03) | B116: VT5000 QD(P)-RJ9(03) | C116: =VLOOKUP(B116,VT!B:E,3,0) -> 15770 | F116: =C116*0.93 -> 14666.1 | H116: add
A117: VT Проводная гарнитура VT5000-D QD(P)-RJ9(03), Дуо, Узкополосный звук, QD, переходник QD-RJ09(03) | B117: VT5000-D QD(P)-RJ9(03) | C117: =VLOOKUP(B117,VT!B:E,3,0) -> 19500 | F117: =C117*0.93 -> 18135 | H117: add
A118: VT Проводная гарнитура VT6200 QD(P)-RJ9(03), Моно, HD звук, QD, переходник QD-RJ09(03) | B118: VT6200 QD(P)-RJ9(03) | C118: =VLOOKUP(B118,VT!B:E,3,0) -> 19570 | F118: =C118*0.93 -> 18200.1 | H118: add
A119: VT Проводная гарнитура VT6200-D QD(P)-RJ9(03), Дуо, HD звук, QD, переходник QD-RJ09(03) | B119: VT6200-D QD(P)-RJ9(03) | C119: =VLOOKUP(B119,VT!B:E,3,0) -> 22370 | F119: =C119*0.93 -> 20804.1 | H119: add
A120: Yealink YHS34 Mono Моно, Проводная, HD звук, QD, RJ9 | B120: YHS34 Mono | C120: 20240 | F120: =C120*0.93 -> 18823.2 | H120: add
A121: Yealink YHS34 Dual Дуо, Проводная, HD звук, QD, RJ9 | B121: YHS34 Dual | C121: 27830 | F121: =C121*0.93 -> 25881.9 | H121: add
A122: Yealink YHS34 Lite Mono Моно, Проводная, HD звук, QD, RJ9 | B122: YHS34 Lite Mono | C122: 17710 | F122: =C122*0.93 -> 16470.3 | H122: add
A123: Yealink YHS34 Lite Dual Дуо, Проводная, HD звук, QD, RJ9 | B123: YHS34 Lite Dual | C123: 22770 | F123: =C123*0.93 -> 21176.1 | H123: add
A124: Yealink YHS36 Mono Моно, Проводная, HD звук, QD, RJ9 | B124: YHS36 Mono | C124: 27830 | F124: =C124*0.93 -> 25881.9 | H124: add
A125: Yealink YHS36 Dual Дуо, Проводная, HD звук, QD, RJ9 | B125: YHS36 Dual | C125: 35410 | F125: =C125*0.93 -> 32931.3 | H125: add
A126: Mairdi Гарнитура MRD-509S + MRD-QD002 шнур-переходник с разъемами QD и RJ9 | B126: MRD-509S | C126: 13450 | F126: =C126*0.93 -> 12508.5
A127: Гарнитуры USB | F127: =C127*0.93 -> 0
A128: VT Проводная гарнитура VT5000 USB, Моно, HD звук | B128: VT5000 USB | C128: =VLOOKUP(B128,VT!B:E,3,0) -> 17890 | F128: =C128*0.93 -> 16637.7 | H128: add
A129: VT Проводная гарнитура VT5000-D USB, Дуо, HD звук | B129: VT5000-D USB | C129: =VLOOKUP(B129,VT!B:E,3,0) -> 19930 | F129: =C129*0.93 -> 18534.9 | H129: add
A130: VT Проводная гарнитура VT1000-D USB, Дуо Узкополосный звук | B130: VT1000 USB old | C130: 11000 | F130: =C130*0.93 -> 10230 | H130: add
A131: VT Проводная гарнитура VT6200-D, Дуо, HD звук, USB | B131: VT6200-D USB | C131: =VLOOKUP(B131,VT!B:E,3,0) -> 24440 | F131: =C131*0.93 -> 22729.2 | H131: add
A132: VT Проводная гарнитура VT6200, Моно, HD звук, USB | B132: VT6200 USB | C132: =VLOOKUP(B132,VT!B:E,3,0) -> 22370 | F132: =C132*0.93 -> 20804.1 | H132: add
A133: VT Проводная гарнитура VT6300, Моно, HD звук, USB | B133: VT6300 USB | C133: =VLOOKUP(B133,VT!B:E,3,0) -> 27400 | F133: =C133*0.93 -> 25482 | H133: add
A134: VT Проводная гарнитура VT6300-D, Дуо, HD звук, USB | B134: VT6300-D USB | C134: =VLOOKUP(B134,VT!B:E,3,0) -> 26850 | F134: =C134*0.93 -> 24970.5 | H134: add
...

Sheet Yeastar
A2: Артикул | B2: Краткое описание | C2: РРЦ | D2: Сайт Цена
A3: P - Серия
A4: P520 | B4: IP-АТС до 20 абонентов и до 10 одновременных вызовов позволяет подключать аналоговые линии/телефоны, линии BRI и GSM-линию посредством дополнительных модулей, поддерживает протоколы MFC R2, SS7, FXO, FXS, GSM, BRI, WCDMA(3G), LTE(4G) | C4: 314050 | D4: =C4*0.93 -> 292066.5
A5: P550 | B5: IP-АТС до 50 абонентов и до 25 одновременных вызовов позволяет подключать аналоговые линии/телефоны, линии BRI и GSM-линию посредством дополнительных модулей, поддерживает протоколы MFC R2, SS7, FXO, FXS, GSM, BRI, WCDMA(3G), LTE(4G) | C5: 615450 | D5: =C5*0.93 -> 572368.5
A6: P560 | B6: IP-АТС на 100 абонентов и 30 одновременных вызовов позволяет подключать аналоговые линии/телефоны, линии BRI и GSM-линию посредством дополнительных модулей, поддерживает протоколы MFC R2, SS7, FXO, FXS, GSM, BRI, WCDMA(3G), LTE(4G) | C6: 813450 | D6: =C6*0.93 -> 756508.5
A7: P570 | B7: IP-АТС на 300 абонентов и 60 одновременных вызовов позволяет подключать аналоговые линии/телефоны, линии BRI/PRI и GSM-линии посредством дополнительных модулей, поддерживает протоколы MFC R2, SS7, FXO, FXS, GSM, BRI, PRI, WCDMA(3G), LTE(4G), с помощью модуля D30 расширяется до 200 пользователей и 60 одновременных вызовов | C7: 1658800 | D7: =C7*0.93 -> 1542684
A8: S - Серия
A9: S20 | B9: IP-АТС до 20 абонентов и до 10 одновременных вызовов позволяет подключать аналоговые линии/телефоны, линии BRI и GSM-линию посредством дополнительных модулей, поддерживает протоколы MFC R2, SS7, FXO, FXS, GSM, BRI, WCDMA(3G), LTE(4G) | C9: 276100 | D9: =C9*0.93 -> 256773
A10: S50 | B10: IP-АТС на 50 абонентов и 25 одновременных вызовов позволяет подключать аналоговые линии/телефоны, линии BRI и GSM-линию посредством дополнительных модулей, поддерживает протоколы MFC R2, SS7, FXO, FXS, GSM, BRI, WCDMA(3G), LTE(4G) | C10: 520850 | D10: =C10*0.93 -> 484390.5
A11: S100 | B11: IP-АТС на 100 абонентов и 30 одновременных вызовов позволяет подключать аналоговые линии/телефоны, линии BRI и GSM-линию посредством дополнительных модулей, поддерживает протоколы MFC R2, SS7, FXO, FXS, GSM, BRI, WCDMA(3G), LTE(4G) | C11: 691820 | D11: =C11*0.93 -> 643392.6
A12: Модули для АТС
A13: EX08 | B13: Плата расширения для телефонных станций Yeastar S-серии (S-100 и S-300) На плату может быть установлено до 4-х модулей S2, O2, SO, BRI, GSM, WCDMA и LTE. | C13: 56100 | D13: =C13*0.93 -> 52173
A14: EX30 | B14: Плата расширения для телефонных станций Yeastar S-серии (S-100 и S-300) Поддерживает подключение одного интерфейса E1/T1 | C14: 486200 | D14: =C14*0.93 -> 452166
A15: D30 Card | B15: DSP-модуль для телефонных станций Yeastar S-серии (S100 /S300) один модуль добавляет возможности расширения до 100 пользователей и 30 одновременных вызовов. | C15: 163350 | D15: =C15*0.93 -> 151915.5
A16: O2 | B16: Модуль для подключения 2-х FXO телефонных линий Предназначен для работы со всеми IP-АТС Yeastar. | C16: 64900 | D16: =C16*0.93 -> 60357
A17: S2 | B17: Модуль для подключения 2-х FXS телефонных линий Предназначен для работы со всеми IP-АТС Yeastar. | C17: 57750 | D17: =C17*0.93 -> 53707.5
A18: SO | B18: Модуль для подключения одной FXS и одной FXO линии Переключается в режим «Моста» при неработоспособности системы, соединяя напрямую аналоговый телефон с внешней телефонной линией. Предназначен для работы со всеми IP-АТС Yeastar. | C18: 67100 | D18: =C18*0.93 -> 62403
A19: GSM | B19: Модуль для подключения одного GSM-канала (GSM 850/900/1800/1900МГц ). Предназначен для работы со всеми IP-АТС Yeastar. | C19: 95150 | D19: =C19*0.93 -> 88489.5
A20: UMTS | B20: Модуль для подключения одного UMTS-канала (UMTS 900/2100МГц или 850/2100МГц или 850/1900МГц). Предназначен для работы со всеми IP-АТС Yeastar. | C20: 154050 | D20: =C20*0.93 -> 143266.5
A21: LTE | B21: Модуль для подключения одной LTE линии, позволяет передавать VoIP-данные через сети 4G для подключения к VoIP-операторам по протоколу SIP | C21: 219450 | D21: =C21*0.93 -> 204088.5
A22: B2 | B22: Модуль для подключения двух линий BRI предназначен для работы со всеми IP-АТС Yeastar | C22: 110200 | D22: =C22*0.93 -> 102486
A23: GSM - шлюзы
A24: TG100 | B24: VoIP-GSM-шлюз с поддержкой 1 GSM-линии 850/900/1800/1900 МГц | C24: 87050 | D24: =C24*0.93 -> 80956.5
A25: TG200 | B25: VoIP-GSM-шлюз с поддержкой 2 GSM-линий 850/900/1800/1900 МГц | C25: 174710 | D25: =C25*0.93 -> 162480.3
A26: TG400 | B26: VoIP-GSM-шлюз с поддержкой 4 GSM-линий 850/900/1800/1900 МГц | C26: 330290 | D26: =C26*0.93 -> 307169.7
A27: TG800 | B27: VoIP-GSM-шлюз с поддержкой 8 GSM-линий 850/900/1800/1900 МГц | C27: 598250 | D27: =C27*0.93 -> 556372.5
A28: TG1600/16 | B28: VoIP-GSM-шлюз с поддержкой 16 GSM-линий 850/900/1800/1900 МГц ( 8 GSM-линий 850/900/1800/1900 в комплекте ) | C28: 1234780 | D28: =C28*0.93 -> 1148345.4
A29: FXS/FXO - шлюзы
A30: TA100 | B30: VoIP-FXS-шлюз с поддержкой 1 FXS-линии | C30: 22000 | D30: =C30*0.93 -> 20460
A31: TA200 | B31: VoIP-FXS-шлюз с поддержкой 2 FXS-линий | C31: 32090 | D31: =C31*0.93 -> 29843.7
A32: TA400 | B32: VoIP-FXS-шлюз с поддержкой 4 FXS-линий | C32: 73860 | D32: =C32*0.93 -> 68689.8
A33: TA800 | B33: VoIP-FXS-шлюз с поддержкой 8 FXS-линий | C33: 122900 | D33: =C33*0.93 -> 114297
A34: TA1600 | B34: VoIP-FXS-шлюз с поддержкой 16 FXS-линий | C34: 304440 | D34: =C34*0.93 -> 283129.2
A35: TA2400 | B35: VoIP-FXS-шлюз с поддержкой 24 FXS-линий | C35: 378740 | D35: =C35*0.93 -> 352228.2
A36: TA3200 | B36: VoIP-FXS-шлюз с поддержкой 32 FXS-линий | C36: 453730 | D36: =C36*0.93 -> 421968.9
A37: TA410 | B37: VoIP-FXS-шлюз с поддержкой 4 FXO-линий | C37: 134570 | D37: =C37*0.93 -> 125150.1
A38: TA810 | B38: VoIP-FXS-шлюз с поддержкой 8 FXO-линий | C38: 230560 | D38: =C38*0.93 -> 214420.8
A39: TA1610 | B39: VoIP-FXS-шлюз с поддержкой 16 FXO-линий | C39: 489500 | D39: =C39*0.93 -> 455235
A40: ISDN - шлюзы
A41: TE100 | B41: VoIP-PRI шлюз на 1 порт (E1/T1), поддерживающий до 30 одновременных вызовов | C41: 474070 | D41: =C41*0.93 -> 440885.1
A42: TE200 | B42: VoIP-PRI шлюз на 2 порта (E1/T1) порта, поддерживающий до 30 одновременных вызовов по каждому из портов | C42: 786230 | D42: =C42*0.93 -> 731193.9
A43: TB400 | B43: VoIP-BRI шлюз на 2 BRI порта, поддерживающий до 4-х одновременных вызовов. | C43: 349590 | D43: =C43*0.93 -> 325118.7
A44: Лицензии и программные модули для АТС
A45: Лицензии для расширения функционала P-серии
A46: YSL 109 0010 | B46: P520 Standard License, удалённый доступ (годовая) | C46: 122100 | D46: =C46*0.93 -> 113553
A47: YSL 109 0011 | B47: P520 Enterprise License, удалённый доступ, колл-центр (годовая) | C47: 157850 | D47: =C47*0.93 -> 146800.5
A48: YSL 109 0012 | B48: P520 Ultimate License, удалённый доступ, колл-центр, видеоконф. (годовая) | C48: 237050 | D48: =C48*0.93 -> 220456.5
A49: P520-HMM | B49: P520 HMM License, Hotel Management Module (бессрочная) | C49: 184250 | D49: =C49*0.93 -> 171352.5
A50: YSL 109 0007 | B50: P550 Standard License удалённый доступ (годовая) | C50: 215600 | D50: =C50*0.93 -> 200508
A51: YSL 109 0001 | B51: P550 Enterprise License, удалённый доступ, колл-центр (годовая) | C51: 316800 | D51: =C51*0.93 -> 294624
A52: YSL 109 0004 | B52: P550 Ultimate License, удалённый доступ, колл-центр, видеоконф. (годовая) | C52: 475200 | D52: =C52*0.93 -> 441936
A53: P550-PMS | B53: P550 PMS License, интеграция с Micros Fidelio & Oracle Opera (бессрочная) | C53: 273350 | D53: =C53*0.93 -> 254215.5
A54: P550-HMM | B54: P550 HMM License, Hotel Management Module (бессрочная) | C54: 277750 | D54: =C54*0.93 -> 258307.5
A55: YSL 109 0008 | B55: P560 Standard License, удалённый доступ (годовая) | C55: 323950 | D55: =C55*0.93 -> 301273.5
A56: YSL 109 0002 | B56: P560 Enterprise License, удалённый доступ, колл-центр (годовая) | C56: 396000 | D56: =C56*0.93 -> 368280
A57: YSL 109 0005 | B57: P560 Ultimate License, удалённый доступ, колл-центр, видеоконф. (годовая) | C57: 712800 | D57: =C57*0.93 -> 662904
... A66: P1000m | B66: 1000 минут транскрибирования голосовой почты для P-серии | C66: 22000 | D66: =C66*0.93 -> 20460
A67: Годовые подписки для Yeastar S-серии
A68: YSL 108 0001 | B68: Приложение Linkus Cloud Service для АТС Yeastar S20, год | C68: 92950 | D68: =C68*0.93 -> 86443.5
A69: YSL 108 0002 | B69: Приложение Linkus Cloud Service для АТС Yeastar S50, год | C69: 165000 | D69: =C69*0.93 -> 153450
A70: YSL 108 0003 | B70: Приложение Linkus Cloud Service для АТС Yeastar S100, год | C70: 287650 | D70: =C70*0.93 -> 267514.5
A71: YSL 108 0004 | B71: Приложение Linkus Cloud Service для АТС Yeastar S300, год | C71: 503800 | D71: =C71*0.93 -> 468534
A72: YSL 108 0005 | B72: Приложение Linkus Cloud Service для АТС Yeastar S412, год | C72: 92950 | D72: =C72*0.93 -> 86443.5
A73: YSL 108 0011 | B73: Приложение Linkus Cloud Service PRO (FQDN) для АТС Yeastar S20, год | C73: 122100 | D73: =C73*0.93 -> 113553
A74: YSL 108 0012 | B74: Приложение Linkus Cloud Service PRO (FQDN) для АТС Yeastar S50, год | C74: 215600 | D74: =C74*0.93 -> 200508
A75: YSL 108 0013 | B75: Приложение Linkus Cloud Service PRO (FQDN) для АТС Yeastar S100, год | C75: 323950 | D75: =C75*0.93 -> 301273.5
A76: YSL 108 0014 | B76: Приложение Linkus Cloud Service PRO (FQDN) для АТС Yeastar S300, год | C76: 540100 | D76: =C76*0.93 -> 502293
A77: YSL 108 0015 | B77: Приложение Linkus Cloud Service PRO (FQDN) для АТС Yeastar S412, год | C77: 122100 | D77: =C77*0.93 -> 113553
A78: YSL 107 0002 | B78: Yeastar Remote Management на 1 дополнительное подключение (разово) | C78: 30770 | D78: =C78*0.93 -> 28616.1
A79: Модули ПО для Yeastar
A80: YBMS20 | B80: Billing S20 | C80: 57200 | D80: =C80*0.93 -> 53196
A81: YBMS50 | B81: Billing S50 | C81: 71500 | D81: =C81*0.93 -> 66495
A82: YBMS100 | B82: Billing S100 | C82: 179850 | D82: =C82*0.93 -> 167260.5
A83: YBMS300 | B83: Billing S300 | C83: 316800 | D83: =C83*0.93 -> 294624
A84: YHMS20 | B84: Hotel S20 | C84: 92950 | D84: =C84*0.93 -> 86443.5
A85: YHMS50 | B85: Hotel S50 | C85: 266200 | D85: =C85*0.93 -> 247566
A86: YHMS100 | B86: Hotel S100 | C86: 345400 | D86: =C86*0.93 -> 321222
A87: YHMS300 | B87: Hotel S300 | C87: 575850 | D87: =C87*0.93 -> 535540.5
A88: YCMS20 | B88: Char S20 | C88: 57200 | D88: =C88*0.93 -> 53196
A89: YCMS50 | B89: Char S50 | C89: 71500 | D89: =C89*0.93 -> 66495
A90: YCMS100 | B90: Char S100 | C90: 179850 | D90: =C90*0.93 -> 167260.5
A91: YCMS300 | B91: Char S300 | C91: 316800 | D91: =C91*0.93 -> 294624
A92: PSE - серия (P Software Edition) - по количеству одновременных вызовов
A93: PSE - Enterprise - годовые лицензии
A94: PSE-EP-4SC | B94: Лицензия PSE EP на 4 вызова (реком. до 10 пользователей) на 1г | C94: 143550 | D94: =C94*0.93 -> 133501.5
A95: PSE-EP-8SC | B95: Лицензия PSE EP на 8 вызова (реком. до 25 пользователей) на 1г | C95: 209000 | D95: =C95*0.93 -> 194370
A96: PSE-EP-16SC | B96: Лицензия PSE EP на 16 вызова (реком. до 50 пользователей) на 1г | C96: 479600 | D96: =C96*0.93 -> 446028
A97: PSE-EP-24SC | B97: Лицензия PSE EP на 24 вызова (реком. до 75 пользователей) на 1г | C97: 709500 | D97: =C97*0.93 -> 659835
A98: PSE-EP-32SC | B98: Лицензия PSE EP на 32 вызова (реком. до 120 пользователей) на 1г | C98: 906400 | D98: =C98*0.93 -> 842952
A99: PSE-EP-48SC | B99: Лицензия PSE EP на 48 вызова (реком. до 160 пользователей) на 1г | C99: 1418450 | D99: =C99*0.93 -> 1319158.5
A100: PSE-EP-64SC | B100: Лицензия PSE EP на 64 вызова (реком. до 200 пользователей) на 1г | C100: 1890900 | D100: =C100*0.93 -> 1758537
A101: PSE-EP-96SC | B101: Лицензия PSE EP на 96 вызова (реком. до 300 пользователей) на 1г | C101: 3001900 | D101: =C101*0.93 -> 2791767
A102: PSE-EP-128SC | B102: Лицензия PSE EP на 128 вызова (реком. до 400 пользователей) на 1г | C102: 4001800 | D102: =C102*0.93 -> 3721674
A103: PSE-EP-192SC | B103: Лицензия PSE EP на 192 вызова (реком. до 600 пользователей) на 1г | C103: 6002700 | D103: =C103*0.93 -> 5582511
A104: PSE-EP-256SC | B104: Лицензия PSE EP на 256 вызова (реком. до 800 пользователей) на 1г | C104: 8003600 | D104: =C104*0.93 -> 7443348
A105: PSE-EP-512SC | B105: Лицензия PSE EP на 512 вызова (реком. до 1550 пользователей) на 1г | C105: 13612500 | D105: =C105*0.93 -> 12659625
A106: PSE-EP-1024SC | B106: Лицензия PSE EP на 1024 вызова (реком. до 4000 пользователей) на 1г | C106: 25208150 | D106: =C106*0.93 -> 23443580
A107: PSE - Ultimate - годовые лицензии
A108: PSE-UP-4SC | B108: Лицензия PSE UP на 4 вызова (реком. до 10 пользователей) на 1г | C108: 179850 | D108: =C108*0.93 -> 167260.5
A109: PSE-UP-8SC | B109: Лицензия PSE UP на 8 вызова (реком. до 25 пользователей) на 1г | C109: 261800 | D109: =C109*0.93 -> 243474
...

Sheet Сетевое
A1: URL | B1: Артикул | C1: Описание | D1: Цена | E1: Дилер
F2: Status
A3: https://ipmatika.kz/products/lte-routery/ | B3: LTE Роутеры
A4: https://ipmatika.kz/products/lte-routery/wi-tek-wi-lte110-o-v2/ | B4: WI-LTE110-O v2 | C4: WI-LTE110-O Outdoor LTE роутер, Cloud | D4: =IFERROR(VLOOKUP($B4,Подбор[#All],4,0),"") -> 46430 | E4: =IFERROR(VLOOKUP($B4,Подбор[#All],5,0),"") -> 37147.55 | F4: =IFERROR(VLOOKUP($B4,Подбор[#All],19,0),"")
A5: https://ipmatika.kz/products/lte-routery/wi-tek-wi-lte113-o/ | B5: WI-LTE113-O | C5: WI-LTE113-O Внешний LTE роутер | D5: =IFERROR(VLOOKUP($B5,Подбор[#All],4,0),"") -> 159190 | E5: =IFERROR(VLOOKUP($B5,Подбор[#All],5,0),"") -> 127352.77 | F5: =IFERROR(VLOOKUP($B5,Подбор[#All],19,0),"")
A6: https://ipmatika.kz/products/lte-routery/wi-tek-wi-lte115-o-v2/ | B6: WI-LTE115-O v2 | C6: WI-LTE115-O Внешний LTE роутер, Cloud | D6: =IFERROR(VLOOKUP($B6,Подбор[#All],4,0),"") -> 46430 | E6: =IFERROR(VLOOKUP($B6,Подбор[#All],5,0),"") -> 37147.55 | F6: =IFERROR(VLOOKUP($B6,Подбор[#All],19,0),"") -> EOL
A7: https://ipmatika.kz/products/lte-routery/wi-tek-wi-lte117-o-v2/ | B7: WI-LTE117-O v2 | C7: WI-LTE117-O v2 Внешний LTE роутер | D7: =IFERROR(VLOOKUP($B7,Подбор[#All],4,0),"") -> 51740 | E7: =IFERROR(VLOOKUP($B7,Подбор[#All],5,0),"") -> 41390.25 | F7: =IFERROR(VLOOKUP($B7,Подбор[#All],19,0),"")
B8: PON-оборудование | F8: =IFERROR(VLOOKUP($B8,Подбор[#All],19,0),"")
B9: WI-POL308G-P | C9: WI-POL308G-P, управляемый GPON MDU 8*GE PoE + 1*2,5G GPON SC | D9: =IFERROR(VLOOKUP($B9,Подбор[#All],4,0),"") -> 92860 | E9: =IFERROR(VLOOKUP($B9,Подбор[#All],5,0),"") -> 74287.125 | F9: =IFERROR(VLOOKUP($B9,Подбор[#All],19,0),"") -> Под заказ
B10: WI-POL5800-08 | C10: WI-POL5800-08, Управляемый коммутатор GPON OLT 8*GPON SC+4*10G SFP+4*GE | D10: =IFERROR(VLOOKUP($B10,Подбор[#All],4,0),"") -> 1193950 | E10: =IFERROR(VLOOKUP($B10,Подбор[#All],5,0),"") -> 955157.78 | F10: =IFERROR(VLOOKUP($B10,Подбор[#All],19,0),"") -> Под заказ
A11: https://ipmatika.kz/products/wifi-mosty/ | B11: WiFi мосты | F11: =IFERROR(VLOOKUP($B11,Подбор[#All],19,0),"")
A12: https://ipmatika.kz/products/wifi-mosty/wi-tek-wi-cpe110-kit/ | B12: WI-CPE110-KIT | C12: WI-CPE110-KIT комплект из двух преднастроенных точек доступа, 802.11b/g/n, 2.4ГГц, до 300Мбит/с | D12: =IFERROR(VLOOKUP($B12,Подбор[#All],4,0),"") -> 33170 | E12: =IFERROR(VLOOKUP($B12,Подбор[#All],5,0),"") -> 26532.825 | F12: =IFERROR(VLOOKUP($B12,Подбор[#All],19,0),"")
A13: https://ipmatika.kz/products/wifi-mosty/wi-tek-wi-cpe110-kit/ | B13: WI-CPE110-KIT v2 | C13: WI-CPE110-KIT комплект из двух преднастроенных точек доступа, 802.11b/g/n, 2.4ГГц, до 300Мбит/с | D13: =IFERROR(VLOOKUP($B13,Подбор[#All],4,0),"") -> 44000 | E13: =IFERROR(VLOOKUP($B13,Подбор[#All],5,0),"") | F13: =IFERROR(VLOOKUP($B13,Подбор[#All],19,0),"") -> NEW
A14: https://ipmatika.kz/products/wifi-mosty/wi-tek-wi-cpe111-kit-v2/ | B14: WI-CPE111-KIT V2 | C14: WI-CPE111-KIT комплект из двух преднастроенных точек доступа 802.11b/g/n 2,4ГГц до 300Мбит/с, Cloud | D14: =IFERROR(VLOOKUP($B14,Подбор[#All],4,0),"") -> 54390 | E14: =IFERROR(VLOOKUP($B14,Подбор[#All],5,0),"") -> 43511.6 | F14: =IFERROR(VLOOKUP($B14,Подбор[#All],19,0),"") -> EOL
A15: https://ipmatika.kz/products/wifi-mosty/wi-tek-wi-cpe511h-kit/ | B15: WI-CPE511H-KIT | C15: WI-CPE511H-KIT комплект из двух преднастроенных точек доступа, 802.11a/n, 5ГГц, до 900Мбит/с | D15: =IFERROR(VLOOKUP($B15,Подбор[#All],4,0),"") -> 59690 | E15: =IFERROR(VLOOKUP($B15,Подбор[#All],5,0),"") -> 47754.3 | F15: =IFERROR(VLOOKUP($B15,Подбор[#All],19,0),"")
A16: https://ipmatika.kz/products/wifi-mosty/wi-tek-wi-cpe513p-kit-v3/ | B16: WI-CPE513P-KIT v3 | C16: WI-CPE513P-KIT комплект из двух преднастроенных точек доступа 802.11a/n, 5ГГц, 2 LAN, PoE, Cloud | D16: 59260 | E16: 47550 | F16: Акция
A17: https://ipmatika.kz/products/wifi-mosty/wi-tek-wi-cpe515h-kit/ | B17: WI-CPE515H-KIT | C17: WI-CPE515H-KIT комплект из двух преднастроенных точек доступа наружная 802.11a/n 5ГГц до 300Мбит/c | D17: =IFERROR(VLOOKUP($B17,Подбор[#All],4,0),"") -> 91530 | E17: =IFERROR(VLOOKUP($B17,Подбор[#All],5,0),"") -> 73226.45 | F17: =IFERROR(VLOOKUP($B17,Подбор[#All],19,0),"") -> EOL
A18: https://ipmatika.kz/products/wifi-mosty/wi-tek-wi-cpe800-kit-v3/ | B18: WI-CPE800-KIT v3 | C18: WI-CPE800-KIT комплект из двух преднастроенных точек доступа, 802.11a/n, 5ГГц, до 867Мбит/с | D18: =IFERROR(VLOOKUP($B18,Подбор[#All],4,0),"") -> 112760 | E18: =IFERROR(VLOOKUP($B18,Подбор[#All],5,0),"") -> 90205.225 | F18: =IFERROR(VLOOKUP($B18,Подбор[#All],19,0),"") -> NEW
A19: https://ipmatika.kz/products/wifi-mosty/wi-tek-wi-cpe821/ | B19: WI-CPE821 | C19: WI-CPE821, Точка доступа наружная 360гр 802.11a/n 5,8Ггц до 867Мбит/c | D19: =IFERROR(VLOOKUP($B19,Подбор[#All],4,0),"") -> 145920 | E19: =IFERROR(VLOOKUP($B19,Подбор[#All],5,0),"") -> 116738.05 | F19: =IFERROR(VLOOKUP($B19,Подбор[#All],19,0),"")
A20: https://ipmatika.kz/products/wifi-smb/ | B20: WiFi точки доступа | F20: =IFERROR(VLOOKUP($B20,Подбор[#All],19,0),"")
A21: https://ipmatika.kz/products/wifi-smb/wi-tek-wi-ac105p-v2/ | B21: WI-AC105P v2 | C21: WI-AC105P Контроллер WiFi | D21: =IFERROR(VLOOKUP($B21,Подбор[#All],4,0),"") -> 46430 | E21: =IFERROR(VLOOKUP($B21,Подбор[#All],5,0),"") -> 37147.55 | F21: =IFERROR(VLOOKUP($B21,Подбор[#All],19,0),"")
A22: https://ipmatika.kz/products/wifi-smb/wi-tek-wi-ac108p-v2/ | B22: WI-AC108P v2 | C22: WI-AC108P Контроллер WiFi | D22: =IFERROR(VLOOKUP($B22,Подбор[#All],4,0),"") -> 79600 | E22: =IFERROR(VLOOKUP($B22,Подбор[#All],5,0),"") -> 63680.375 | F22: =IFERROR(VLOOKUP($B22,Подбор[#All],19,0),"")
A23: https://ipmatika.kz/products/wifi-smb/wi-tek-wi-ac150/ | B23: WI-AC150 | C23: WI-AC150 Контроллер WiFi | D23: =IFERROR(VLOOKUP($B23,Подбор[#All],4,0),"") -> 66330 | E23: =IFERROR(VLOOKUP($B23,Подбор[#All],5,0),"") -> 53065.65 | F23: =IFERROR(VLOOKUP($B23,Подбор[#All],19,0),"")
A24: https://ipmatika.kz/products/wifi-smb/wi-tek-wi-ac50/ | B24: WI-AC50 | C24: WI-AC50 Контроллер WiFi | D24: =IFERROR(VLOOKUP($B24,Подбор[#All],4,0),"") -> 23220 | E24: =IFERROR(VLOOKUP($B24,Подбор[#All],5,0),"") -> 18573.775 | F24: =IFERROR(VLOOKUP($B24,Подбор[#All],19,0),"") -> EOL
A25: https://ipmatika.kz/products/wifi-smb/wi-tek-wi-ac500/ | B25: WI-AC500 | C25: WI-AC500 Контроллер WiFi | D25: =IFERROR(VLOOKUP($B25,Подбор[#All],4,0),"") -> 331650 | E25: =IFERROR(VLOOKUP($B25,Подбор[#All],5,0),"") -> 265320.27 | F25: =IFERROR(VLOOKUP($B25,Подбор[#All],19,0),"") -> Под заказ
A26: https://ipmatika.kz/products/accessories/wi-tek-wi-aod6/ | B26: WI-AODB6 | C26: WI-AODB6, Антенна всенаправленная двухдиапазонная 2,4/5 ГГц (6dBi), type-N | D26: =IFERROR(VLOOKUP($B26,Подбор[#All],4,0),"") -> 9290 | E26: =IFERROR(VLOOKUP($B26,Подбор[#All],5,0),"") -> 7432.7 | F26: =IFERROR(VLOOKUP($B26,Подбор[#All],19,0),"") -> EOL
A27: https://ipmatika.kz/products/wifi-smb/wi-tek-wi-ap210-lite/ | B27: WI-AP210-Lite | C27: WI-AP210-Lite Точка доступа c поддержкой PoE, Wi-Fi 4 (802.11a/b/g/n) | D27: =IFERROR(VLOOKUP($B27,Подбор[#All],4,0),"") -> 24950 | E27: =IFERROR(VLOOKUP($B27,Подбор[#All],5,0),"") -> 19960 | F27: =IFERROR(VLOOKUP($B27,Подбор[#All],19,0),"")
A28: https://ipmatika.kz/products/wifi-smb/wi-tek-wi-ap215/ | B28: WI-AP215 | C28: WI-AP215 AC750 Двухдиапазонная точка доступа c поддержкой PoE, Wi-Fi 5 (802.11AC) | D28: =IFERROR(VLOOKUP($B28,Подбор[#All],4,0),"") -> 49740 | E28: =IFERROR(VLOOKUP($B28,Подбор[#All],5,0),"") -> 39795.25 | F28: =IFERROR(VLOOKUP($B28,Подбор[#All],19,0),"") -> EOL
A29: https://ipmatika.kz/products/wifi-smb/wi-tek-wi-ap216v2/ | B29: WI-AP216 v2 | C29: WI-AP216 точка доступа Wi-Fi 5 AC1200 серии Lite для установки в помещении | D29: =IFERROR(VLOOKUP($B29,Подбор[#All],4,0),"") -> 25200 | E29: =IFERROR(VLOOKUP($B29,Подбор[#All],5,0),"") -> 20160.8 | F29: =IFERROR(VLOOKUP($B29,Подбор[#All],19,0),"")
A30: https://ipmatika.kz/products/wifi-smb/wi-tek-wi-ap217/ | B30: WI-AP217 | C30: WI-AP217 AC1200 Гигабитная двухдиапазонная точка доступа c поддержкой PoE, Wi-Fi 5 (802.11AC Wave2) | D30: =IFERROR(VLOOKUP($B30,Подбор[#All],4,0),"") -> 69640 | E30: =IFERROR(VLOOKUP($B30,Подбор[#All],5,0),"") -> 55713.35 | F30: =IFERROR(VLOOKUP($B30,Подбор[#All],19,0),"")
A31: https://ipmatika.kz/products/wifi-smb/wi-tek-wi-ap217-lite/ | B31: WI-AP217-Lite | C31: WI-AP217-Lite Гигабитная двухдиапазонная точка доступа c поддержкой PoE, Wi-Fi 5 (802.11AC Wave2) | D31: =IFERROR(VLOOKUP($B31,Подбор[#All],4,0),"") -> 50410 | E31: =IFERROR(VLOOKUP($B31,Подбор[#All],5,0),"") -> 40329.575 | F31: =IFERROR(VLOOKUP($B31,Подбор[#All],19,0),"") -> EOL
A32: https://ipmatika.kz/products/wifi-smb/wi-tek-wi-ap217-lite-v2/ | B32: WI-AP217-Lite v2 | C32: WI-AP217-Lite точка доступа потолочная Wi-Fi 5 (802.11AC), PoE, до 100 клиентов | D32: =IFERROR(VLOOKUP($B32,Подбор[#All],4,0),"") -> 43780 | E32: =IFERROR(VLOOKUP($B32,Подбор[#All],5,0),"") -> 35026.2 | F32: =IFERROR(VLOOKUP($B32,Подбор[#All],19,0),"") -> NEW
... A43: https://ipmatika.kz/products/wifi-smb/wi-tek-wi-ap417P/ | B43: WI-AP417P | C43: WI-AP417P точка доступа Wi-Fi 5 (802.11aс) серии Project для встраивания в стену, PoE, 4GE | D43: =IFERROR(VLOOKUP($B43,Подбор[#All],4,0),"") -> 46430 | E43: =IFERROR(VLOOKUP($B43,Подбор[#All],5,0),"") -> 37147.55 | F43: =IFERROR(VLOOKUP($B43,Подбор[#All],19,0),"") -> EOL
A44: https://ipmatika.kz/products/wifi-smb/wi-tek-wi-ap510/ | B44: WI-AP510 | C44: WI-AP510 AC1200 Внешняя двухдиапазонная точка доступа c поддержкой PoE, Wi-Fi 5 (802.11AC Wave2) | D44: 187140 | E44: 140250 | F44: Акция
A45: https://ipmatika.kz/products/wifi-smb/wi-tek-wi-ap518ax/ | B45: WI-AP518AX | C45: WI-AP518AX Внешняя двухдиапазонная точка доступа c поддержкой PoE, Wi-Fi 6 (802.11AX) | D45: =IFERROR(VLOOKUP($B45,Подбор[#All],4,0),"") -> 514270 | E45: =IFERROR(VLOOKUP($B45,Подбор[#All],5,0),"") -> 411414.3 | F45: =IFERROR(VLOOKUP($B45,Подбор[#All],19,0),"") -> EOL
A46: https://ipmatika.kz/products/wifi-smb/wi-tek-wi-ap520ax-d/ | B46: WI-AP520AX-D | C46: WI-AP520AX-D, внешняя двухдиапазонная точка доступа c поддержкой PoE, Wi-Fi6, SFP | D46: =IFERROR(VLOOKUP($B46,Подбор[#All],4,0),"") -> 212250 | E46: =IFERROR(VLOOKUP($B46,Подбор[#All],5,0),"") -> 169803.7 | F46: =IFERROR(VLOOKUP($B46,Подбор[#All],19,0),"")
A47: https://ipmatika.kz/products/opticheskie-moduli/ | B47: SFP модули | D47: =IFERROR(VLOOKUP($B47,Подбор[#All],4,0),"") | E47: =IFERROR(VLOOKUP($B47,Подбор[#All],5,0),"") | F47: =IFERROR(VLOOKUP($B47,Подбор[#All],19,0),"")
A48: https://ipmatika.kz/products/opticheskie-moduli/wi-sfp10lc-20km/ | B48: WI-SFP10LC-20KM | C48: WI-SFP10LC-20KM, Модуль SFP WDM, дальность до 20км (14dB), комплект 2шт 1310/1550нм | D48: =IFERROR(VLOOKUP($B48,Подбор[#All],4,0),"") -> 13270 | E48: =IFERROR(VLOOKUP($B48,Подбор[#All],5,0),"") -> 10614.725 | F48: =IFERROR(VLOOKUP($B48,Подбор[#All],19,0),"")
A49: https://ipmatika.kz/products/opticheskie-moduli/wi-sfp10lc-3km/ | B49: WI-SFP10LC-3KM | C49: WI-SFP10LC-3KM, Модуль SFP WDM, дальность до 3км (6dB), комплект 2шт 1310/1550нм | D49: =IFERROR(VLOOKUP($B49,Подбор[#All],4,0),"") -> 10620 | E49: =IFERROR(VLOOKUP($B49,Подбор[#All],5,0),"") -> 8493.375 | F49: =IFERROR(VLOOKUP($B49,Подбор[#All],19,0),"")
A50: https://ipmatika.kz/products/opticheskie-moduli/wi-sfp10sc-20km/ | B50: WI-SFP10SC-20KM | C50: WI-SFP10SC-20KM, Модуль SFP WDM, дальность до 20км (14dB), комплект 2шт 1310/1550нм | D50: =IFERROR(VLOOKUP($B50,Подбор[#All],4,0),"") -> 13270 | E50: =IFERROR(VLOOKUP($B50,Подбор[#All],5,0),"") -> 10614.725 | F50: =IFERROR(VLOOKUP($B50,Подбор[#All],19,0),"")
A51: https://ipmatika.kz/products/opticheskie-moduli/wi-sfp10sc-3km/ | B51: WI-SFP10SC-3KM | C51: WI-SFP10SC-3KM, Модуль SFP WDM, дальность до 3км (6dB), комплект 2шт 1310/1550нм | D51: =IFERROR(VLOOKUP($B51,Подбор[#All],4,0),"") -> 11940 | E51: =IFERROR(VLOOKUP($B51,Подбор[#All],5,0),"") -> 9554.05 | F51: =IFERROR(VLOOKUP($B51,Подбор[#All],19,0),"")
A52: https://ipmatika.kz/products/opticheskie-moduli/wi-sfp20-10g-20km/ | B52: WI-SFP20-10G-20KM | C52: WI-SFP20-10G-20KM, Модуль SFP+ дальность до 20км (11dB), 1310нм | D52: =IFERROR(VLOOKUP($B52,Подбор[#All],4,0),"") -> 11940 | E52: =IFERROR(VLOOKUP($B52,Подбор[#All],5,0),"") -> 9554.05 | F52: =IFERROR(VLOOKUP($B52,Подбор[#All],19,0),"")
A53: https://ipmatika.kz/products/opticheskie-moduli/wi-sfp30-10g/ | B53: WI-SFP30-10G | C53: WI-SFP30-10G, Модуль SFP+ с интерфейсом RJ45, до 30м | D53: =IFERROR(VLOOKUP($B53,Подбор[#All],4,0),"") -> 33170 | E53: =IFERROR(VLOOKUP($B53,Подбор[#All],5,0),"") -> 26532.825 | F53: =IFERROR(VLOOKUP($B53,Подбор[#All],19,0),"")
A54: https://ipmatika.kz/products/switch-accessories/tgnet-sfp-10ge-lx-sm1310/ | B54: SFP+-10GE-LX-SM1310 | C54: МодульTG-NET SFP-10GE-LX-SM1310 (комплект 2шт) | D54: 25990 | E54: 20790 | F54: Акция
A55: https://ipmatika.kz/products/opticheskie-moduli/wi-sfp30/ | B55: WI-SFP30 | C55: WI-SFP30, Модуль SFP с интерфейсом RJ45, до 100м | D55: =IFERROR(VLOOKUP($B55,Подбор[#All],4,0),"") -> 9290 | E55: =IFERROR(VLOOKUP($B55,Подбор[#All],5,0),"") -> 7432.7 | F55: =IFERROR(VLOOKUP($B55,Подбор[#All],19,0),"")
A56: https://ipmatika.kz/products/accessories/ | B56: Аксессуары | F56: =IFERROR(VLOOKUP($B56,Подбор[#All],19,0),"")
A57: https://ipmatika.kz/products/accessories/wi-tek-wi-08kit/ | B57: WI-08KIT | C57: WI-08KIT, Комплект кронштейнов для монтажа коммутаторов 19'' | D57: =IFERROR(VLOOKUP($B57,Подбор[#All],4,0),"") -> 3980 | E57: =IFERROR(VLOOKUP($B57,Подбор[#All],5,0),"") -> 3182.025 | F57: =IFERROR(VLOOKUP($B57,Подбор[#All],19,0),"")
A58: https://ipmatika.kz/products/accessories/wi-tek-wi-brkc135/ | B58: WI-BRKC135 | C58: WI-BRKC135, кронштейн для монтажа беспроводных мостов | D58: =IFERROR(VLOOKUP($B58,Подбор[#All],4,0),"") -> 2650 | E58: =IFERROR(VLOOKUP($B58,Подбор[#All],5,0),"") -> 2121.35 | F58: =IFERROR(VLOOKUP($B58,Подбор[#All],19,0),"")
A59: https://ipmatika.kz/products/accessories/wi-tek-wi-pe31e/ | B59: WI-PE31E | C59: WI-PE31E, Повторитель PoE, порты 1FE PoE-in + 2FE PoE-out | D59: =IFERROR(VLOOKUP($B59,Подбор[#All],4,0),"") -> 17910 | E59: =IFERROR(VLOOKUP($B59,Подбор[#All],5,0),"") -> 14331.075 | F59: =IFERROR(VLOOKUP($B59,Подбор[#All],19,0),"")
A60: https://ipmatika.kz/products/accessories/wi-tek-wi-pe51e/ | B60: WI-PE51E | C60: WI-PE51E, Повторитель PoE, порты 1FE PoE-in + 4FE PoE-out + 1FE | D60: =IFERROR(VLOOKUP($B60,Подбор[#All],4,0),"") -> 26540 | E60: =IFERROR(VLOOKUP($B60,Подбор[#All],5,0),"") -> 21229.45 | F60: =IFERROR(VLOOKUP($B60,Подбор[#All],19,0),"")
A61: https://ipmatika.kz/products/accessories/wi-tek-wi-poe11s-48v/ | B61: WI-POE11S-48V | C61: WI-POE11S-48V, Сплиттер PoE, совместим с 802.3af/at ,1FE PoE-in, 1FE out, DC 12В out | D61: =IFERROR(VLOOKUP($B61,Подбор[#All],4,0),"") -> 2920 | E61: =IFERROR(VLOOKUP($B61,Подбор[#All],5,0),"") -> 2336.675 | F61: =IFERROR(VLOOKUP($B61,Подбор[#All],19,0),"")
A62: https://ipmatika.kz/products/accessories/wi-tek-wi-poe21e-o/ | B62: WI-POE21E-O | C62: WI-POE21E-O, Повторитель PoE уличный, 1GE PoE-вход 802.3bt (60Вт), 2GE PoE-выхода 802.3af/at | D62: =IFERROR(VLOOKUP($B62,Подбор[#All],4,0),"") -> 42450 | E62: =IFERROR(VLOOKUP($B62,Подбор[#All],5,0),"") -> 33957.55 | F62: =IFERROR(VLOOKUP($B62,Подбор[#All],19,0),"")
A63: https://ipmatika.kz/products/accessories/wi-tek-wi-poe22e-o/ | B63: WI-POE22E-O | C63: WI-POE22E-O, Повторитель PoE уличный, 1GE PoE-вход 802.3bt (90Вт), 2GE PoE-выхода 802.3af/at/bt | D63: =IFERROR(VLOOKUP($B63,Подбор[#All],4,0),"") -> 55720 | E63: =IFERROR(VLOOKUP($B63,Подбор[#All],5,0),"") -> 44572.275 | F63: =IFERROR(VLOOKUP($B63,Подбор[#All],19,0),"")
A64: https://ipmatika.kz/products/accessories/wi-tek-wi-poe60-24v/ | B64: WI-POE60-24V | C64: WI-POE60-24V, преобразователь PoE Gigabit Ethernet 48В в 24В | D64: =IFERROR(VLOOKUP($B64,Подбор[#All],4,0),"") -> 9290 | E64: =IFERROR(VLOOKUP($B64,Подбор[#All],5,0),"") -> 7432.7 | F64: =IFERROR(VLOOKUP($B64,Подбор[#All],19,0),"")
A65: https://ipmatika.kz/products/accessories/wi-tek-wi-poe90x/ | B65: WI-POE90X | C65: WI-POE90X, преобразователь PoE Gigabit Ethernet 12/24В в 48В | D65: =IFERROR(VLOOKUP($B65,Подбор[#All],4,0),"") -> 19900 | E65: =IFERROR(VLOOKUP($B65,Подбор[#All],5,0),"") -> 15918.1 | F65: =IFERROR(VLOOKUP($B65,Подбор[#All],19,0),"")
B66: Блоки питания | D66: =IFERROR(VLOOKUP($B66,Подбор[#All],4,0),"") | E66: =IFERROR(VLOOKUP($B66,Подбор[#All],5,0),"") | F66: =IFERROR(VLOOKUP($B66,Подбор[#All],19,0),"")
A67: https://ipmatika.kz/products/accessories/wi-tek-wi-dp120w-48v/ | B67: WI-DP120W-48V | C67: WI-DP120W-48V блок питания 48В, 2,5А, 120Вт | D67: =IFERROR(VLOOKUP($B67,Подбор[#All],4,0),"") -> 27190 | E67: =IFERROR(VLOOKUP($B67,Подбор[#All],5,0),"") -> 21755.8 | F67: =IFERROR(VLOOKUP($B67,Подбор[#All],19,0),"") -> NEW
A68: https://ipmatika.kz/products/accessories/wi-tek-wi-dp240w-48v/ | B68: WI-DP240W-48V | C68: WI-DP240W-48V блок питания 48В, 5А, 240Вт | D68: =IFERROR(VLOOKUP($B68,Подбор[#All],4,0),"") -> 46430 | E68: =IFERROR(VLOOKUP($B68,Подбор[#All],5,0),"") -> 37147.55 | F68: =IFERROR(VLOOKUP($B68,Подбор[#All],19,0),"") -> NEW
A69: https://ipmatika.kz/products/accessories/wi-tek-wi-dp30w-12v/ | B69: WI-DP30W-12V | C69: WI-DP30W-12V блок питания 12В, 2.5А, 30Вт | D69: =IFERROR(VLOOKUP($B69,Подбор[#All],4,0),"") -> 10620 | E69: =IFERROR(VLOOKUP($B69,Подбор[#All],5,0),"") -> 8493.375 | F69: =IFERROR(VLOOKUP($B69,Подбор[#All],19,0),"") -> NEW
A70: https://ipmatika.kz/products/accessories/wi-tek-wi-dp480w-48v/ | B70: WI-DP480W-48V | C70: WI-DP480W-48V блок питания 48В, 10А, 480Вт | D70: =IFERROR(VLOOKUP($B70,Подбор[#All],4,0),"") -> 92860 | E70: =IFERROR(VLOOKUP($B70,Подбор[#All],5,0),"") -> 74287.125 | F70: =IFERROR(VLOOKUP($B70,Подбор[#All],19,0),"") -> NEW
A71: https://ipmatika.kz/products/accessories/wi-tek-wi-dp75w-48v/ | B71: WI-DP75W-48V | C71: WI-DP75W-48V блок питания 48В, 1,6А, 76Вт | D71: =IFERROR(VLOOKUP($B71,Подбор[#All],4,0),"") -> 19900 | E71: =IFERROR(VLOOKUP($B71,Подбор[#All],5,0),"") -> 15918.1 | F71: =IFERROR(VLOOKUP($B71,Подбор[#All],19,0),"") -> NEW
B72: Инжекторы PoE | D72: =IFERROR(VLOOKUP($B72,Подбор[#All],4,0),"") | E72: =IFERROR(VLOOKUP($B72,Подбор[#All],5,0),"") | F72: =IFERROR(VLOOKUP($B72,Подбор[#All],19,0),"")
A73: https://ipmatika.kz/products/accessories/wi-tek-wi-poe31-24v/ | B73: WI-POE31-24V | C73: WI-POE31-24V, Инжектор 100Base-T, PoE 24В | D73: =IFERROR(VLOOKUP($B73,Подбор[#All],4,0),"") -> 5700 | E73: =IFERROR(VLOOKUP($B73,Подбор[#All],5,0),"") -> 4561.7 | F73: =IFERROR(VLOOKUP($B73,Подбор[#All],19,0),"")
A74: https://ipmatika.kz/products/accessories/wi-tek-wi-poe31-48v/ | B74: WI-POE31-48V | C74: WI-POE31-48V, Инжектор 100Base-T 30Вт совместим с 802.3af/at , 48В | D74: =IFERROR(VLOOKUP($B74,Подбор[#All],4,0),"") -> 5700 | E74: =IFERROR(VLOOKUP($B74,Подбор[#All],5,0),"") -> 4561.7 | F74: =IFERROR(VLOOKUP($B74,Подбор[#All],19,0),"")
A75: https://ipmatika.kz/products/accessories/wi-tek-wi-poe31-48v/ | B75: WI-POE31-48V-4578 | C75: WI-POE31-48V, Инжектор 100Base-T 30Вт, PIN 4,5+/7,8-, 48В | D75: =IFERROR(VLOOKUP($B75,Подбор[#All],4,0),"") | E75: =IFERROR(VLOOKUP($B75,Подбор[#All],5,0),"") | F75: =IFERROR(VLOOKUP($B75,Подбор[#All],19,0),"")
A76: https://ipmatika.kz/products/accessories/wi-tek-wi-poe51-24v/ | B76: WI-POE51-24V | C76: WI-POE51-24V, Инжектор 1000Base-T, PoE 24В | D76: =IFERROR(VLOOKUP($B76,Подбор[#All],4,0),"") -> 11270 | E76: =IFERROR(VLOOKUP($B76,Подбор[#All],5,0),"") -> 9019.725 | F76: =IFERROR(VLOOKUP($B76,Подбор[#All],19,0),"")
A77: https://ipmatika.kz/products/accessories/wi-tek-wi-poe51-48v/ | B77: WI-POE51-48V | C77: WI-POE51-48V, Инжектор 1000Base-T 30Вт совместим с 802.3af/at , 48В | D77: =IFERROR(VLOOKUP($B77,Подбор[#All],4,0),"") -> 11270 | E77: =IFERROR(VLOOKUP($B77,Подбор[#All],5,0),"") -> 9019.725 | F77: =IFERROR(VLOOKUP($B77,Подбор[#All],19,0),"") -> EOL
A78: https://ipmatika.kz/products/accessories/wi-tek-wi-poe51-48v/ | B78: WI-POE51-48V v2 | C78: WI-POE51-48V, Инжектор 1000Base-T 30Вт совместим с 802.3af/at , 48В, v2 | D78: =IFERROR(VLOOKUP($B78,Подбор[#All],4,0),"") -> 11270 | E78: =IFERROR(VLOOKUP($B78,Подбор[#All],5,0),"") -> 9019.725 | F78: =IFERROR(VLOOKUP($B78,Подбор[#All],19,0),"")
A79: https://ipmatika.kz/products/accessories/wi-tek-wi-poe55-48v-60w/ | B79: WI-POE55-48V-60W | C79: WI-POE55-48V-60W, Инжектор 1000Base-T 60Вт совместим с 802.3af/at/bt, 48В | D79: =IFERROR(VLOOKUP($B79,Подбор[#All],4,0),"") -> 17250 | E79: =IFERROR(VLOOKUP($B79,Подбор[#All],5,0),"") -> 13796.75 | F79: =IFERROR(VLOOKUP($B79,Подбор[#All],19,0),"")
A80: https://ipmatika.kz/products/accessories/wi-poe58-bt%20v2/ | B80: WI-POE58-BT v2 | C80: WI-POE58-BT инжектор PoE 2.5GE BT + 2.5GE Uplink | D80: =IFERROR(VLOOKUP($B80,Подбор[#All],4,0),"") | E80: =IFERROR(VLOOKUP($B80,Подбор[#All],5,0),"") | F80: =IFERROR(VLOOKUP($B80,Подбор[#All],19,0),"")
A81: https://ipmatika.kz/products/accessories/wi-poe58-bt-l-dc/ | B81: WI-POE58-BT-I-DC | C81: WI-POE58-BT-I-DC Промышленный PoE инжектор 1GE BT+1GE Uplink, DC 12-57В | D81: =IFERROR(VLOOKUP($B81,Подбор[#All],4,0),"") -> 53060 | E81: =IFERROR(VLOOKUP($B81,Подбор[#All],5,0),"") -> 42450.925 | F81: =IFERROR(VLOOKUP($B81,Подбор[#All],19,0),"") -> NEW
A82: https://ipmatika.kz/products/ups/wi-tek-wi-ps302g-ups/ | B82: WI-PS302G-UPS | C82: WI-PS302G-UPS, Инжектор с функцией UPS, 1-1000Base-T PoE, 1-1000Base-T, AC/DC in, DC out 24/48В | D82: =IFERROR(VLOOKUP($B82,Подбор[#All],4,0),"") -> 23880 | E82: =IFERROR(VLOOKUP($B82,Подбор[#All],5,0),"") -> 19100.125 | F82: =IFERROR(VLOOKUP($B82,Подбор[#All],19,0),"") -> EOL
B83: Промышленные SFP модули | D83: =IFERROR(VLOOKUP($B83,Подбор[#All],4,0),"") | E83: =IFERROR(VLOOKUP($B83,Подбор[#All],5,0),"") | F83: =IFERROR(VLOOKUP($B83,Подбор[#All],19,0),"")
A84: https://ipmatika.kz/products/opticheskie-moduli/wi-sfp10l-10g-20km-l/ | B84: WI-SFP10L-10G-20KM-I | C84: WI-SFP10L-10G-20KM-I, промышленный модуль SFP+ с разъемом LC, до 20км | D84: =IFERROR(VLOOKUP($B84,Подбор[#All],4,0),"") | E84: =IFERROR(VLOOKUP($B84,Подбор[#All],5,0),"") | F84: =IFERROR(VLOOKUP($B84,Подбор[#All],19,0),"")
A85: https://ipmatika.kz/products/opticheskie-moduli/wi-sfp10l-25g-20km-i/ | B85: WI-SFP10L-2.5G-20KM-I | C85: WI-SFP10L-2.5G-20KM-I, промышленный модуль SFP+ с разъемом LC, до 20км, 2 шт. | D85: =IFERROR(VLOOKUP($B85,Подбор[#All],4,0),"") -> 22550 | E85: =IFERROR(VLOOKUP($B85,Подбор[#All],5,0),"") -> 18039.45 | F85: =IFERROR(VLOOKUP($B85,Подбор[#All],19,0),"")
A86: https://ipmatika.kz/products/opticheskie-moduli/wi-sfp10l-20km-i/ | B86: WI-SFP10L-20KM-I | C86: WI-SFP10L-20KM-I, промышленный модуль SFP+ с разъемом LC, до 20км, 2 шт. | D86: =IFERROR(VLOOKUP($B86,Подбор[#All],4,0),"") -> 15920 | E86: =IFERROR(VLOOKUP($B86,Подбор[#All],5,0),"") -> 12736.075 | F86: =IFERROR(VLOOKUP($B86,Подбор[#All],19,0),"")
A87: https://ipmatika.kz/products/opticheskie-moduli/wi-sfp10l-3km-i/ | B87: WI-SFP10L-3KM-I | C87: WI-SFP10L-3KM-I, промышленный модуль SFP с разъемом LC, до 3км, 2 шт. | D87: =IFERROR(VLOOKUP($B87,Подбор[#All],4,0),"") -> 13270 | E87: =IFERROR(VLOOKUP($B87,Подбор[#All],5,0),"") -> 10614.725 | F87: =IFERROR(VLOOKUP($B87,Подбор[#All],19,0),"")
A88: https://ipmatika.kz/products/opticheskie-moduli/wi-sfp10s-20km-i/ | B88: WI-SFP10S-20KM-I | C88: WI-SFP10S-20KM-I, промышленный модуль SFP с разъемом SC, до 20км, 2шт. | D88: =IFERROR(VLOOKUP($B88,Подбор[#All],4,0),"") -> 15920 | E88: =IFERROR(VLOOKUP($B88,Подбор[#All],5,0),"") -> 12736.075 | F88: =IFERROR(VLOOKUP($B88,Подбор[#All],19,0),"")
A89: https://ipmatika.kz/products/opticheskie-moduli/wi-sfp10s-3km-i/ | B89: WI-SFP10S-3KM-I | C89: WI-SFP10S-3KM-I, промышленный модуль SFP с разъемом SC, до 3км, 2шт. | D89: =IFERROR(VLOOKUP($B89,Подбор[#All],4,0),"") -> 13270 | E89: =IFERROR(VLOOKUP($B89,Подбор[#All],5,0),"") -> 10614.725 | F89: =IFERROR(VLOOKUP($B89,Подбор[#All],19,0),"")
A90: https://ipmatika.kz/products/opticheskie-moduli/wi-sfp20l-25g-20km-i/ | B90: WI-SFP20L-2.5G-20KM-I | C90: WI-SFP20L-2.5G-20KM-I, промышленный модуль SFP+ с разъемом LC, до 20км | D90: =IFERROR(VLOOKUP($B90,Подбор[#All],4,0),"") -> 10620 | E90: =IFERROR(VLOOKUP($B90,Подбор[#All],5,0),"") -> 8493.375 | F90: =IFERROR(VLOOKUP($B90,Подбор[#All],19,0),"")
A91: https://ipmatika.kz/products/opticheskie-moduli/wi-sfp20l-20km-i/ | B91: WI-SFP20L-20KM-I | C91: WI-SFP20L-20KM-I, промышленный модуль SFP с разъемом LC, до 20км | D91: =IFERROR(VLOOKUP($B91,Подбор[#All],4,0),"") | E91: =IFERROR(VLOOKUP($B91,Подбор[#All],5,0),"") | F91: =IFERROR(VLOOKUP($B91,Подбор[#All],19,0),"")
A92: https://ipmatika.kz/products/opticheskie-moduli/wi-sfp21l-550-i/ | B92: WI-SFP21L-550-I | C92: WI-SFP21L-550-I, промышленный модуль SFP с разъемом LC, до 550м | D92: =IFERROR(VLOOKUP($B92,Подбор[#All],4,0),"") -> 7960 | E92: =IFERROR(VLOOKUP($B92,Подбор[#All],5,0),"") -> 6364.05 | F92: =IFERROR(VLOOKUP($B92,Подбор[#All],19,0),"")
A93: https://ipmatika.kz/products/opticheskie-moduli/wi-sfp30-10g-I/ | B93: WI-SFP30-10G-I | C93: WI-SFP30-10G-I, промышленный модуль SFP+ с интерфейсом RJ45, до 100м | D93: =IFERROR(VLOOKUP($B93,Подбор[#All],4,0),"") -> 43780 | E93: =IFERROR(VLOOKUP($B93,Подбор[#All],5,0),"") -> 35026.2 | F93: =IFERROR(VLOOKUP($B93,Подбор[#All],19,0),"")
A94: https://ipmatika.kz/products/opticheskie-moduli/wi-sfp30-i/ | B94: WI-SFP30-I | C94: WI-SFP30-I, промышленный модуль SFP с интерфейсом RJ45, до 100м | D94: =IFERROR(VLOOKUP($B94,Подбор[#All],4,0),"") -> 13270 | E94: =IFERROR(VLOOKUP($B94,Подбор[#All],5,0),"") -> 10614.725 | F94: =IFERROR(VLOOKUP($B94,Подбор[#All],19,0),"")
B95: Промышленные SFP модули | D95: =IFERROR(VLOOKUP($B95,Подбор[#All],4,0),"") | E95: =IFERROR(VLOOKUP($B95,Подбор[#All],5,0),"") | F95: =IFERROR(VLOOKUP($B95,Подбор[#All],19,0),"")
A96: https://ipmatika.kz/products/accessories/wi-tek-wi-spd10kv-poe/ | B96: WI-SPD10KV-POE | C96: WI-SPD10KV-POE устройство грозозащиты Gigabit Ethernet с PoE на DIN-рейку | D96: =IFERROR(VLOOKUP($B96,Подбор[#All],4,0),"") -> 6630 | E96: =IFERROR(VLOOKUP($B96,Подбор[#All],5,0),"") -> 5303.375 | F96: =IFERROR(VLOOKUP($B96,Подбор[#All],19,0),"") -> NEW
A97: https://ipmatika.kz/products/accessories/wi-tek-wi-spd10kv-poe-a/ | B97: WI-SPD10KV-POE-A | C97: WI-SPD10KV-POE-A устройство грозозащиты Gigabit Ethernet с PoE | D97: =IFERROR(VLOOKUP($B97,Подбор[#All],4,0),"") -> 7030 | E97: =IFERROR(VLOOKUP($B97,Подбор[#All],5,0),"") -> 5622.375 | F97: =IFERROR(VLOOKUP($B97,Подбор[#All],19,0),"") -> NEW
A98: https://ipmatika.kz/products/kommutatory-poe/ | B98: Коммутаторы PoE | F98: =IFERROR(VLOOKUP($B98,Подбор[#All],19,0),"")
A99: https://ipmatika.kz/products/nastraivaemye-easy-smart/ | B99: Настраиваемые PoE-коммутаторы 100M/1000M серии Easy Smart | D99: =IFERROR(VLOOKUP($B99,Подбор[#All],4,0),"") | E99: =IFERROR(VLOOKUP($B99,Подбор[#All],5,0),"") | F99: =IFERROR(VLOOKUP($B99,Подбор[#All],19,0),"")
A100: https://ipmatika.kz/products/nastraivaemye-easy-smart/wi-tek-wi-pces206/ | B100: WI-PCES206 | C100: WI-PCES206, настраиваемый PoE 60Вт, порты 4FE PoE + 2FE, Easy Smart | D100: =IFERROR(VLOOKUP($B100,Подбор[#All],4,0),"") -> 19900 | E100: =IFERROR(VLOOKUP($B100,Подбор[#All],5,0),"") -> 15918.1 | F100: =IFERROR(VLOOKUP($B100,Подбор[#All],19,0),"")
A101: https://ipmatika.kz/products/nastraivaemye-easy-smart/wi-tek-wi-pces210g/ | B101: WI-PCES210G | C101: WI-PCES210G, настраиваемый PoE 100Вт, порты 8FE PoE + 2GE, Easy Smart | D101: =IFERROR(VLOOKUP($B101,Подбор[#All],4,0),"") -> 35820 | E101: =IFERROR(VLOOKUP($B101,Подбор[#All],5,0),"") -> 28654.175 | F101: =IFERROR(VLOOKUP($B101,Подбор[#All],19,0),"")
A102: https://ipmatika.kz/products/nastraivaemye-easy-smart/wi-tek-wi-pces218gf/ | B102: WI-PCES218GF | C102: WI-PCES218GF, настраиваемый PoE 250Вт, порты 16FE PoE + 2SFP, Easy Smart | D102: =IFERROR(VLOOKUP($B102,Подбор[#All],4,0),"") -> 92860 | E102: =IFERROR(VLOOKUP($B102,Подбор[#All],5,0),"") -> 74287.125 | F102: =IFERROR(VLOOKUP($B102,Подбор[#All],19,0),"")
A103: https://ipmatika.kz/products/nastraivaemye-easy-smart/wi-tek-wi-pces226gf/ | B103: WI-PCES226GF | C103: WI-PCES226GF, настраиваемый PoE 280Вт, порты 24FE PoE + 2Combo SFP, Easy Smart | D103: =IFERROR(VLOOKUP($B103,Подбор[#All],4,0),"") -> 118070 | E103: =IFERROR(VLOOKUP($B103,Подбор[#All],5,0),"") -> 94455.9 | F103: =IFERROR(VLOOKUP($B103,Подбор[#All],19,0),"")
A104: https://ipmatika.kz/products/nastraivaemye-easy-smart/wi-tek-wi-pces306g/ | B104: WI-PCES306G | C104: WI-PCES306G настраиваемый PoE 60Вт, порты 4 PoE GE + 2GE, Easy Smart | D104: =IFERROR(VLOOKUP($B104,Подбор[#All],4,0),"") -> 34490 | E104: =IFERROR(VLOOKUP($B104,Подбор[#All],5,0),"") -> 27593.5 | F104: =IFERROR(VLOOKUP($B104,Подбор[#All],19,0),"") -> EOL
A105: https://ipmatika.kz/products/nastraivaemye-easy-smart/wi-tek-wi-pces306g-v2/ | B105: WI-PCES306G v2 | C105: WI-PCES306G, настраиваемый PoE 60Вт, порты 4 PoE GE + 2GE, Easy Smart | D105: =IFERROR(VLOOKUP($B105,Подбор[#All],4,0),"") -> 30510 | E105: =IFERROR(VLOOKUP($B105,Подбор[#All],5,0),"") -> 24411.475 | F105: =IFERROR(VLOOKUP($B105,Подбор[#All],19,0),"")
A106: https://ipmatika.kz/products/nastraivaemye-easy-smart/wi-tek-wi-pces306gf/ | B106: WI-PCES306GF | C106: WI-PCES306GF настраиваемый PoE 60Вт, порты 4 PoE GE + 1GE + 1SFP, Easy Smart | D106: =IFERROR(VLOOKUP($B106,Подбор[#All],4,0),"") -> 35820 | E106: =IFERROR(VLOOKUP($B106,Подбор[#All],5,0),"") -> 28654.175 | F106: =IFERROR(VLOOKUP($B106,Подбор[#All],19,0),"") -> EOL
A107: https://ipmatika.kz/products/nastraivaemye-easy-smart/wi-tek-wi-pces308gf/ | B107: WI-PCES308GF | C107: WI-PCES308GF настраиваемый PoE 60Вт, порты 8 PoE GE + 1 GE + 1 SFP, Easy Smart | D107: =IFERROR(VLOOKUP($B107,Подбор[#All],4,0),"") -> 55720 | E107: =IFERROR(VLOOKUP($B107,Подбор[#All],5,0),"") -> 44572.275 | F107: =IFERROR(VLOOKUP($B107,Подбор[#All],19,0),"") -> EOL
A108: https://ipmatika.kz/products/nastraivaemye-easy-smart/wi-tek-wi-pces310g/ | B108: WI-PCES310G | C108: WI-PCES310G настраиваемый PoE 110Вт, порты 8 PoE GE + 2 GE | D108: =IFERROR(VLOOKUP($B108,Подбор[#All],4,0),"") -> 53060 | E108: =IFERROR(VLOOKUP($B108,Подбор[#All],5,0),"") -> 42450.925 | F108: =IFERROR(VLOOKUP($B108,Подбор[#All],19,0),"")
A109: https://ipmatika.kz/products/nastraivaemye-easy-smart/wi-tek-wi-pces310gf-v2/ | B109: WI-PCES310GF v2 | C109: WI-PCES310GF, настраиваемый PoE 120Вт, порты 8 PoE GE + 2 SFP, Easy Smart | D109: =IFERROR(VLOOKUP($B109,Подбор[#All],4,0),"") -> 57040 | E109: =IFERROR(VLOOKUP($B109,Подбор[#All],5,0),"") -> 45632.95 | F109: =IFERROR(VLOOKUP($B109,Подбор[#All],19,0),"")
A110: https://ipmatika.kz/products/nastraivaemye-easy-smart/wi-tek-wi-pces318gf-v2/ | B110: WI-PCES318GF v2 | C110: WI-PCES318GF, настраиваемый PoE 250Вт, порты 16 PoE GE + 2 SFP, Easy Smart | D110: =IFERROR(VLOOKUP($B110,Подбор[#All],4,0),"") -> 130000 | E110: =IFERROR(VLOOKUP($B110,Подбор[#All],5,0),"") -> 104001.98 | F110: =IFERROR(VLOOKUP($B110,Подбор[#All],19,0),"")
...

Sheet Fanvil
A1: URL | B1: Артикул | C1: Описание | D1: KZ РРЦ | E1: Цена Сайт | F1: Status
A2: https://ipmatika.kz/products/2-wire-shlyuzy/ | B2: 2-Wire коммутаторы | F2: =IFERROR(VLOOKUP($B2,Подбор[#All],19,0),"")
A3: https://ipmatika.kz/products/2-wire-shlyuzy/fanvil-pn1/ | B3: PN1 | C3: PN1, SIP-шлюз для подключения IP-телефонов по двухжильному проводу | D3: =IFERROR(VLOOKUP($B3,Подбор[#All],4,0),"") -> 94310 | E3: =D3*0.93 -> 87708.3 | F3: =IFERROR(VLOOKUP($B3,Подбор[#All],19,0),"")
A4: https://ipmatika.kz/products/2-wire-shlyuzy/fanvil-pn24/ | B4: PN24 | C4: PN24, SIP-шлюз для подключения IP-телефонов по двухжильному проводу | D4: =IFERROR(VLOOKUP($B4,Подбор[#All],4,0),"") -> 183960 | E4: =D4*0.93 -> 171082.8 | F4: =IFERROR(VLOOKUP($B4,Подбор[#All],19,0),"")
A5: https://ipmatika.kz/products/2-wire-shlyuzy/fanvil-pn8/ | B5: PN8 | C5: PN8, SIP-шлюз для подключения IP-телефонов по двухжильному проводу | D5: =IFERROR(VLOOKUP($B5,Подбор[#All],4,0),"") -> 98110 | E5: =D5*0.93 -> 91242.3 | F5: =IFERROR(VLOOKUP($B5,Подбор[#All],19,0),"")
A6: https://ipmatika.kz/products/roip-shlyuzy/ | B6: RoIP-шлюзы | E6: =D6*0.93 -> 0 | F6: =IFERROR(VLOOKUP($B6,Подбор[#All],19,0),"")
A7: https://ipmatika.kz/products/roip-shlyuzy/W712/ | B7: LW712 | C7: RoIP-шлюз Linkvil W712 | D7: =IFERROR(VLOOKUP($B7,Подбор[#All],4,0),"") -> 319940 | E7: =D7*0.93 -> 297544.2 | F7: =IFERROR(VLOOKUP($B7,Подбор[#All],19,0),"")
A8: https://ipmatika.kz/products/voip-fxs-fxo/ | B8: VoIP-шлюзы FXS/FXO | E8: =D8*0.93 -> 0 | F8: =IFERROR(VLOOKUP($B8,Подбор[#All],19,0),"")
A9: https://ipmatika.kz/products/voip-fxs-fxo/GA10/ | B9: GA10 | C9: VoIP-шлюз Fanvil GA10, 1*FXS | E9: =D9*0.93 -> 0 | F9: =IFERROR(VLOOKUP($B9,Подбор[#All],19,0),"")
A10: https://ipmatika.kz/products/sip-opoveshchenie/ | B10: SIP-колонки Fanvil | E10: =D10*0.93 -> 0 | F10: =IFERROR(VLOOKUP($B10,Подбор[#All],19,0),"")
A11: https://ipmatika.kz/products/sip-opoveshchenie/Fanvil-A201/ | B11: A201 | C11: Fanvil A201, SIP-громкоговоритель, PoE, встраиваемый | D11: =IFERROR(VLOOKUP($B11,Подбор[#All],4,0),"") -> 88240 | E11: =D11*0.93 -> 82063.2 | F11: =IFERROR(VLOOKUP($B11,Подбор[#All],19,0),"")
A12: https://ipmatika.kz/products/sip-opoveshchenie/Fanvil-A212/ | B12: A212W | C12: Fanvil A212, SIP-громкоговоритель, PoE, настенный, белый | D12: =IFERROR(VLOOKUP($B12,Подбор[#All],4,0),"") -> 110310 | E12: =D12*0.93 -> 102588.3 | F12: =IFERROR(VLOOKUP($B12,Подбор[#All],19,0),"")
A13: https://ipmatika.kz/products/sip-opoveshchenie/Fanvil-A212/ | B13: A212B | C13: Fanvil A212, SIP-громкоговоритель, PoE, настенный, черный | D13: =IFERROR(VLOOKUP($B13,Подбор[#All],4,0),"") -> 110310 | E13: =D13*0.93 -> 102588.3 | F13: =IFERROR(VLOOKUP($B13,Подбор[#All],19,0),"")
A14: https://ipmatika.kz/products/sip-opoveshchenie/Fanvil-A233/ | B14: A233 | C14: Fanvil A233, SIP-громкоговоритель, PoE, рупорный, уличный | D14: =IFERROR(VLOOKUP($B14,Подбор[#All],4,0),"") -> 155730 | E14: =D14*0.93 -> 144828.9 | F14: =IFERROR(VLOOKUP($B14,Подбор[#All],19,0),"")
A15: https://ipmatika.kz/products/sip-opoveshchenie/Fanvil-FH-S01/ | B15: FH-S01 | C15: Fanvil FH-S01, SIP-громкоговоритель, PoE, встраиваемый | D15: =IFERROR(VLOOKUP($B15,Подбор[#All],4,0),"") -> 142750 | E15: =D15*0.93 -> 132757.5 | F15: =IFERROR(VLOOKUP($B15,Подбор[#All],19,0),"")
A16: https://ipmatika.kz/products/wifi-telefony/ | B16: Wi-Fi-телефоны | F16: =IFERROR(VLOOKUP($B16,Подбор[#All],19,0),"")
A17: https://ipmatika.kz/products/wifi-telefony/Linkvil-W610W/ | B17: FLW610W | C17: (Linkvil) W610W, цветной экран, б/п, Wi-Fi 2,4G/5G | D17: =IFERROR(VLOOKUP($B17,Подбор[#All],4,0),"") -> 61660 | E17: =D17*0.93 -> 57343.8 | F17: =IFERROR(VLOOKUP($B17,Подбор[#All],19,0),"")
A18: https://ipmatika.kz/products/wifi-telefony/Linkvil-W611W/ | B18: FLW611W | C18: (Linkvil) W611W, цветной экран, IP67, б/п, Wi-Fi 2,4G/5G | D18: =IFERROR(VLOOKUP($B18,Подбор[#All],4,0),"") -> 120510 | E18: =D18*0.93 -> 112074.3 | F18: =IFERROR(VLOOKUP($B18,Подбор[#All],19,0),"")
A19: https://ipmatika.kz/products/konsoli-monitoringa-i-opoveshcheniya/ | B19: Консоли мониторинга и управления | F19: =IFERROR(VLOOKUP($B19,Подбор[#All],19,0),"")
A20: https://ipmatika.kz/products/konsoli-monitoringa-i-opoveshcheniya/Fanvil-A320/ | B20: A320 | C20: A320, цветной экран, 20 аккаунтов, Android, камера | D20: =IFERROR(VLOOKUP($B20,Подбор[#All],4,0),"") -> 324440 | E20: =D20*0.93 -> 301729.2 | F20: =IFERROR(VLOOKUP($B20,Подбор[#All],19,0),"")
A21: https://ipmatika.kz/products/konsoli-monitoringa-i-opoveshcheniya/Fanvil-A320/ | B21: A320white | C21: A320, цветной экран, 20 аккаунтов, Android, камера, белый | D21: =IFERROR(VLOOKUP($B21,Подбор[#All],4,0),"") -> 324440 | E21: =D21*0.93 -> 301729.2 | F21: =IFERROR(VLOOKUP($B21,Подбор[#All],19,0),"")
A22: https://ipmatika.kz/products/konsoli-monitoringa-i-opoveshcheniya/Fanvil-A320i/ | B22: A320i | C22: A320i, цветной экран, 20 аккаунтов, Android, камера | D22: =IFERROR(VLOOKUP($B22,Подбор[#All],4,0),"") -> 480170 | E22: =D22*0.93 -> 446558.1 | F22: =IFERROR(VLOOKUP($B22,Подбор[#All],19,0),"")
A23: https://ipmatika.kz/products/konsoli-monitoringa-i-opoveshcheniya/Fanvil-A320i/ | B23: A320iwhite | C23: A320i, цветной экран, 20 аккаунтов, Android, камера, белый | D23: =IFERROR(VLOOKUP($B23,Подбор[#All],4,0),"") -> 480170 | E23: =D23*0.93 -> 446558.1 | F23: =IFERROR(VLOOKUP($B23,Подбор[#All],19,0),"")
A24: https://ipmatika.kz/products/konsoli-monitoringa-i-opoveshcheniya/Fanvil-X210i/ | B24: X210iO | C24: Fanvil X210i, цветной экран, 20 аккаунтов | D24: =IFERROR(VLOOKUP($B24,Подбор[#All],4,0),"") | F24: =IFERROR(VLOOKUP($B24,Подбор[#All],19,0),"")
A25: https://ipmatika.kz/products/konsoli-monitoringa-i-opoveshcheniya/Fanvil-X210i/ | B25: X210 | C25: X210, цветной экран, 20 аккаунтов | D25: =IFERROR(VLOOKUP($B25,Подбор[#All],4,0),"") -> 106240 | E25: =D25*0.93 -> 98803.2 | F25: =IFERROR(VLOOKUP($B25,Подбор[#All],19,0),"")
A26: https://ipmatika.kz/products/konsoli-monitoringa-i-opoveshcheniya/Fanvil-X210i/ | B26: X210i | C26: X210i, цветной экран, 20 аккаунтов | D26: =IFERROR(VLOOKUP($B26,Подбор[#All],4,0),"") -> 285510 | E26: =D26*0.93 -> 265524.3 | F26: =IFERROR(VLOOKUP($B26,Подбор[#All],19,0),"")
A27: https://ipmatika.kz/products/konsoli-monitoringa-i-opoveshcheniya/X5UR/ | B27: X5U | C27: X5U, красный, 16 аккаунтов, 2 цветных ЖК-экрана, PoE | D27: =IFERROR(VLOOKUP($B27,Подбор[#All],4,0),"") | F27: =IFERROR(VLOOKUP($B27,Подбор[#All],19,0),"")
A28: https://ipmatika.kz/products/hotel-phone/ | B28: Отельные телефоны | F28: =IFERROR(VLOOKUP($B28,Подбор[#All],19,0),"")
A29: https://ipmatika.kz/products/hotel-phone/Fanvil-H1-2023/ | B29: FH1PBPSU | C29: H1 отельный, 2 аккаунта, без экрана, PoE, б/п | D29: =IFERROR(VLOOKUP($B29,Подбор[#All],4,0),"") -> 29120 | E29: =D29*0.93 -> 27081.6 | F29: =IFERROR(VLOOKUP($B29,Подбор[#All],19,0),"")
A30: https://ipmatika.kz/products/hotel-phone/fanvil-h1-2-wire/ | B30: FH12WIRE | C30: H1-2 Wire отельный, 2 аккаунта, без экрана, б/п | D30: =IFERROR(VLOOKUP($B30,Подбор[#All],4,0),"") -> 29120 | E30: =D30*0.93 -> 27081.6 | F30: =IFERROR(VLOOKUP($B30,Подбор[#All],19,0),"")
A31: https://ipmatika.kz/products/hotel-phone/H2UW/ | B31: FH2UPW | C31: H2U отельный, белый, 2 аккаунта, PoE, без б/п | D31: =IFERROR(VLOOKUP($B31,Подбор[#All],4,0),"") -> 23830 | E31: =D31*0.93 -> 22161.9 | F31: =IFERROR(VLOOKUP($B31,Подбор[#All],19,0),"")
A32: https://ipmatika.kz/products/vnutrennie-sip-paneli/H2URI/ | B32: FH2UPR | C32: H2U отельный, красный, 2 аккаунта, PoE, без б/п | D32: =IFERROR(VLOOKUP($B32,Подбор[#All],4,0),"") -> 34410 | E32: =D32*0.93 -> 32001.3 | F32: =IFERROR(VLOOKUP($B32,Подбор[#All],19,0),"")
A33: https://ipmatika.kz/products/hotel-phone/H2UB/ | B33: FH2UPB | C33: H2U отельный, чёрный, 2 аккаунта, PoE, без б/п | D33: =IFERROR(VLOOKUP($B33,Подбор[#All],4,0),"") -> 23830 | E33: =D33*0.93 -> 22161.9 | F33: =IFERROR(VLOOKUP($B33,Подбор[#All],19,0),"")
A34: https://ipmatika.kz/products/hotel-phone/Fanvil-H3/ | B34: FH3PB sale | C34: H3 отельный, 2 аккаунта, без экрана, PoE, б/п | D34: 31710 | E34: =D34*0.93 -> 29490.3 | F34: Акция
A35: https://ipmatika.kz/products/hotel-phone/Fanvil-H3/ | B35: FH3PPSUB | C35: H3 отельный, 2 аккаунта, без экрана, PoE, б/п | D35: =IFERROR(VLOOKUP($B35,Подбор[#All],4,0),"") -> 25330 | E35: =D35*0.93 -> 23556.9 | F35: =IFERROR(VLOOKUP($B35,Подбор[#All],19,0),"") -> EOL
A36: https://ipmatika.kz/products/hotel-phone/Fanvil-H3W/ | B36: FH3PPSUW | C36: H3 отельный, белый, 2 аккаунта, без экрана, PoE, б/п | D36: =IFERROR(VLOOKUP($B36,Подбор[#All],4,0),"") -> 35960 | E36: =D36*0.93 -> 33442.8 | F36: =IFERROR(VLOOKUP($B36,Подбор[#All],19,0),"") -> EOL
A37: https://ipmatika.kz/products/hotel-phone/Fanvil-H3WF/ | B37: FH3WPPSUB | C37: H3W отельный, 2 аккаунта, без экрана, PoE, б/п, WiFi | D37: =IFERROR(VLOOKUP($B37,Подбор[#All],4,0),"") -> 33500 | E37: =D37*0.93 -> 31155 | F37: =IFERROR(VLOOKUP($B37,Подбор[#All],19,0),"") -> EOL
A38: https://ipmatika.kz/products/hotel-phone/Fanvil-H3WFW/ | B38: FH3WPPSUW | C38: H3W отельный, белый, 2 аккаунта, без экрана, PoE, б/п, WiFi | D38: =IFERROR(VLOOKUP($B38,Подбор[#All],4,0),"") -> 40850 | E38: =D38*0.93 -> 37990.5 | F38: =IFERROR(VLOOKUP($B38,Подбор[#All],19,0),"") -> EOL
A39: https://ipmatika.kz/products/hotel-phone/Fanvil-H4/ | B39: FH4PPSUB | C39: H4 отельный, 2 аккаунта, без экрана, PoE, б/п | D39: =IFERROR(VLOOKUP($B39,Подбор[#All],4,0),"") -> 33100 | E39: =D39*0.93 -> 30783 | F39: =IFERROR(VLOOKUP($B39,Подбор[#All],19,0),"")
A40: https://ipmatika.kz/products/hotel-phone/Fanvil-H4-white/ | B40: FH4PPSUW | C40: H4 отельный, белый, 2 аккаунта, без экрана, PoE, б/п | D40: =IFERROR(VLOOKUP($B40,Подбор[#All],4,0),"") -> 33100 | E40: =D40*0.93 -> 30783 | F40: =IFERROR(VLOOKUP($B40,Подбор[#All],19,0),"")
A41: https://ipmatika.kz/products/hotel-phone/Fanvil-H4W/ | B41: FH4WPPSUB | C41: H4W отельный, 2 аккаунта, без экрана, PoE, б/п | D41: =IFERROR(VLOOKUP($B41,Подбор[#All],4,0),"") -> 46330 | E41: =D41*0.93 -> 43086.9 | F41: =IFERROR(VLOOKUP($B41,Подбор[#All],19,0),"")
A42: https://ipmatika.kz/products/hotel-phone/Fanvil-H4W-white/ | B42: FH4WPPSUW | C42: H4W отельный, белый, 2 аккаунта, без экрана, PoE, б/п | D42: =IFERROR(VLOOKUP($B42,Подбор[#All],4,0),"") -> 46330 | E42: =D42*0.93 -> 43086.9 | F42: =IFERROR(VLOOKUP($B42,Подбор[#All],19,0),"")
A43: https://ipmatika.kz/products/hotel-phone/Fanvil-H5/ | B43: FH5PB sale | C43: H5 отельный, 2 аккаунта, цветной ЖК экран, PoE, б/п | D43: 28070 | E43: =D43*0.93 -> 26105.1 | F43: Акция
A44: https://ipmatika.kz/products/hotel-phone/Fanvil-H5/ | B44: FH5PPSUB | C44: H5 отельный, 2 аккаунта, цветной ЖК экран, PoE, б/п | D44: =IFERROR(VLOOKUP($B44,Подбор[#All],4,0),"") -> 41670 | E44: =D44*0.93 -> 38753.1 | F44: =IFERROR(VLOOKUP($B44,Подбор[#All],19,0),"") -> EOL
A45: https://ipmatika.kz/products/hotel-phone/Fanvil-H5W/ | B45: FH5PPSUW | C45: H5 отельный, белый, 2 аккаунта, цветной ЖК экран, PoE, б/п | D45: =IFERROR(VLOOKUP($B45,Подбор[#All],4,0),"") -> 41670 | E45: =D45*0.93 -> 38753.1 | F45: =IFERROR(VLOOKUP($B45,Подбор[#All],19,0),"") -> EOL
A46: https://ipmatika.kz/products/hotel-phone/Fanvil-H5W/ | B46: FH5PW | C46: H5 отельный, белый, 2 аккаунта, цветной ЖК экран, PoE, без б/п | D46: =IFERROR(VLOOKUP($B46,Подбор[#All],4,0),"") -> 41670 | E46: =D46*0.93 -> 38753.1 | F46: =IFERROR(VLOOKUP($B46,Подбор[#All],19,0),"") -> EOL
A47: https://ipmatika.kz/products/hotel-phone/Fanvil-H5WF/ | B47: FH5WPPSUB | C47: H5W отельный, 2 аккаунта, цветной ЖК экран, PoE, б/п, WiFi | D47: =IFERROR(VLOOKUP($B47,Подбор[#All],4,0),"") | F47: =IFERROR(VLOOKUP($B47,Подбор[#All],19,0),"")
A48: https://ipmatika.kz/products/hotel-phone/Fanvil-H5WFW/ | B48: FH5WPPSUW | C48: H5W отельный, белый, 2 аккаунта, цветной ЖК экран, PoE, б/п, WiFi | D48: =IFERROR(VLOOKUP($B48,Подбор[#All],4,0),"") -> 49030 | E48: =D48*0.93 -> 45597.9 | F48: =IFERROR(VLOOKUP($B48,Подбор[#All],19,0),"") -> EOL
A49: https://ipmatika.kz/products/hotel-phone/Fanvil-H601W/ | B49: FH601W | C49: H601W отельный, 2 аккаунта, б/п, WiFi, без клавиатуры | D49: =IFERROR(VLOOKUP($B49,Подбор[#All],4,0),"") -> 31770 | E49: =D49*0.93 -> 29546.1 | F49: =IFERROR(VLOOKUP($B49,Подбор[#All],19,0),"")
A50: https://ipmatika.kz/products/hotel-phone/Fanvil-H602/ | B50: FH602 | C50: H602 отельный, 2 аккаунта, без б/п | D50: =IFERROR(VLOOKUP($B50,Подбор[#All],4,0),"") -> 35740 | E50: =D50*0.93 -> 33238.2 | F50: =IFERROR(VLOOKUP($B50,Подбор[#All],19,0),"")
A51: https://ipmatika.kz/products/hotel-phone/Fanvil-H603W/ | B51: FH603W | C51: H603W отельный, 2 аккаунта, Wi-Fi-трубка, б/п | D51: =IFERROR(VLOOKUP($B51,Подбор[#All],4,0),"") -> 132380 | E51: =D51*0.93 -> 123113.4 | F51: =IFERROR(VLOOKUP($B51,Подбор[#All],19,0),"")
A52: https://ipmatika.kz/products/hotel-phone/Fanvil-H6W/ | B52: FH6WPPSUB | C52: H6W отельный, 2 аккаунта, цветной ЖК экран, PoE, б/п | D52: =IFERROR(VLOOKUP($B52,Подбор[#All],4,0),"") -> 59560 | E52: =D52*0.93 -> 55390.8 | F52: =IFERROR(VLOOKUP($B52,Подбор[#All],19,0),"")
A53: https://ipmatika.kz/products/hotel-phone/Fanvil-H6W-white/ | B53: FH6WPPSUW | C53: H6W отельный, белый, 2 аккаунта, цветной ЖК экран, PoE, б/п | D53: =IFERROR(VLOOKUP($B53,Подбор[#All],4,0),"") -> 59560 | E53: =D53*0.93 -> 55390.8 | F53: =IFERROR(VLOOKUP($B53,Подбор[#All],19,0),"")
A54: https://ipmatika.kz/products/hotel-phone/Fanvil-H7/ | B54: FJ7A | C54: J7A отельный, цветной сенсорный экран 7'', PoE, Android, WiFi, Bluetooth | D54: =IFERROR(VLOOKUP($B54,Подбор[#All],4,0),"") -> 69450 | E54: =D54*0.93 -> 64588.5 | F54: =IFERROR(VLOOKUP($B54,Подбор[#All],19,0),"") -> EOL
A55: https://ipmatika.kz/products/telefony-dlya-call-tsentra/ | B55: Телефоны для call-центра | D55: =IFERROR(VLOOKUP($B55,Подбор[#All],4,0),"") | F55: =IFERROR(VLOOKUP($B55,Подбор[#All],19,0),"")
A56: https://ipmatika.kz/products/telefony-dlya-call-tsentra/Fanvil-X2C/ | B56: X2C | C56: X2C, для call-центра, ЧБ-дисплей, 2 аккаунта, LED подсветка кнопок, без PoE, БП | D56: =IFERROR(VLOOKUP($B56,Подбор[#All],4,0),"") | F56: =IFERROR(VLOOKUP($B56,Подбор[#All],19,0),"")
A57: https://ipmatika.kz/products/telefony-dlya-call-tsentra/Fanvil-X2P/ | B57: X2P | C57: X2P, для сall-центра, цветной дисплей, 2 аккаунта, LED подсветка кнопок, PoE, без БП | D57: =IFERROR(VLOOKUP($B57,Подбор[#All],4,0),"") | F57: =IFERROR(VLOOKUP($B57,Подбор[#All],19,0),"")
A58: https://ipmatika.kz/products/ip-telefony-dlya-pozhilykh/ | B58: Телефоны для пожилых | F58: =IFERROR(VLOOKUP($B58,Подбор[#All],19,0),"")
A59: https://ipmatika.kz/products/ip-telefony-dlya-pozhilykh/X305/ | B59: X305 | C59: X305, цветной дисплей, 2 аккаунта, большие кнопки, PoE, БП | D59: =IFERROR(VLOOKUP($B59,Подбор[#All],4,0),"") -> 84360 | E59: =D59*0.93 -> 78454.8 | F59: =IFERROR(VLOOKUP($B59,Подбор[#All],19,0),"")
A60: https://ipmatika.kz/products/sistemy-smart-workspace/ | B60: Системы Smart Workspace | F60: =IFERROR(VLOOKUP($B60,Подбор[#All],19,0),"")
A61: https://ipmatika.kz/products/sistemy-smart-workspace/linkvil_ca400/ | B61: CA400 | C61: Fanvil CA400, беспроводной комплект для ВКС и презентаций | D61: =IFERROR(VLOOKUP($B61,Подбор[#All],4,0),"") -> 358580 | E61: =D61*0.93 -> 333479.4 | F61: =IFERROR(VLOOKUP($B61,Подбор[#All],19,0),"")
A62: https://ipmatika.kz/products/audiodomofony/ | B62: Аудио-SIP-домофоны | F62: =IFERROR(VLOOKUP($B62,Подбор[#All],19,0),"")
A63: https://ipmatika.kz/products/audiodomofony/Fanvil-A10/ | B63: A10 | C63: Fanvil A10 IP-аудиодомофон, накладной, IP54, 3 кнопки | D63: =IFERROR(VLOOKUP($B63,Подбор[#All],4,0),"") -> 38930 | E63: =D63*0.93 -> 36204.9 | F63: =IFERROR(VLOOKUP($B63,Подбор[#All],19,0),"")
A64: https://ipmatika.kz/products/audiodomofony/Fanvil-A10W/ | B64: A10W | C64: Fanvil A10W IP-аудиодомофон, накладной, IP54, 3 кнопки, WiFi | D64: =IFERROR(VLOOKUP($B64,Подбор[#All],4,0),"") -> 45420 | E64: =D64*0.93 -> 42240.6 | F64: =IFERROR(VLOOKUP($B64,Подбор[#All],19,0),"")
A65: https://ipmatika.kz/products/audiodomofony/Fanvil-A12/ | B65: A12 | C65: Fanvil A12 IP-домофон, накладной, внешний, стальной корпус, IP66, IK10 | D65: =IFERROR(VLOOKUP($B65,Подбор[#All],4,0),"") -> 155730 | E65: =D65*0.93 -> 144828.9 | F65: =IFERROR(VLOOKUP($B65,Подбор[#All],19,0),"")
A66: https://ipmatika.kz/products/audiodomofony/Fanvil-i10S/ | B66: i10S | C66: Fanvil i10S IP-аудиодомофон, накладной, IP54 | D66: =IFERROR(VLOOKUP($B66,Подбор[#All],4,0),"") -> 45420 | E66: =D66*0.93 -> 42240.6 | F66: =IFERROR(VLOOKUP($B66,Подбор[#All],19,0),"")
A67: https://ipmatika.kz/products/audiodomofony/Fanvil-i11S/ | B67: i11S | C67: Fanvil i11S IP-домофон, накладной, внешний, IP65, IK10 | D67: =IFERROR(VLOOKUP($B67,Подбор[#All],4,0),"") -> 58400 | E67: =D67*0.93 -> 54312 | F67: =IFERROR(VLOOKUP($B67,Подбор[#All],19,0),"")
A68: https://ipmatika.kz/products/audiodomofony/Fanvil-i16S/ | B68: i16S | C68: Fanvil i16S IP-домофон, накладной, внешний, IP65, IK10 | D68: =IFERROR(VLOOKUP($B68,Подбор[#All],4,0),"") -> 97330 | E68: =D68*0.93 -> 90516.9 | F68: =IFERROR(VLOOKUP($B68,Подбор[#All],19,0),"")
A69: https://ipmatika.kz/products/audiodomofony/Fanvil-i16S-02P/ | B69: i16S-02P | C69: Fanvil i16S-02P интерком, накладной, внешний, IP65, IK10, 2 кнопки | D69: =IFERROR(VLOOKUP($B69,Подбор[#All],4,0),"") -> 115500 | E69: =D69*0.93 -> 107415 | F69: =IFERROR(VLOOKUP($B69,Подбор[#All],19,0),"")
A70: https://ipmatika.kz/products/audiodomofony/Fanvil-i20S/ | B70: i20S | C70: Fanvil i20S IP-домофон, накладной, внешний, IP65, клавиатура | D70: 67580 | E70: =D70*0.93 -> 62849.4 | F70: Акция
A71: https://ipmatika.kz/products/audiodomofony/Fanvil-Y501/ | B71: Y501 | C71: Fanvil Y501 IP-аудиодомофон, накладной, IP54, 3 кнопки | D71: =IFERROR(VLOOKUP($B71,Подбор[#All],4,0),"") -> 58400 | E71: =D71*0.93 -> 54312 | F71: =IFERROR(VLOOKUP($B71,Подбор[#All],19,0),"")
A72: https://ipmatika.kz/products/audiodomofony/Fanvil-Y501W-Y/ | B72: Y501W-Y | C72: Fanvil Y501W-Y IP-аудиодомофон, накладной, IP54, 6 кнопок, WiFi, проводной пульт | D72: =IFERROR(VLOOKUP($B72,Подбор[#All],4,0),"") -> 71380 | E72: =D72*0.93 -> 66383.4 | F72: =IFERROR(VLOOKUP($B72,Подбор[#All],19,0),"")
A73: https://ipmatika.kz/products/videodomofony/ | B73: Видео-SIP-домофоны | F73: =IFERROR(VLOOKUP($B73,Подбор[#All],19,0),"")
A74: https://ipmatika.kz/products/videodomofony/Fanvil-i10SV/ | B74: i10SV | C74: Fanvil i10SV IP-видеодомофон, накладной, IP54 | D74: =IFERROR(VLOOKUP($B74,Подбор[#All],4,0),"") -> 64890 | E74: =D74*0.93 -> 60347.7 | F74: =IFERROR(VLOOKUP($B74,Подбор[#All],19,0),"")
A75: https://ipmatika.kz/products/videodomofony/Fanvil-i11SV/ | B75: i11SV | C75: Fanvil i11SV IP-видеодомофон, накладной, внешний, HD камера, IP65, IK10 | D75: =IFERROR(VLOOKUP($B75,Подбор[#All],4,0),"") -> 71380 | E75: =D75*0.93 -> 66383.4 | F75: =IFERROR(VLOOKUP($B75,Подбор[#All],19,0),"")
A76: https://ipmatika.kz/products/videodomofony/Fanvil-i16SV/ | B76: i16SV | C76: Fanvil i16SV IP-видеодомофон, накладной, внешний, HD камера, IP65, IK10 | D76: =IFERROR(VLOOKUP($B76,Подбор[#All],4,0),"") -> 128480 | E76: =D76*0.93 -> 119486.4 | F76: =IFERROR(VLOOKUP($B76,Подбор[#All],19,0),"")
A77: https://ipmatika.kz/products/videodomofony/Fanvil-i16SV-02P/ | B77: i16SV-02P | C77: Fanvil i16SV-02P интерком, накладной, внешний, IP65, IK10, 2 кнопки | D77: =IFERROR(VLOOKUP($B77,Подбор[#All],4,0),"") -> 155730 | E77: =D77*0.93 -> 144828.9 | F77: =IFERROR(VLOOKUP($B77,Подбор[#All],19,0),"")
A78: https://ipmatika.kz/products/videodomofony/Fanvil-i33V/ | B78: i33V | C78: Fanvil i33V домофон, накладной, внешний, клавиатура, HD камера, IC/RFID, IP65 | D78: =IFERROR(VLOOKUP($B78,Подбор[#All],4,0),"") | F78: =IFERROR(VLOOKUP($B78,Подбор[#All],19,0),"")
A79: https://ipmatika.kz/products/videodomofony/Fanvil-i60/ | B79: i60 | C79: Fanvil i60 IP-видеодомофон, накладной, IP65, 1 кнопка, Mifare | D79: =IFERROR(VLOOKUP($B79,Подбор[#All],4,0),"") -> 38930 | E79: =D79*0.93 -> 36204.9 | F79: =IFERROR(VLOOKUP($B79,Подбор[#All],19,0),"")
A80: https://ipmatika.kz/products/videodomofony/Fanvil-i60K/ | B80: i60K | C80: Fanvil i60K IP-видеодомофон, накладной, IP65, клавиатура, Mifare | D80: =IFERROR(VLOOKUP($B80,Подбор[#All],4,0),"") -> 71380 | E80: =D80*0.93 -> 66383.4 | F80: =IFERROR(VLOOKUP($B80,Подбор[#All],19,0),"")
A81: https://ipmatika.kz/products/videodomofony/Fanvil-i61/ | B81: i61 | C81: Fanvil i61 IP-видеодомофон, накладной, IP66 IK07 | D81: =IFERROR(VLOOKUP($B81,Подбор[#All],4,0),"") -> 123280 | E81: =D81*0.93 -> 114650.4 | F81: =IFERROR(VLOOKUP($B81,Подбор[#All],19,0),"")
A82: https://ipmatika.kz/products/videodomofony/Fanvil-i62/ | B82: i62 | C82: Fanvil i62 IP-видеодомофон, накладной, IP66 IK07 | D82: =IFERROR(VLOOKUP($B82,Подбор[#All],4,0),"") -> 99690 | E82: =D82*0.93 -> 92711.7 | F82: =IFERROR(VLOOKUP($B82,Подбор[#All],19,0),"")
A83: https://ipmatika.kz/products/videodomofony/Fanvil-i63/ | B83: i63 | C83: Fanvil i63 IP-видеодомофон, накладной, IP66, IK07, 5 кнопок | D83: =IFERROR(VLOOKUP($B83,Подбор[#All],4,0),"") -> 103820 | E83: =D83*0.93 -> 96552.6 | F83: =IFERROR(VLOOKUP($B83,Подбор[#All],19,0),"")
A84: https://ipmatika.kz/products/videodomofony/Fanvil-i64/ | B84: i64 | C84: Fanvil i64 IP-видеодомофон, накладной, IP66, IK07, 16 кнопок | D84: =IFERROR(VLOOKUP($B84,Подбор[#All],4,0),"") -> 116790 | E84: =D84*0.93 -> 108614.7 | F84: =IFERROR(VLOOKUP($B84,Подбор[#All],19,0),"")
A85: https://ipmatika.kz/products/videodomofony/Fanvil-i66/ | B85: i66 | C85: Fanvil i66 IP-видеодомофон, накладной, IP66, IK07, 16 кнопок, дисплей | D85: =IFERROR(VLOOKUP($B85,Подбор[#All],4,0),"") -> 233600 | E85: =D85*0.93 -> 217248 | F85: =IFERROR(VLOOKUP($B85,Подбор[#All],19,0),"")
A86: https://ipmatika.kz/products/videodomofony/Fanvil-i67/ | B86: i67 | C86: Fanvil i67 IP-видеодомофон, накладной, IP66, IK07, 12 кнопок, дисплей 7'' | D86: =IFERROR(VLOOKUP($B86,Подбор[#All],4,0),"") -> 324440 | E86: =D86*0.93 -> 301729.2 | F86: =IFERROR(VLOOKUP($B86,Подбор[#All],19,0),"")
A87: https://ipmatika.kz/products/videodomofony/Fanvil-i68/ | B87: i68 | C87: Fanvil i68 IP-видеодомофон, IP66, IK07, дисплей 8'' | D87: =IFERROR(VLOOKUP($B87,Подбор[#All],4,0),"") -> 363370 | E87: =D87*0.93 -> 337934.1 | F87: =IFERROR(VLOOKUP($B87,Подбор[#All],19,0),"")
A88: https://ipmatika.kz/products/vnutrennie-sip-paneli/ | B88: Ответные части | F88: =IFERROR(VLOOKUP($B88,Подбор[#All],19,0),"")
A89: https://ipmatika.kz/products/vnutrennie-sip-paneli/Fanvil-i10SD/ | B89: i10SD | C89: Fanvil i10SD IP-аудиодомофон, накладной, IP54, кнопки | D89: =IFERROR(VLOOKUP($B89,Подбор[#All],4,0),"") -> 53210 | E89: =D89*0.93 -> 49485.3 | F89: =IFERROR(VLOOKUP($B89,Подбор[#All],19,0),"")
A90: https://ipmatika.kz/products/vnutrennie-sip-paneli/Fanvil-i501/ | B90: i501 | C90: Fanvil i501, PoE, IP домофонная трубка, 4 кнопки | D90: =IFERROR(VLOOKUP($B90,Подбор[#All],4,0),"") -> 15570 | E90: =D90*0.93 -> 14480.1 | F90: =IFERROR(VLOOKUP($B90,Подбор[#All],19,0),"")
A91: https://ipmatika.kz/products/vnutrennie-sip-paneli/Fanvil-i501W/ | B91: i501W | C91: Fanvil i501W, PoE, Wi-Fi, IP домофонная трубка, 4 кнопки | D91: =IFERROR(VLOOKUP($B91,Подбор[#All],4,0),"") -> 19940 | E91: =D91*0.93 -> 18544.2 | F91: =IFERROR(VLOOKUP($B91,Подбор[#All],19,0),"")
A92: https://ipmatika.kz/products/vnutrennie-sip-paneli/Fanvil-i504/ | B92: i504 | C92: Fanvil i504, без БП, ответная часть для SIP-домофона | D92: =IFERROR(VLOOKUP($B92,Подбор[#All],4,0),"") -> 45420 | E92: =D92*0.93 -> 42240.6 | F92: =IFERROR(VLOOKUP($B92,Подбор[#All],19,0),"")
A93: https://ipmatika.kz/products/vnutrennie-sip-paneli/Fanvil-i504/ | B93: i504W | C93: Fanvil i504W, без БП, Wi-Fi, ответная часть для SIP-домофона | D93: =IFERROR(VLOOKUP($B93,Подбор[#All],4,0),"") -> 51910 | E93: =D93*0.93 -> 48276.3 | F93: =IFERROR(VLOOKUP($B93,Подбор[#All],19,0),"")
A94: https://ipmatika.kz/products/vnutrennie-sip-paneli/Fanvil-i505/ | B94: i505 | C94: Fanvil i505, без БП, Android, ответная часть для SIP-домофона | D94: =IFERROR(VLOOKUP($B94,Подбор[#All],4,0),"") -> 94730 | E94: =D94*0.93 -> 88098.9 | F94: =IFERROR(VLOOKUP($B94,Подбор[#All],19,0),"")
A95: https://ipmatika.kz/products/vnutrennie-sip-paneli/Fanvil-i506W/ | B95: i506W | C95: Fanvil i506W, без БП, WiFi, ответная часть для SIP-домофона | D95: =IFERROR(VLOOKUP($B95,Подбор[#All],4,0),"") -> 84360 | E95: =D95*0.93 -> 78454.8 | F95: =IFERROR(VLOOKUP($B95,Подбор[#All],19,0),"")
A96: https://ipmatika.kz/products/vnutrennie-sip-paneli/Fanvil-i507W/ | B96: i507W | C96: Fanvil i507W, без БП, Android, WiFi, ответная часть для SIP-домофона | D96: =IFERROR(VLOOKUP($B96,Подбор[#All],4,0),"") -> 133670 | E96: =D96*0.93 -> 124313.1 | F96: =IFERROR(VLOOKUP($B96,Подбор[#All],19,0),"")
A97: https://ipmatika.kz/products/vnutrennie-sip-paneli/Fanvil-i51W/ | B97: i51W | C97: Fanvil i51W, WiFi, без БП, ответная часть для SIP-домофона | D97: =IFERROR(VLOOKUP($B97,Подбор[#All],4,0),"") | F97: =IFERROR(VLOOKUP($B97,Подбор[#All],19,0),"")
A98: https://ipmatika.kz/products/vnutrennie-sip-paneli/Fanvil-i52W/ | B98: i52W | C98: Fanvil i52W, WiFi, без БП, ответная часть для SIP-домофона | D98: 26510 | E98: =D98*0.93 -> 24654.3 | F98: Акция
A99: https://ipmatika.kz/products/vnutrennie-sip-paneli/Fanvil-i53W/ | B99: i53W | C99: Fanvil i53W, WiFi, без БП, Сенсорный экран, ответная часть для SIP-домофона | D99: 67580 | E99: =D99*0.93 -> 62849.4 | F99: Акция
A100: https://ipmatika.kz/products/vnutrennie-sip-paneli/Fanvil-i55A/ | B100: i55A | C100: Fanvil i55A, WiFi, без БП, ответная часть для SIP-домофона | D100: =IFERROR(VLOOKUP($B100,Подбор[#All],4,0),"") -> 116790 | E100: =D100*0.93 -> 108614.7 | F100: =IFERROR(VLOOKUP($B100,Подбор[#All],19,0),"")
...

Sheet VT
A1: URL | B1: Артикул | C1: Описание | D1: KZ РРЦ | E1: Цена Сайт | F1: Status
A2: https://ipmatika.kz/products/garnitury-vt/ | B2: Гарнитуры VT | F2: =IFERROR(VLOOKUP($B2,Подбор[#All],19,0),"")
A3: https://ipmatika.kz/products/besprovodnye/ | B3: Беспроводные гарнитуры
A4: https://ipmatika.kz/products/bluetooth/ | B4: Беспроводные гарнитуры Bluetooth
A5: https://ipmatika.kz/products/bluetooth/vt_flow/ | B5: VT FLOW | C5: VT FLOW, Дуо, Hi-Fi звук, 30м Bluetooth, индикатор занятости, ANC, складная, чехол, Dongle | D5: 133100 | E5: =D5*0.93 -> 123783
A6: https://ipmatika.kz/products/bluetooth/VT9200-D/ | B6: VT9200-D | C6: VT9200-D, Дуо, HD звук, 30м Bluetooth, USB Type-C Dongle | D6: 52800 | E6: =D6*0.93 -> 49104
A7: https://ipmatika.kz/products/bluetooth/VT9200/ | B7: VT9200 | C7: VT9200, Моно, HD звук, 30м Bluetooth, USB Type-C Dongle | D7: 46750 | E7: =D7*0.93 -> 43477.5
A8: https://ipmatika.kz/products/bluetooth/VT9200_Without/ | B8: VT9200_Without | C8: VT9200, Моно, HD звук, 30м Bluetooth, USB Type-C без донгла | D8: 35750 | E8: =D8*0.93 -> 33247.5
A9: https://ipmatika.kz/products/bluetooth/VT-VT9500-D/ | B9: VT9500-D | C9: VT9500-D, Дуо, HD звук, 10м Bluetooth | D9: 33300 | E9: =D9*0.93 -> 30969
A10: https://ipmatika.kz/products/bluetooth/VT9605-D/ | B10: VT9605-D | C10: VT9605-D, Дуо, Hi-Fi звук, 30м Bluetooth, индикатор занятости, в комплекте с USB-BT адаптером | D10: 53020 | E10: =D10*0.93 -> 49308.6
A11: https://ipmatika.kz/products/bluetooth/VT-X300BT-D/ | B11: X300BT-D | C11: X300BT-D, Дуо, Hi-Fi звук, 30м Bluetooth, индикатор занятости, в комплекте с USB-BT адаптером | D11: 114400 | E11: =D11*0.93 -> 106392
A12: https://ipmatika.kz/products/dect-/ | B12: Беспроводные гарнитуры DECT
A13: https://ipmatika.kz/products/dect-/W310U-D/ | B13: W310U-D | C13: VT W310U-D, Дуо, HD звук, 150м DECT, USB-dogle type-C, чехол | D13: 129250 | E13: =D13*0.93 -> 120202.5
A14: https://ipmatika.kz/products/dect-/W310U/ | B14: W310U | C14: VT W310U, Моно, HD звук, 150м DECT, USB-dogle type-C, чехол | D14: 119900 | E14: =D14*0.93 -> 111507
A15: https://ipmatika.kz/products/dect-/VT-VT9000_LFT/ | B15: VT9000_LFT | C15: VT9000 в комплекте с микролифтом, Моно, HD звук, 150м DECT, для телефона | D15: 124140 | E15: =D15*0.93 -> 115450.2
A16: https://ipmatika.kz/products/dect-/VT-VT9000-D_LFT/ | B16: VT9000-D_LFT | C16: VT9000-D в комплекте с микролифтом, Дуо, HD звук, 150м DECT, для телефона | D16: 130290 | E16: =D16*0.93 -> 121169.7
A17: https://ipmatika.kz/products/dect-/VT-VT9000-D/ | B17: VT9000-D | C17: VT9000-D, Дуо, HD звук, 150м DECT, для телефона | D17: 112000 | E17: =D17*0.93 -> 104160
A18: https://ipmatika.kz/products/dect-/VT-VT9000/ | B18: VT9000 | C18: VT9000, Моно, HD звук, 150м DECT, для телефона | D18: 58740 | E18: =D18*0.93 -> 54628.2
A19: https://ipmatika.kz/products/dect-/VT-VT9400-D/ | B19: VT9400-D | C19: VT9400-D, Дуо, HD звук, 150м DECT, для компьютера и телефона | D19: 118000 | E19: =D19*0.93 -> 109740
A20: https://ipmatika.kz/products/dect-/VT-VT9400/ | B20: VT9400 | C20: VT9400, Моно, HD звук, 150м DECT, для компьютера и телефона | D20: 67060 | E20: =D20*0.93 -> 62365.8
A21: https://ipmatika.kz/products/usb-videokamery-i-byod-resheniya/ | B21: Веб-камеры
A22: https://ipmatika.kz/products/usb-videokamery-i-byod-resheniya/vt-webcam-v100/ | B22: V100 | C22: VT V100 USB веб-камера Full HD | D22: 38500 | E22: =D22*0.93 -> 35805
A23: https://ipmatika.kz/products/garnitury-zashchishchyennye/ | B23: Гарнитуры защищённые для склада
A24: https://ipmatika.kz/products/garnitury-zashchishchyennye/vt-w300/ | B24: W300 | C24: W300 защищенная, моно, 30м Bluetooth, от -20 до +50 град, 2 аккумулятора | D24: 207460 | E24: =D24*0.93 -> 192937.8
A25: https://ipmatika.kz/products/provodnye/ | B25: Проводные гарнитуры
A26: https://ipmatika.kz/products/provodnye/VT-VT1000-RJ9%2803%29/ | B26: VT1000 RJ9(03) | C26: VT1000 RJ9(03), Моно, Узкополосный звук, SE, усовершенствованный микрофон | D26: 10000 | E26: =D26*0.93 -> 9300
A27: https://ipmatika.kz/products/archive/provodnye/VT-VT1000-USB/ | B27: VT1000 USB old | C27: VT1000 USB, Моно, Узкополосный звук, SE, усовершенствованный | D27: 11440 | E27: =D27*0.93 -> 10639.2
A28: https://ipmatika.kz/products/provodnye/VT-VT1000-D-RJ9%2803%29/ | B28: VT1000-D RJ9(03) | C28: VT1000-D RJ9(03), Дуо, Узкополосный звук SE, усовершенствованный микрофон | D28: 11610 | E28: =D28*0.93 -> 10797.3
A29: https://ipmatika.kz/products/provodnye/VT-VT1000-D-USB/ | B29: VT1000-D USB | C29: VT1000-D USB, Дуо, Узкополосный звук SE, усовершенствованный микрофон | D29: 19950 | E29: =D29*0.93 -> 18553.5
A30: https://ipmatika.kz/products/provodnye/VT-VT5000-QD%28P%29-RJ9%2803%29/ | B30: VT5000 QD(P)-RJ9(03) | C30: VT5000 QD(P)-RJ9(03), Моно, Узкополосный звук, QD, переходник QD-RJ09(03) | D30: 15770 | E30: =D30*0.93 -> 14666.1
A31: https://ipmatika.kz/products/provodnye/VT5000_USB/ | B31: VT5000 USB | C31: VT5000 USB, Моно, HD звук | D31: 17890 | E31: =D31*0.93 -> 16637.7
A32: https://ipmatika.kz/products/provodnye/VT-VT5000-D-QD%28P%29-RJ9%2803%29/ | B32: VT5000-D QD(P)-RJ9(03) | C32: VT5000-D QD(P)-RJ9(03), Дуо, Узкополосный звук, QD, переходник QD-RJ09(03) | D32: 19500 | E32: =D32*0.93 -> 18135
A33: https://ipmatika.kz/products/provodnye/VT5000-D_USB/ | B33: VT5000-D USB | C33: VT5000-D USB, Дуо, HD звук | D33: 19930 | E33: =D33*0.93 -> 18534.9
A34: https://ipmatika.kz/products/provodnye/VT-VT6200-QD%28P%29-RJ9%2803%29/ | B34: VT6200 QD(P)-RJ9(03) | C34: VT6200 QD(P)-RJ9(03), Моно, HD звук, QD, переходник QD-RJ09(03) | D34: 19570 | E34: =D34*0.93 -> 18200.1
A35: https://ipmatika.kz/products/provodnye/VT-VT6200-USB/ | B35: VT6200 USB | C35: VT6200 USB, Моно, HD звук | D35: 22370 | E35: =D35*0.93 -> 20804.1
A36: https://ipmatika.kz/products/provodnye/VT-VT6200-D-QD%28P%29-RJ9%2803%29/ | B36: VT6200-D QD(P)-RJ9(03) | C36: VT6200-D QD(P)-RJ9(03), Дуо, HD звук, QD, переходник QD-RJ09(03) | D36: 22370 | E36: =D36*0.93 -> 20804.1
A37: https://ipmatika.kz/products/provodnye/VT-VT6200-D-USB/ | B37: VT6200-D USB | C37: VT6200-D USB, Дуо, HD звук | D37: 24440 | E37: =D37*0.93 -> 22729.2
... A43: https://ipmatika.kz/products/provodnye/X208/ | B43: X208 | C43: X208, Моно, HD звук, разъемы 3,5 мм Jack и USB | D43: 36300 | E43: =D43*0.93 -> 33759
A44: https://ipmatika.kz/products/spikerfony/ | B44: Спикерфоны VT
A45: https://ipmatika.kz/products/spikerfony/VT-CS61/ | B45: CS61ENC-A | C45: CS61ENC-A USB/Bluetooth в комплекте с BT-dongle, переходником USB-TypeA-USB-TypeC | D45: 92000 | E45: =D45*0.93 -> 85560
A46: https://ipmatika.kz/products/aksessuary/ | B46: Аксессуары для гарнитур
A47: https://ipmatika.kz/products/aksessuary/SmartCord/ | B47: QD-SmartCord | C47: QD-SmartCord - универсальный переходник для подключения гарнитур VT к разным телефонам | D47: 8800 | E47: =D47*0.93 -> 8184
A48: https://ipmatika.kz/products/aksessuary/VT-QD%28P%29-3.5-mm-%2801%29/ | B48: QD(P) - 3.5 mm (01) | C48: QD(P) - 3.5 mm (01), для VoIP и аналоговых телефонов и смартфонов | D48: 3760 | E48: =D48*0.93 -> 3496.8
A49: https://ipmatika.kz/products/aksessuary/VT-QD%28P%29-USB-%2801%29/ | B49: QD(P) - USB (01) | C49: QD(P) - USB (01), для софтфона и Skype | D49: 9350 | E49: =D49*0.93 -> 8695.5
A50: https://ipmatika.kz/products/aksessuary/VT-QD%28P%29-2QD%28P%29%2802%29/ | B50: QD(P)-2QD(P)(02) | C50: QD(P)-2QD(P)(02) | D50: 8250 | E50: =D50*0.93 -> 7672.5
A51: https://ipmatika.kz/products/aksessuary/VT-QD%28P%29-HIS/ | B51: QD(P)-HIS | C51: QD(P)-HIS, для телефонов Avaya 16xx, 96xx | D51: 8250 | E51: =D51*0.93 -> 7672.5
A52: https://ipmatika.kz/products/aksessuary/VT-QD%28P%29-RJ09%2801%29/ | B52: QD(P)-RJ9(01) | C52: QD(P)-RJ9(01), для аналоговых и Avaya, Polycom, Mitel, Astra,Fanvil,Digium,Ecense,Nec,Sangoma,Alcate | D52: 3760 | E52: =D52*0.93 -> 3496.8
A53: https://ipmatika.kz/products/aksessuary/VT-QD%28P%29-RJ9%2802%29/ | B53: QD(P)-RJ9(02) | C53: QD(P)-RJ9(02), для CISCO | D53: 3760 | E53: =D53*0.93 -> 3496.8
A54: https://ipmatika.kz/products/aksessuary/VT-QD%28P%29-RJ09%2803%29/ | B54: QD(P)-RJ9(03) | C54: QD(P)-RJ9(03), для Yealink, Grandstream, Huawei ,Htek, Xorcom, Siemens, Snom | D54: 3760 | E54: =D54*0.93 -> 3496.8
A55: https://ipmatika.kz/products/aksessuary/VT-LeatherCushion/ | B55: VT-LeatherCushion | C55: Запасной амбушюр для гарнитур VT5000/6200/9000/9300/9500, экокожа, ⌀5 см | D55: 1540 | E55: =D55*0.93 -> 1432.2
A56: https://ipmatika.kz/products/aksessuary/LeatherCusionX140/ | B56: VT-LeatherCusionX140 | C56: Запасной амбушюр для гарнитур X140, экокожа, ⌀5 см | D56: 1680 | E56: =D56*0.93 -> 1562.4
A57: https://ipmatika.kz/products/aksessuary/VT-Lifter/ | B57: VT-Lifter | C57: Микролифт механический для DECT гарнитур VT9000/VT9400 | D57: 45650 | E57: =D57*0.93 -> 42454.5

Sheet Qbic
A1: URL | B1: Артикул | C1: Описание | D1: KZ РРЦ | E1: KZ Дилер | F1: Status
A2: https://ipmatika.kz/products/promyshlennye-i-kommercheskie-kompyutery/ | B2: Панельные компьютеры и мини-ПК | F2: =IFERROR(VLOOKUP($B2,Подбор[#All],19,0),"")
A3: https://ipmatika.kz/products/panelnye-kompyutery/ | B3: Панельные ПК | E3: =IFERROR(D3*0.85,"") | F3: =IFERROR(VLOOKUP($B3,Подбор[#All],19,0),"")
A4: https://ipmatika.kz/products/panelnye-kompyutery/ep-0400/ | B4: EP-0400 | C4: EP-0400 - Дисплей e-ink 4.2'', 400x300, 3 цвета: черн, белый, красный, 3 кнопки | D4: =IFERROR(VLOOKUP($B4,Подбор[#All],4,0),"") -> 90750 | E4: =IFERROR(VLOOKUP($B4,Подбор[#All],5,0),"") -> 77137.5 | F4: =IFERROR(VLOOKUP($B4,Подбор[#All],19,0),"") -> Под заказ
A5: https://ipmatika.kz/products/panelnye-kompyutery/ep-0700/ | B5: EP-0700 | C5: EP-0700 - Дисплей e-ink 7.5'', 800x480, 3 цвета: черн, белый, красный, 3 кнопки | D5: =IFERROR(VLOOKUP($B5,Подбор[#All],4,0),"") -> 181500 | E5: =IFERROR(VLOOKUP($B5,Подбор[#All],5,0),"") -> 154275 | F5: =IFERROR(VLOOKUP($B5,Подбор[#All],19,0),"") -> Под заказ
A6: https://ipmatika.kz/products/panelnye-kompyutery/qbic-td-0350-bh/ | B6: TD-0350-BH125 | C6: TD-0350, 3,5" сенсорная панель, BT, NFC/RFID/HID, RCC, черный | D6: =IFERROR(VLOOKUP($B6,Подбор[#All],4,0),"") -> 334400 | E6: =IFERROR(VLOOKUP($B6,Подбор[#All],5,0),"") -> 284240 | F6: =IFERROR(VLOOKUP($B6,Подбор[#All],19,0),"") -> EOL
A7: https://ipmatika.kz/products/panelnye-kompyutery/TD-0360/ | B7: TD-0360-S | C7: TD-0360, 3,6" сенсорная панель, BT, NFC/RFID, RCC, серебристый | D7: =IFERROR(VLOOKUP($B7,Подбор[#All],4,0),"") -> 308000 | E7: =IFERROR(VLOOKUP($B7,Подбор[#All],5,0),"") -> 261800 | F7: =IFERROR(VLOOKUP($B7,Подбор[#All],19,0),"") -> NEW
A8: https://ipmatika.kz/products/panelnye-kompyutery/qbic-td-1050pro-b-/ | B8: TD-1050PRO-B | C8: TD-1050 PRO, 10" сенсорная панель, BT, NFC/RFID, RCC, черный | D8: =IFERROR(VLOOKUP($B8,Подбор[#All],4,0),"") -> 726000 | E8: =IFERROR(VLOOKUP($B8,Подбор[#All],5,0),"") -> 617100 | F8: =IFERROR(VLOOKUP($B8,Подбор[#All],19,0),"") -> EOL
A9: https://ipmatika.kz/products/panelnye-kompyutery/qbic-td-1060-slim/ | B9: TD-1060 Slim | C9: TD-1060 Slim, 10" сенсорная панель, BT, RCC, черный | D9: =IFERROR(VLOOKUP($B9,Подбор[#All],4,0),"") -> 533500 | E9: =IFERROR(VLOOKUP($B9,Подбор[#All],5,0),"") -> 453475 | F9: =IFERROR(VLOOKUP($B9,Подбор[#All],19,0),"")
A10: https://ipmatika.kz/products/panelnye-kompyutery/qbic-td-1070/ | B10: TD-1070-BH | C10: TD-1070, 10" сенсорная панель Full HD, BT, NFC/HID/RFID, RCC, Android11 | D10: =IFERROR(VLOOKUP($B10,Подбор[#All],4,0),"") -> 1034000 | E10: =IFERROR(VLOOKUP($B10,Подбор[#All],5,0),"") -> 878900 | F10: =IFERROR(VLOOKUP($B10,Подбор[#All],19,0),"") -> Под заказ
A11: https://ipmatika.kz/products/panelnye-kompyutery/qbic-td-1070/ | B11: TD-1070-B | C11: TD-1070, 10" сенсорная панель Full HD, BT, NFC/RFID, RCC, Android11 | D11: =IFERROR(VLOOKUP($B11,Подбор[#All],4,0),"") -> 825000 | E11: =IFERROR(VLOOKUP($B11,Подбор[#All],5,0),"") -> 701250 | F11: =IFERROR(VLOOKUP($B11,Подбор[#All],19,0),"") -> ОБРАЗЕЦ
A12: https://ipmatika.kz/products/panelnye-kompyutery/qbic-td-1070-lite/ | B12: TD-1070 Lite | C12: TD-1070L-S, 10" сенсорная панель Full HD, BT, NFC/RFID, RCC, Android12 | D12: =IFERROR(VLOOKUP($B12,Подбор[#All],4,0),"") -> 764500 | E12: =IFERROR(VLOOKUP($B12,Подбор[#All],5,0),"") -> 649825 | F12: =IFERROR(VLOOKUP($B12,Подбор[#All],19,0),"")
A13: https://ipmatika.kz/products/panelnye-kompyutery/qbic-td-1070-lite/ | B13: TD-1070 Lite H | C13: TD-1070L-SH, 10" сенсорная панель Full HD, BT, NFC/RFID/HID, RCC, Android12 | D13: =IFERROR(VLOOKUP($B13,Подбор[#All],4,0),"") -> 946000 | E13: =IFERROR(VLOOKUP($B13,Подбор[#All],5,0),"") -> 804100 | F13: =IFERROR(VLOOKUP($B13,Подбор[#All],19,0),"") -> Под заказ
A14: https://ipmatika.kz/products/box-pc/ | B14: Промышленные мини-ПК | D14: =IFERROR(VLOOKUP($B14,Подбор[#All],4,0),"") | E14: =IFERROR(VLOOKUP($B14,Подбор[#All],5,0),"") | F14: =IFERROR(VLOOKUP($B14,Подбор[#All],19,0),"")
A15: https://ipmatika.kz/products/box-pc/BXP-100/ | B15: BXP-100 | C15: BXP-100 - Мини-ПК, HDMI output, 2GB RAM, 32GB storage, micro-SDHC expansion | D15: =IFERROR(VLOOKUP($B15,Подбор[#All],4,0),"") -> 236500 | E15: =IFERROR(VLOOKUP($B15,Подбор[#All],5,0),"") -> 201025 | F15: =IFERROR(VLOOKUP($B15,Подбор[#All],19,0),"")
A16: https://ipmatika.kz/products/box-pc/BXP-320/ | B16: BXP-320 | C16: BXP-320 - Мини-ПК, HDMI output 4K, 4GB RAM, 32GB storage, micro-SDHC expansion | D16: =IFERROR(VLOOKUP($B16,Подбор[#All],4,0),"") -> 588500 | E16: =IFERROR(VLOOKUP($B16,Подбор[#All],5,0),"") -> 500225 | F16: =IFERROR(VLOOKUP($B16,Подбор[#All],19,0),"") -> Под заказ
A17: https://ipmatika.kz/products/box-pc/BXP-321/ | B17: BXP-321 | C17: BXP-321 - Мини-ПК, HDMI input и HDMI output 4K, 4GB RAM, 32GB storage, micro-SDHC expansion | D17: =IFERROR(VLOOKUP($B17,Подбор[#All],4,0),"") -> 638000 | E17: =IFERROR(VLOOKUP($B17,Подбор[#All],5,0),"") -> 542300 | F17: =IFERROR(VLOOKUP($B17,Подбор[#All],19,0),"") -> Под заказ
A18: https://ipmatika.kz/products/box-pc/qbic-bxt-312/ | B18: BXT-312 | C18: BXT-312 - Мини-ПК, 2xHDMI-out (8k, 4k), 1xHDMI-in 4k, 8GB RAM, 128GB storage, micro-SDHC | D18: =IFERROR(VLOOKUP($B18,Подбор[#All],4,0),"") | E18: =IFERROR(VLOOKUP($B18,Подбор[#All],5,0),"") | F18: =IFERROR(VLOOKUP($B18,Подбор[#All],19,0),"")
A19: https://ipmatika.kz/products/box-pc/qbic_BXT_512/ | B19: BXT-512 | C19: BXT-512 - Мини-ПК, Core-i3 7100U/8gb/256ssd/VESA/EU Power Code | D19: =IFERROR(VLOOKUP($B19,Подбор[#All],4,0),"") -> 1314500 | E19: =IFERROR(VLOOKUP($B19,Подбор[#All],5,0),"") -> 1117325 | F19: =IFERROR(VLOOKUP($B19,Подбор[#All],19,0),"")
A20: https://ipmatika.kz/products/sistemy-bronirovaniya/ | B20: Системы бронирования | D20: =IFERROR(VLOOKUP($B20,Подбор[#All],4,0),"") | E20: =IFERROR(VLOOKUP($B20,Подбор[#All],5,0),"") | F20: =IFERROR(VLOOKUP($B20,Подбор[#All],19,0),"")
A21: https://ipmatika.kz/products/doortablet-on-premise/ | B21: Door Tablet | D21: =IFERROR(VLOOKUP($B21,Подбор[#All],4,0),"") | E21: =IFERROR(VLOOKUP($B21,Подбор[#All],5,0),"") | F21: =IFERROR(VLOOKUP($B21,Подбор[#All],19,0),"")
A22: https://ipmatika.kz/products/doortablet-on-premise/DT-PREC/ | B22: DT-PREC | C22: Desk Presence Controller - Лицензия для подключения 1 концентратора AC-210.ex к системе Deskware | D22: =IFERROR(VLOOKUP($B22,Подбор[#All],4,0),"") | E22: =IFERROR(VLOOKUP($B22,Подбор[#All],5,0),"") | F22: =IFERROR(VLOOKUP($B22,Подбор[#All],19,0),"") -> Под заказ
A23: https://ipmatika.kz/products/doortablet-on-premise/DT-PRE/ | B23: DT-PRE | C23: DeskWare Presence license - Отображение статуса занятости 1 рабочего стола без бронирования | D23: =IFERROR(VLOOKUP($B23,Подбор[#All],4,0),"") | E23: =IFERROR(VLOOKUP($B23,Подбор[#All],5,0),"") | F23: =IFERROR(VLOOKUP($B23,Подбор[#All],19,0),"") -> Под заказ
A24: https://ipmatika.kz/products/doortablet-on-premise/DT-PRE/ | B24: DT-API | C24: Door Tablet API - Лицензия на предоставление доступа к серверу стронних устройств и приложений | D24: =IFERROR(VLOOKUP($B24,Подбор[#All],4,0),"") | E24: =IFERROR(VLOOKUP($B24,Подбор[#All],5,0),"") | F24: =IFERROR(VLOOKUP($B24,Подбор[#All],19,0),"") -> Под заказ
A25: https://ipmatika.kz/products/doortablet-on-premise/DT-EN/ | B25: DT-EN | C25: Enterprise Server Licence - Лицензия на серверное ПО для 10 и более переговорных | D25: =IFERROR(VLOOKUP($B25,Подбор[#All],4,0),"") | E25: =IFERROR(VLOOKUP($B25,Подбор[#All],5,0),"") | F25: =IFERROR(VLOOKUP($B25,Подбор[#All],19,0),"") -> Под заказ
A26: https://ipmatika.kz/products/doortablet-on-premise/SUPG/ | B26: SUPG | C26: Enterprise Server Upgrade - Лицензия - обновление сервера со Standard Server на Enterprise | D26: =IFERROR(VLOOKUP($B26,Подбор[#All],4,0),"") | E26: =IFERROR(VLOOKUP($B26,Подбор[#All],5,0),"") | F26: =IFERROR(VLOOKUP($B26,Подбор[#All],19,0),"") -> Под заказ
A27: https://ipmatika.kz/products/doortablet-on-premise/DT-DSKO/ | B27: DT-DSKO | C27: Hot Desk OEM - Лицензия для использования Qbic TD-0350 в системе DeskWare | D27: =IFERROR(VLOOKUP($B27,Подбор[#All],4,0),"") | E27: =IFERROR(VLOOKUP($B27,Подбор[#All],5,0),"") | F27: =IFERROR(VLOOKUP($B27,Подбор[#All],19,0),"") -> Под заказ
A28: https://ipmatika.kz/products/doortablet-on-premise/DT-RMO/ | B28: DT-RMO | C28: OEM Room Licence - Лицензия для подключения 1 ПК Qbic TD-1050/TD-1060 для переговорной | D28: =IFERROR(VLOOKUP($B28,Подбор[#All],4,0),"") | E28: =IFERROR(VLOOKUP($B28,Подбор[#All],5,0),"") | F28: =IFERROR(VLOOKUP($B28,Подбор[#All],19,0),"") -> Под заказ
A29: https://ipmatika.kz/products/doortablet-on-premise/DT-SR/ | B29: DT-SR | C29: Standard Server Licence - Лицензия на серверное ПО для 1-9 переговорных | D29: =IFERROR(VLOOKUP($B29,Подбор[#All],4,0),"") | E29: =IFERROR(VLOOKUP($B29,Подбор[#All],5,0),"") | F29: =IFERROR(VLOOKUP($B29,Подбор[#All],19,0),"") -> Под заказ
A30: https://ipmatika.kz/products/doortablet-on-premise/DT-WF/ | B30: DT-WF | C30: Wayfinding Interactivity Licence - Лицензия для ПК с Touch-screen дисплеем | D30: =IFERROR(VLOOKUP($B30,Подбор[#All],4,0),"") | E30: =IFERROR(VLOOKUP($B30,Подбор[#All],5,0),"") | F30: =IFERROR(VLOOKUP($B30,Подбор[#All],19,0),"") -> Под заказ
B31: BXT-512_DT-EN | C31: ПК BXT-512 в комплекте с ПО DoorTablet Enterprise Server Win IoT | D31: =IFERROR(VLOOKUP($B31,Подбор[#All],4,0),"") | E31: =IFERROR(VLOOKUP($B31,Подбор[#All],5,0),"") | F31: =IFERROR(VLOOKUP($B31,Подбор[#All],19,0),"") -> Под заказ
B32: BXT-512_DT-SR | C32: ПК BXT-512 в комплекте с ПО DoorTablet Standard Server Win IoT | D32: =IFERROR(VLOOKUP($B32,Подбор[#All],4,0),"") | E32: =IFERROR(VLOOKUP($B32,Подбор[#All],5,0),"") | F32: =IFERROR(VLOOKUP($B32,Подбор[#All],19,0),"") -> Под заказ
B33: UtiClock_ | C33: Программное обеспечение "Система бронирования переговорных комнат Utinet UtiClock"__ | D33: =IFERROR(VLOOKUP($B33,Подбор[#All],4,0),"") | E33: =IFERROR(VLOOKUP($B33,Подбор[#All],5,0),"")
A34: https://ipmatika.kz/products/qbic-lanneck/ | B34: Lanneck | D34: =IFERROR(VLOOKUP($B34,Подбор[#All],4,0),"") | E34: =IFERROR(VLOOKUP($B34,Подбор[#All],5,0),"") | F34: =IFERROR(VLOOKUP($B34,Подбор[#All],19,0),"")
A35: https://ipmatika.kz/products/qbic-lanneck/TD-1050PRO-B_Lanneck/ | B35: TD-1050PRO-B_Lanneck | C35: TD-1050PRO-B в комплекте с ПО LanneckRoomBooking | D35: =IFERROR(VLOOKUP($B35,Подбор[#All],4,0),"") -> 898150 | E35: =IFERROR(VLOOKUP($B35,Подбор[#All],5,0),"") -> 763427.5 | F35: =IFERROR(VLOOKUP($B35,Подбор[#All],19,0),"")
A36: https://ipmatika.kz/products/qbic-lanneck/TD-1060-Slim-B-Lanneck/ | B36: TD-1060 Slim_B_Lanneck | C36: TD-1060 Slim чёрный в комплекте с ПО LanneckRoomBooking | D36: =IFERROR(VLOOKUP($B36,Подбор[#All],4,0),"") -> 720500 | E36: =IFERROR(VLOOKUP($B36,Подбор[#All],5,0),"") -> 612425 | F36: =IFERROR(VLOOKUP($B36,Подбор[#All],19,0),"")
A37: https://ipmatika.kz/products/qbic-lanneck/TD-1070_Lanneck/ | B37: TD-1070_Lanneck | C37: TD-1070 в комплекте с ПО LanneckRoomBooking | D37: =IFERROR(VLOOKUP($B37,Подбор[#All],4,0),"") -> 1053250 | E37: =IFERROR(VLOOKUP($B37,Подбор[#All],5,0),"") -> 895262.5 | F37: =IFERROR(VLOOKUP($B37,Подбор[#All],19,0),"")
B38: T-Mate | D38: =IFERROR(VLOOKUP($B38,Подбор[#All],4,0),"") | E38: =IFERROR(VLOOKUP($B38,Подбор[#All],5,0),"") | F38: =IFERROR(VLOOKUP($B38,Подбор[#All],19,0),"")
B39: TD-1060 Slim_T-Mate | C39: TD-1060 Slim чёрный в комплекте с ПО T-Mate | D39: =IFERROR(VLOOKUP($B39,Подбор[#All],4,0),"") | E39: =IFERROR(VLOOKUP($B39,Подбор[#All],5,0),"") | F39: =IFERROR(VLOOKUP($B39,Подбор[#All],19,0),"")
B40: TD-1070-L_T-Mate | C40: TD-1070 Lite в комплекте с ПО T-Mate | D40: =IFERROR(VLOOKUP($B40,Подбор[#All],4,0),"") | E40: =IFERROR(VLOOKUP($B40,Подбор[#All],5,0),"") | F40: =IFERROR(VLOOKUP($B40,Подбор[#All],19,0),"")
B41: TD-1070_T-Mate | C41: TD-1070 в комплекте с ПО T-Mate | D41: =IFERROR(VLOOKUP($B41,Подбор[#All],4,0),"") | E41: =IFERROR(VLOOKUP($B41,Подбор[#All],5,0),"") | F41: =IFERROR(VLOOKUP($B41,Подбор[#All],19,0),"")
A42: https://ipmatika.kz/products/aksessuary-dlya-panelnykh-kompyuterov/ | B42: Аксессуары | D42: =IFERROR(VLOOKUP($B42,Подбор[#All],4,0),"") -> 0 | E42: =IFERROR(VLOOKUP($B42,Подбор[#All],5,0),"") -> 0 | F42: =IFERROR(VLOOKUP($B42,Подбор[#All],19,0),"")
A43: https://ipmatika.kz/products/aksessuary-dlya-panelnykh-kompyuterov/qbic-ac-112/ | B43: AC-112B | C43: Qbic AC-112, Подставка для TD-1050 PRO/TD-1060 Slim, черный | D43: =IFERROR(VLOOKUP($B43,Подбор[#All],4,0),"") -> 85250 | E43: =IFERROR(VLOOKUP($B43,Подбор[#All],5,0),"") -> 72462.5 | F43: =IFERROR(VLOOKUP($B43,Подбор[#All],19,0),"")
A44: https://ipmatika.kz/products/aksessuary-dlya-panelnykh-kompyuterov/qbic-ac-112W/ | B44: AC-112W | C44: Qbic AC-112W, Подставка для TD-1050 PRO/TD-1060 Slim/TD-1070, серебристая | D44: =IFERROR(VLOOKUP($B44,Подбор[#All],4,0),"") -> 85250 | E44: =IFERROR(VLOOKUP($B44,Подбор[#All],5,0),"") -> 72462.5 | F44: =IFERROR(VLOOKUP($B44,Подбор[#All],19,0),"")
A45: https://ipmatika.kz/products/aksessuary-dlya-panelnykh-kompyuterov/ac-120/ | B45: AC-120 | C45: Qbic AC-120, Врезное крепление для скрытой установки TD-1050 PRO | D45: =IFERROR(VLOOKUP($B45,Подбор[#All],4,0),"") -> 412500 | E45: =IFERROR(VLOOKUP($B45,Подбор[#All],5,0),"") -> 350625 | F45: =IFERROR(VLOOKUP($B45,Подбор[#All],19,0),"") -> EOL
A46: https://ipmatika.kz/products/aksessuary-dlya-panelnykh-kompyuterov/ac-121/ | B46: AC-121 | C46: Qbic AC-121, Врезное крепление для скрытой установки TD-1070 | D46: =IFERROR(VLOOKUP($B46,Подбор[#All],4,0),"") -> 326700 | E46: =IFERROR(VLOOKUP($B46,Подбор[#All],5,0),"") -> 277695 | F46: =IFERROR(VLOOKUP($B46,Подбор[#All],19,0),"") -> Под заказ
A47: https://ipmatika.kz/products/aksessuary-dlya-panelnykh-kompyuterov/ac-210.ex/ | B47: AC-210.Ex | C47: Qbic AC-210.Ex, хаб RS-232 для подключения 10 сенсоров/индикаторов занятости | D47: =IFERROR(VLOOKUP($B47,Подбор[#All],4,0),"") -> 167750 | E47: =IFERROR(VLOOKUP($B47,Подбор[#All],5,0),"") -> 142587.5 | F47: =IFERROR(VLOOKUP($B47,Подбор[#All],19,0),"") -> Под заказ
A48: https://ipmatika.kz/products/aksessuary-dlya-panelnykh-kompyuterov/as-211/ | B48: AC-211 | C48: Qbic AC-211, Датчик занятости помещения | D48: =IFERROR(VLOOKUP($B48,Подбор[#All],4,0),"") -> 118250 | E48: =IFERROR(VLOOKUP($B48,Подбор[#All],5,0),"") -> 100512.5 | F48: =IFERROR(VLOOKUP($B48,Подбор[#All],19,0),"")
A49: https://ipmatika.kz/products/aksessuary-dlya-panelnykh-kompyuterov/Qbic_AC_212/ | B49: AC-212 | C49: Qbic AC-212, Индикаторная лампа светодиодная | D49: =IFERROR(VLOOKUP($B49,Подбор[#All],4,0),"") -> 134750 | E49: =IFERROR(VLOOKUP($B49,Подбор[#All],5,0),"") -> 114537.5 | F49: =IFERROR(VLOOKUP($B49,Подбор[#All],19,0),"") -> Под заказ
A50: https://ipmatika.kz/products/aksessuary-dlya-panelnykh-kompyuterov/ac-500/ | B50: AC-500 | C50: Qbic AC-500, Модуль GPIO реле/сухие контакты для TD-1050/TD-1060/TD-0350 в защитном корпусе | D50: =IFERROR(VLOOKUP($B50,Подбор[#All],4,0),"") | E50: =IFERROR(VLOOKUP($B50,Подбор[#All],5,0),"") | F50: =IFERROR(VLOOKUP($B50,Подбор[#All],19,0),"")
A51: https://ipmatika.kz/products/aksessuary-dlya-panelnykh-kompyuterov/qbic-ac-610/ | B51: AC-610 | C51: Qbic AC-610, Датчик занятости рабочего места для TD-0350 | D51: =IFERROR(VLOOKUP($B51,Подбор[#All],4,0),"") -> 90750 | E51: =IFERROR(VLOOKUP($B51,Подбор[#All],5,0),"") -> 77137.5 | F51: =IFERROR(VLOOKUP($B51,Подбор[#All],19,0),"")
A52: https://ipmatika.kz/products/aksessuary-dlya-panelnykh-kompyuterov/qbic-ac-620/ | B52: AC-620 | C52: Qbic AC-620, POE-адаптер для TD-0350, RJ45, USBx2 | D52: =IFERROR(VLOOKUP($B52,Подбор[#All],4,0),"") -> 90750 | E52: =IFERROR(VLOOKUP($B52,Подбор[#All],5,0),"") -> 77137.5 | F52: =IFERROR(VLOOKUP($B52,Подбор[#All],19,0),"")
A53: https://ipmatika.kz/products/aksessuary-dlya-panelnykh-kompyuterov/qbic-cb-110/ | B53: CB-110 | C53: Qbic CB-110, Кабель USB на micro USB L-типа, 3 м для TD-0350 | D53: =IFERROR(VLOOKUP($B53,Подбор[#All],4,0),"") -> 13200 | E53: =IFERROR(VLOOKUP($B53,Подбор[#All],5,0),"") -> 11220 | F53: =IFERROR(VLOOKUP($B53,Подбор[#All],19,0),"")
A54: https://ipmatika.kz/products/aksessuary-dlya-panelnykh-kompyuterov/ms-1070/ | B54: MS-1070 | C54: Qbic MS-1070, настольная подставка TD-1070 с органайзером проводов | D54: =IFERROR(VLOOKUP($B54,Подбор[#All],4,0),"") -> 99000 | E54: =IFERROR(VLOOKUP($B54,Подбор[#All],5,0),"") -> 84150 | F54: =IFERROR(VLOOKUP($B54,Подбор[#All],19,0),"") -> NEW
A55: https://ipmatika.kz/products/aksessuary-dlya-panelnykh-kompyuterov/ms-2000/ | B55: MS-2000 | C55: Qbic MS-2000, монтажное крепление/органайзер для установки TD-1060/TD-1070 на стекло/керамику | D55: =IFERROR(VLOOKUP($B55,Подбор[#All],4,0),"") -> 181500 | E55: =IFERROR(VLOOKUP($B55,Подбор[#All],5,0),"") -> 154275 | F55: =IFERROR(VLOOKUP($B55,Подбор[#All],19,0),"") -> Под заказ
B56: AT-102/AC-00Q | C56: Адаптер питания USB 5В, 2А для TD-0350 | D56: =IFERROR(VLOOKUP($B56,Подбор[#All],4,0),"") | E56: =IFERROR(VLOOKUP($B56,Подбор[#All],5,0),"") | F56: =IFERROR(VLOOKUP($B56,Подбор[#All],19,0),"")
A57: https://ipmatika.kz/products/aksessuary-dlya-panelnykh-kompyuterov/AT-105_AC-00M/ | B57: AT-105/AC-00M | C57: Адаптер питания импульсный 12В,1,5А для TD-1050 PRO, TD-1060 Slim | D57: =IFERROR(VLOOKUP($B57,Подбор[#All],4,0),"") -> 13770 | E57: =IFERROR(VLOOKUP($B57,Подбор[#All],5,0),"") -> 11704.5 | F57: =IFERROR(VLOOKUP($B57,Подбор[#All],19,0),"") -> Под заказ
B58: BDG-100 | C58: BDG-100 - Адаптер BLE для подключения E-ink дисплеев | D58: =IFERROR(VLOOKUP($B58,Подбор[#All],4,0),"") -> 74250 | E58: =IFERROR(VLOOKUP($B58,Подбор[#All],5,0),"") -> 63112.5 | F58: =IFERROR(VLOOKUP($B58,Подбор[#All],19,0),"") -> Под заказ

Sheet J&R
A1: Url | B1: Артикул | C1: Описание | D1: РРЦ | E1: Дилер
B2: Средоустойчивые устройства связи
B3: JR100 всепогодные телефоны
B4: а). Взрывозащищенные
A5: https://ipmatika.kz/products/vzryvozashchishchennoe-oborudovanie/J%26R-JREX-FK-SIP/ | B5: JREX101-CB-HB-SIP | C5: JREX101-CB-HB-SIP, клавиатура, маячок, громкоговоритель, PoE, с крышкой | D5: 2236450 | E5: 1565510
A6: https://ipmatika.kz/products/vzryvozashchishchennoe-oborudovanie/J%26R-JREX-CB-SIP/ | B6: JREX101-CB-SIP | C6: JREX101-CB-SIP, PoE, без БП, с крышкой | D6: 1257860 | E6: 880500
A7: https://ipmatika.kz/products/vzryvozashchishchennoe-oborudovanie/J%26R-JREX-FK-SIP/ | B7: JREX101-FK-HB-SIP | C7: JREX101-FK-HB-SIP, клавиатура, маячок, громкоговоритель, PoE, с крышкой | D7: 2351850 | E7: 1646290
A8: https://ipmatika.kz/products/vzryvozashchishchennoe-oborudovanie/J%26R-JREX-FK-SIP/ | B8: JREX101-FK-SIP | C8: JREX101-FK-SIP, клавиатура, PoE, без БП, с крышкой | D8: 1304020 | E8: 912810
A9: https://ipmatika.kz/products/vzryvozashchishchennoe-oborudovanie/J%26R-JREX103-CB-HB-SIP/ | B9: JREX103-CB-HB-SIP | C9: JREX103-CB-HB-SIP, клавиатура, горн, маячок, без крышки, PoE, БП | D9: 2042580 | E9: 1429810
A10: https://ipmatika.kz/products/vzryvozashchishchennoe-oborudovanie/J%26R-JREX103-CB-SIP/ | B10: JREX103-CB-SIP | C10: JREX103-CB-SIP, без крышки, трубка, без клавиатуры и кнопки вызова, PoE, БП | D10: 1151690 | E10: 806180
A11: https://ipmatika.kz/products/vzryvozashchishchennoe-oborudovanie/J%26R-JREX103-CB-SIP/ | B11: JREX103-CB | C11: JREX103-CB, без крышки, трубка, без клавиатуры | D11: 811840 | E11: 568350
A12: https://ipmatika.kz/products/vzryvozashchishchennoe-oborudovanie/J%26R-JREX103-FK-HB-SIP/ | B12: JREX103-FK-HB-SIP | C12: JREX103-FK-HB-SIP, клавиатура, горн, маячок, без крышки, PoE, БП | D12: 2181060 | E12: 1526740
A13: https://ipmatika.kz/products/vzryvozashchishchennoe-oborudovanie/J%26R-JREX103-FK-SIP/ | B13: JREX103-FK-SIP | C13: JREX103-FK-SIP, клавиатура, без крышки, PoE, без БП | D13: 1197850 | E13: 838490
A14: https://ipmatika.kz/products/vzryvozashchishchennoe-oborudovanie/J%26R-JREX-CB-SIP/ | B14: JREX106-A01-CB-SIP | C14: JREX106-A01-CB-SIP, PoE, БП, с крышкой | D14: 1007440 | E14: 705090
A15: https://ipmatika.kz/products/vzryvozashchishchennoe-oborudovanie/J%26R-JREX-CB-SIP/ | B15: JREX106-A01-CB | C15: JREX106-A01-CB, с крышкой, аналоговый | D15: 859730 | E15: 601820
A16: https://ipmatika.kz/products/vzryvozashchishchennoe-oborudovanie/J%26R-JREX-FK-SIP/ | B16: JREX106-A01-SIP | C16: JREX106-A01-SIP, клавиатура, PoE, БП, с крышкой | D16: 1044370 | E16: 731060
... A25: https://ipmatika.kz/products/vzryvozashchishchennoe-oborudovanie/J%26R-JREX103-FK-SIP/ | B25: JREX106 | C25: JREX106, клавиатура, без крышки, аналоговый, взрывозащищенный | D25: 1014950 | E25: 710290
B26: б). Без крышки
A27: https://ipmatika.kz/products/promyshlennye-telefony/jr-jr103-cb-y-sip/ | B27: JR103-CB-4G | C27: JR103-CB-4G, без клавиатуры, БП, без крышки, 1 SIM | D27: 619130 | E27: 433330
A28: https://ipmatika.kz/products/promyshlennye-telefony/jr-jr103-cb-y-sip/ | B28: JR103-CB-L | C28: JR103-CB-L, без клавиатуры, без крышки, маячок, желтый, аналоговый | D28: 530840 | E28: 371590
A29: https://ipmatika.kz/products/promyshlennye-telefony/jr-jr103-cb-y-sip/ | B29: JR103-CB-SIP | C29: JR103-CB-SIP, без клавиатуры, PoE, БП, без крышки | D29: 508340 | E29: 356010
A30: https://ipmatika.kz/products/promyshlennye-telefony/jr-jr103-cb-y-sip/ | B30: JR103-CB | C30: JR103-CB, без клавиатуры, без крышки, аналоговый | D30: 416020 | E30: 291390
A31: https://ipmatika.kz/products/promyshlennye-telefony/jr-jr103-fk-y-sip/ | B31: JR103-FK-4G | C31: JR103-FK-4G, полная клавиатура, БП, без крышки | D31: 656050 | E31: 459290
A32: https://ipmatika.kz/products/promyshlennye-telefony/jr-jr103-fk-y-sip/ | B32: JR103-FK-H-4G | C32: JR103-FK-H-4G, полная клавиатура, громкоговоритель, БП, 1 SIM | D32: 758180 | E32: 530840
A33: https://ipmatika.kz/products/promyshlennye-telefony/jr-jr103-fk-y-h-sip/ | B33: JR103-FK-H-SIP | C33: JR103-FK-H-SIP, полная клавиатура, громкоговоритель, PoE, БП, без крышки | D33: 646820 | E33: 452950
A34: https://ipmatika.kz/products/promyshlennye-telefony/jr-jr103-fk-y-sip/ | B34: JR103-FK-H | C34: JR103-FK-H, полная клавиатура, громкоговоритель, аналоговый | D34: 554500 | E34: 388330
A35: https://ipmatika.kz/https://ipmatika.kz/products/promyshlennye-telefony/jr-jr103-fk-y-hb-sip/ | B35: JR103-FK-HB-4G | C35: JR103-FK-HB-4G, клавиатура, без крышки, горн, маячок, 1 SIM | D35: 785870 | E35: 549890
A36: https://ipmatika.kz/https://ipmatika.kz/products/promyshlennye-telefony/jr-jr103-fk-y-hb-sip/ | B36: JR103-FK-HB-SIP | C36: JR103-FK-HB-SIP, клавиатура, без крышки, горн, маячок, PoE, БП | D36: 665290 | E36: 465640
A37: https://ipmatika.kz/https://ipmatika.kz/products/promyshlennye-telefony/jr-jr103-fk-y-hb-sip/ | B37: JR103-FK-HB | C37: JR103-FK-HB, клавиатура, без крышки, горн, маячок, аналоговый | D37: 572970 | E37: 401020
A38: https://ipmatika.kz/products/promyshlennye-telefony/jr-jr103-fk-y-sip/ | B38: JR103-FK-SIP | C38: JR103-FK-SIP, полная клавиатура, PoE, БП, без крышки | D38: 545270 | E38: 381970
... A49: https://ipmatika.kz/products/promyshlennye-telefony/jr-jr105-fk-y-sip/ | B49: JR105-FK | C49: JR105-FK, дисплей, полная клавиатура, без крышки, желтый, аналоговый | D49: 526810 | E49: 368710
B50: в). С крышкой
A51: https://ipmatika.kz/products/analogovye-telefony/jr-jr101-3b-y/ | B51: JR101-3B-4G | C51: JR101-3B-4G, 3 кнопки, БП, с крышкой | D51: 748950 | E51: 524500
A52: https://ipmatika.kz/products/analogovye-telefony/jr-jr101-3b-y/ | B52: JR101-3B-SIP | C52: JR101-3B-SIP, 3 кнопки, БП, с крышкой | D52: 637590 | E52: 446600
A53: https://ipmatika.kz/products/analogovye-telefony/jr-jr101-3b-y/ | B53: JR101-3B | C53: JR101-3B, 3 кнопки, БП, с крышкой, аналоговый | D53: 545270 | E53: 381970
A54: https://ipmatika.kz/products/promyshlennye-telefony/jr-jr101-cb-y-sip/ | B54: JR101-CB-4G | C54: JR101-CB-4G, без клавиатуры, с крышкой, 1 SIM | D54: 693550 | E54: 485260
A55: 0 | B55: JR101-CB-L-4G | C55: JR101-CB-L-4G, без клавиатуры, маячок, с крышкой, БП, 1 SIM | D55: 730480 | E55: 511220
A56: https://ipmatika.kz/products/promyshlennye-telefony/jr-jr101-%F1b-l-sip/ | B56: JR101-CB-L-SIP | C56: JR101-CB-L-SIP, без клавиатуры, маячок, с крышкой, БП | D56: 619130 | E56: 433330
A57: 0 | B57: JR101-CB-L | C57: JR101-CB-L, без клавиатуры, маячок, с крышкой, аналоговый | D57: 526810 | E57: 368710
A58: https://ipmatika.kz/products/promyshlennye-telefony/jr-jr101-sb-sip/ | B58: JR101-CB-SIP | C58: JR101-CB-SIP, без клавиатуры, PoE, БП, с крышкой | D58: 582200 | E58: 407360
A59: https://ipmatika.kz/products/promyshlennye-telefony/jr-jr101-cb-y-sip/ | B59: JR101-CB-R-SIP | C59: JR101-CB-SIP, без клавиатуры, PoE, БП, с крышкой, красный | D59: 727020 | E59: 508910
A60: https://ipmatika.kz/products/promyshlennye-telefony/jr-jr101-cb-y-sip/ | B60: JR101-CB | C60: JR101-CB, без клавиатуры, с крышкой, аналоговый | D60: 489880 | E60: 342740
A61: https://ipmatika.kz/products/promyshlennye-telefony/jr-jr101-fk-y-sip/ | B61: JR101-FK-4G | C61: JR101-FK-4G, клавиатура, с крышкой, 1 SIM | D61: 730480 | E61: 511220
A62: https://ipmatika.kz/products/promyshlennye-telefony/jr-jr101-fk-y-h-sip/ | B62: JR101-FK-H-4G | C62: JR101-FK-H-4G, клавиатура, громкоговоритель, БП, с крышкой, 1 SIM | D62: 832030 | E62: 582200
A63: https://ipmatika.kz/products/promyshlennye-telefony/jr-jr101-fk-y-h-sip/ | B63: JR101-FK-H-SIP | C63: JR101-FK-H-SIP, клавиатура, громкоговоритель, PoE, БП, с крышкой | D63: 721250 | E63: 504880
A64: https://ipmatika.kz/products/promyshlennye-telefony/jr-jr101-fk-y-h-sip/ | B64: JR101-FK-H | C64: JR101-FK-H, клавиатура, громкоговоритель, БП, с крышкой, аналоговый | D64: 628360 | E64: 439670
A65: https://ipmatika.kz/products/promyshlennye-telefony/jr-jr101-fk-y-hb-sip/ | B65: JR101-FK-HB-4G | C65: JR101-FK-HB-4G, клавиатура, маячок, громкоговоритель, с крышкой, 1 SIM | D65: 850500 | E65: 595460
A66: https://ipmatika.kz/products/promyshlennye-telefony/jr-jr101-fk-y-hb-sip/ | B66: JR101-FK-HB-SIP | C66: JR101-FK-HB-SIP, клавиатура, маячок, громкоговоритель, PoE, БП, с крышкой, | D66: 739710 | E66: 517570
A67: https://ipmatika.kz/products/promyshlennye-telefony/jr-jr101-fk-y-hb-sip/ | B67: JR101-FK-HB | C67: JR101-FK-HB, клавиатура, маячок, громкоговоритель, с крышкой, аналоговый | D67: 646820 | E67: 452950
A68: https://ipmatika.kz/products/promyshlennye-telefony/jr-jr101-fk-l/ | B68: JR101-FK-L-4G | C68: JR101-FK-L-4G, клавиатура, маячок, с крышкой, 1 SIM | D68: 767410 | E68: 537190
A69: https://ipmatika.kz/products/promyshlennye-telefony/jr-jr101-fk-l-sip/ | B69: JR101-FK-L-SIP | C69: JR101-FK-L-SIP, клавиатура, маячок, PoE, с крышкой, желтый | D69: 656050 | E69: 459290
... A78: https://ipmatika.kz/products/promyshlennye-telefony/jr-jr102-sc-y-sip/ | B78: JR102-SC | C78: JR102-SC, 1 кнопка, с крышкой, аналоговая | D78: 452950 | E78: 317350
B79: JR200 общепользовательские телефоны
B80: г). Горячая линия (без кнопок)
A81: https://ipmatika.kz/products/obshchestvennye-telefony-s-trubkoy/J%26R-JR202-CB-OW-SIP/ | B81: JR202-CB-4G | C81: JR202-CB-4G, без кнопок, БП, 1 SIM | D81: 452950 | E81: 317350
A82: https://ipmatika.kz/products/obshchestvennye-telefony-s-trubkoy/J%26R-JR202-CB-OW-SIP/ | B82: JR202-CB-SIP | C82: JR202-CB-SIP, без кнопок, PoE, БП | D82: 323700 | E82: 226770
A83: https://ipmatika.kz/products/obshchestvennye-telefony-s-trubkoy/J%26R-JR202-CB-OW-SIP/ | B83: JR202-CB | C83: JR202-CB, без кнопок, серый, аналоговый | D83: 231380 | E83: 162140
A84: https://ipmatika.kz/products/asepticheskie-telefony-dlya-chistykh-pomeshcheniy/J%26R-JR209-FK-SIP/ | B84: JR208-CB-4G | C84: JR208-CB-4G, без клавиатуры, врезной, БП, 1 SIM | D84: 545270 | E84: 381970
A85: https://ipmatika.kz/products/asepticheskie-telefony-dlya-chistykh-pomeshcheniy/J%26R-JR209-FK-SIP/ | B85: JR208-CB-SIP | C85: JR208-CB-SIP, без клавиатуры, врезной, PoE, БП, серый | D85: 434490 | E85: 304080
A86: https://ipmatika.kz/products/asepticheskie-telefony-dlya-chistykh-pomeshcheniy/J%26R-JR209-FK-SIP/ | B86: JR208-CB | C86: JR208-CB, без клавиатуры, врезной, аналоговый | D86: 342170 | E86: 239460
A87: https://ipmatika.kz/products/obshchestvennye-telefony-s-trubkoy/J%26R-JR211-FK-SIP/ | B87: JR210-1B-4G | C87: JR210-1B-4G, накладной, без клавиатуры, БП, 1 SIM | D87: 563730 | E87: 394670
A88: https://ipmatika.kz/products/obshchestvennye-telefony-s-trubkoy/J%26R-JR211-FK-SIP/ | B88: JR210-1B-SIP | C88: JR210-1B-SIP, накладной, без клавиатуры, PoE, БП | D88: 452950 | E88: 317350
A89: https://ipmatika.kz/products/obshchestvennye-telefony-s-trubkoy/J%26R-JR211-FK-SIP/ | B89: JR210-1B | C89: JR210-1B, накладной, без клавиатуры, аналоговый | D89: 360630 | E89: 252730
A90: https://ipmatika.kz/products/obshchestvennye-telefony-s-trubkoy/J%26R-JR211-FK-SIP/ | B90: JR211-CB-4G | C90: JR211-CB-4G, накладной, без клавиатуры, БП, 1 SIM | D90: 499110 | E90: 349660
A91: https://ipmatika.kz/products/obshchestvennye-telefony-s-trubkoy/J%26R-JR211-FK-SIP/ | B91: JR211-CB-SIP | C91: JR211-CB-SIP, накладной, без клавиатуры, PoE, БП | D91: 388330 | E91: 271770
A92: https://ipmatika.kz/products/obshchestvennye-telefony-s-trubkoy/J%26R-JR211-FK-SIP/ | B92: JR211-CB | C92: JR211-CB, накладной, без клавиатуры, аналоговый | D92: 296010 | E92: 207150
B93: д). Общественные телефоны с клавиатурой
A94: https://ipmatika.kz/products/obshchestvennye-telefony-s-trubkoy/jr-jr201-fk-ow-sip/ | B94: JR201-FK-SIP | C94: JR201-FK-SIP, клавиатура, накладной, PoE, БП | D94: 388330 | E94: 271770
A95: https://ipmatika.kz/products/obshchestvennye-telefony-s-trubkoy/jr-jr201-fk-ow-sip/ | B95: JR201-FK-4G | C95: JR201-FK-SIP, клавиатура, накладной, БП, 1 SIM | D95: 536040 | E95: 375050
A96: https://ipmatika.kz/products/obshchestvennye-telefony-s-trubkoy/JR201-FK-VC-SIP/ | B96: JR201-FK-VC-4G | C96: JR201-FK-VC-4G, клавиатура, накладной, БП, 1 SIM | D96: 600660 | E96: 420640
A97: https://ipmatika.kz/products/obshchestvennye-telefony-s-trubkoy/JR201-FK-VC-SIP/ | B97: JR201-FK-VC-SIP | C97: JR201-FK-VC-SIP, клавиатура, накладной, PoE, без БП, стальной | D97: 452950 | E97: 317350
A98: https://ipmatika.kz/products/analogovye-telefony/jr-jr201-fk-vc/ | B98: JR201-FK-VC | C98: JR201-FK-VC, клавиатура, накладной, стальной, аналоговый | D98: 360630 | E98: 252730
A99: https://ipmatika.kz/products/obshchestvennye-telefony-s-trubkoy/jr-jr201-fk-ow-sip/ | B99: JR201-FK | C99: JR201-FK, клавиатура, накладной, серый, аналоговый | D99: 296010 | E99: 207150
A100: 0 | B100: JR202-FK-4G | C100: JR202-FK-4G, клавиатура, накладной, БП, серый | D100: 452950 | E100: 317350
A101: 0 | B101: JR202-FK-SIP | C101: JR202-FK-SIP, клавиатура, накладной, PoE, БП, серый | D101: 342170 | E101: 239460
A102: https://ipmatika.kz/products/obshchestvennye-telefony-s-trubkoy/jr-jr202-fk-ow-sip/ | B102: JR202-FK | C102: JR202-FK, клавиатура, накладной, серый, аналоговый | D102: 249850 | E102: 174840
A103: https://ipmatika.kz/products/obshchestvennye-telefony-s-trubkoy/jr-jr203-fk-ow-sip/ | B103: JR203-FK-4G | C103: JR203-FK-4G, клавиатура, накладной, БП, серый, 1 SIM | D103: 517570 | E103: 362360
A104: https://ipmatika.kz/products/obshchestvennye-telefony-s-trubkoy/jr-jr203-fk-ow-sip/ | B104: JR203-FK-SIP | C104: JR203-FK-SIP, клавиатура, накладной, PoE, БП, серый | D104: 406790 | E104: 285040
A105: https://ipmatika.kz/products/obshchestvennye-telefony-s-trubkoy/jr-jr203-fk-ow-sip/ | B105: JR203-FK | C105: JR203-FK, клавиатура, накладной, серый, аналоговый | D105: 314470 | E105: 220410
A106: https://ipmatika.kz/products/obshchestvennye-telefony-s-trubkoy/J%26R-JR204-FK-SIP/ | B106: JR204-FK-4G | C106: JR204-FK-4G, клавиатура, дисплей, накладной, БП, 1 SIM | D106: 545270 | E106: 381970
A107: https://ipmatika.kz/products/obshchestvennye-telefony-s-trubkoy/J%26R-JR204-FK-SIP/ | B107: JR204-FK-SIP | C107: JR204-FK-SIP, клавиатура, дисплей, накладной, PoE, без БП, стальной | D107: 434490 | E107: 304080
A108: https://ipmatika.kz/products/analogovye-telefony/jr-jr204-fk/ | B108: JR204-FK | C108: JR204-FK, клавиатура, дисплей, накладной, стальной, аналоговый | D108: 342170 | E108: 239460
A109: https://ipmatika.kz/products/obshchestvennye-telefony-s-trubkoy/J%26R-JR205-FK-SIP/ | B109: JR205-FK-4G | C109: JR205-FK-4G, клавиатура, накладной, БП, 1 SIM | D109: 609890 | E109: 426980
A110: https://ipmatika.kz/products/obshchestvennye-telefony-s-trubkoy/J%26R-JR205-FK-SIP/ | B110: JR205-FK-SIP | C110: JR205-FK-SIP, клавиатура, накладной, PoE, без БП, серый | D110: 499110 | E110: 349660
A111: https://ipmatika.kz/products/obshchestvennye-telefony-s-trubkoy/J%26R-JR205-FK-SIP/ | B111: JR205-FK | C111: JR205-FK, клавиатура, накладной, аналоговый | D111: 406790 | E111: 285040
A112: https://ipmatika.kz/products/obshchestvennye-telefony-s-trubkoy/jr-jr206-fk-ow-3g/ | B112: JR206-FK-4G | C112: JR206-FK-4G, клавиатура, накладной, БП | D112: 517570 | E112: 362360
A113: https://ipmatika.kz/products/obshchestvennye-telefony-s-trubkoy/jr-jr206-fk-ow-3g/ | B113: JR206-FK-SIP | C113: JR206-FK-SIP, клавиатура, накладной, PoE, БП | D113: 406790 | E113: 285040
... A131: https://ipmatika.kz/products/obshchestvennye-telefony-s-trubkoy/J%26R-JR211-FK-SIP/ | B131: JR213-FK-SIP | C131: JR213-FK-SIP, клавиатура, PoE, БП, экран, камера, серый | D131: 1660030 | E131: 1162080
B132: JR300 панели и колонны
B133: е). Вызывные панели
A134: https://ipmatika.kz/products/vyzyvnye-paneli/jr-jr301-sc-sip/ | B134: JR213-2B-4G | C134: JR213-2B-4G, 2 кнопки, накладной, PoE, БП, камера, экран, 1 SIM | D134: 1807750 | E134: 1265370
A135: https://ipmatika.kz/products/vyzyvnye-paneli/jr-jr301-sc-sip/ | B135: JR213-2B-SIP | C135: JR213-2B-SIP, 2 кнопки, накладной, PoE, БП, камера, экран | D135: 1368070 | E135: 957820
A136: https://ipmatika.kz/products/analogovye-vyzyvnye-paneli/jr-jr301-2b/ | B136: JR301-2B-4G | C136: JR301-2B-4G, 2 кнопки, накладной, БП, стальной | D136: 537760 | E136: 376200
A137: https://ipmatika.kz/products/analogovye-vyzyvnye-paneli/jr-jr301-2b-iw/ | B137: JR301-2B-IW-4G | C137: JR301-2B-IW-4G, 2 кнопки, врезной, стальной | D137: 526810 | E137: 368710
A138: https://ipmatika.kz/products/vyzyvnye-paneli/jr-jr301-2b-iw-sip/ | B138: JR301-2B-IW-SIP | C138: JR301-2B-IW-SIP, 2 кнопки, врезной, PoE, БП, стальной | D138: 413130 | E138: 289080
A139: https://ipmatika.kz/products/analogovye-vyzyvnye-paneli/jr-jr301-2b-iw/ | B139: JR301-2B-IW | C139: JR301-2B-IW, 2 кнопки, врезной, стальной, аналоговый | D139: 319090 | E139: 223300
A140: https://ipmatika.kz/products/vyzyvnye-paneli/jr-jr301-2b-sip/ | B140: JR301-2B-SIP | C140: JR301-2B-SIP, 2 кнопки, накладной, PoE, БП, стальной | D140: 424670 | E140: 297160
A141: https://ipmatika.kz/products/vyzyvnye-paneli/jr-jr301-2b-sip/ | B141: JR301-2B | C141: JR301-2B, 2 кнопки, накладной, стальной, аналоговый | D141: 330040 | E141: 230800
A142: https://ipmatika.kz/products/analogovye-vyzyvnye-paneli/jr-jr301-sc/ | B142: JR301-SC-4G | C142: JR301-SC-4G, 1 кнопка, автодозвон, накладной, БП, стальной | D142: 518730 | E142: 362940
A143: https://ipmatika.kz/products/vyzyvnye-paneli/jr-jr301-sc-iw-sip/ | B143: JR301-SC-C1-4G | C143: JR301-SC-C1-4G, 1 кнопка, врезной, БП, стальной, камера, 1 SIM | D143: 896660 | E143: 627780
...

Sheet Gigaset
A1: http://gigaset.review.ipmatika.kz/ | D1: http://prices.ipmatika.kz/
A2: Презентация по Gigaset | D2: ЦЕНА
A3: № | B3: Наименование | C3: Артикул | D3: РРЦ | E3: ДИЛЕР
A4: 1 | B4: Gigaset N670 IP PRO, базовая станция, синглсота DECT, Мини-мультисота DECT (до 3 б\с), до 20 трубок, POE | C4: S30852-H2714-R101 | D4: 234230 | E4: 175678.88
A5: 2 | B5: Gigaset N720 DM PRO SYS IM Контроллер | C5: S30852-H2315-R101 | D5: 148720 | E5: 111540
A6: 3 | B6: Gigaset N720 IP PRO SYS IM Базовая станция | C6: S30852-H2314-R101 | D6: 148720 | E6: 111540
A7: 4 | B7: Gigaset N870 IP PRO, базовая станция/DM, микросота DECT, до 60 баз, до 250 трубок, POE | C7: S30852-H2716-R101 | D7: 644650 | E7: 483495.48
A8: 5 | B8: Gigaset N870E IP PRO, базовая станция/DM, съемные внеш. Антенны, микросота DECT, до 60 баз, до 250 трубок, POE | C8: S30852-H2718-R101 | D8: 715480 | E8: 536608.8
A9: 6 | B9: Gigaset SL800H PRO Телефонный аппарат | C9: S30852-H2975-R102 | D9: 197170 | E9: 147875
A10: 7 | B10: Gigaset R700H PRO Телефонный аппарат | C10: S30852-H2976-R102 | D10: 204260 | E10: 153195.12
A11: 8 | B11: Gigaset S700H PRO Телефонный аппарат | C11: S30852-H2974-R102 | D11: 146400 | E11: 109802.68
A12: 9 | B12: Лицензия апгрейда N670 IP PRO до N870 IP PRO | C12: S30852-H2714-X3 | D12: 516510 | E12: 439040
A13: 10 | B13: Лицензия для дект менеджера GIGASET N670 IP PRO | C13: S30852-H2714-X2 | D13: 171650 | E13: 145900
A14: 11 | B14: Лицензия для дект менеджера GIGASET N870 IP PRO | C14: S30852-H2716-X2 | D14: 498060 | E14: 423360
A15: 12 | B15: Лицензия Integrator для N870/N670 IP PRO | C15: S30852-H2716-X1 | D15: 710950 | E15: 604310
... A18: 15 | B18: Крепление на опору для уличного короба ТША511 | C18: КМА1 | D18: 26850 | E18: 21480

Sheet 3CX
K1: http://prices.ipmatika.kz
A2: Годовые лицензии 3CX | I2: =Телефония!G1 -> 0
A3: ОВ | C3: Basic /РРЦ/тг | E3: Pro/РРЦ /тг | G3: Enterprise /РРЦ/тг
C4: =VLOOKUP(B4,[1]Подбор!$A$6:$AD$51,29,0) -> #N/A | E4: =VLOOKUP(D4,[1]Подбор!$A$7:$AD$51,29,0) -> #N/A | G4: =VLOOKUP(F4,[1]Подбор!$A$6:$AD$51,29,0) -> #N/A
A5: 4 | C5: . | D5: 3CXNAP4M12 | E5: =VLOOKUP(D5,Подбор!$A:$S,4,0) -> 242680
A6: 8 | B6: 3CXNAB8M12 | C6: =VLOOKUP(B6,Подбор!$A:$S,4,0) -> 242680 | D6: 3CXNAP8M12 | E6: =VLOOKUP(D6,Подбор!$A:$S,4,0) -> 323570 | F6: 3CXNAE8M12 | G6: =VLOOKUP(F6,Подбор!$A:$S,4,0) -> 468320
A7: 16 | B7: 3CXNAB16M12 | C7: =VLOOKUP(B7,Подбор!$A:$S,4,0) -> 485350 | D7: 3CXNAP16M12 | E7: =VLOOKUP(D7,Подбор!$A:$S,4,0) -> 647140 | F7: 3CXNAE16M12 | G7: =VLOOKUP(F7,Подбор!$A:$S,4,0) -> 889820
A8: 24 | B8: 3CXNAB24M12 | C8: =VLOOKUP(B8,Подбор!$A:$S,4,0) -> 668430 | D8: 3CXNAP24M12 | E8: =VLOOKUP(D8,Подбор!$A:$S,4,0) -> 889820 | F8: 3CXNAE24M12 | G8: =VLOOKUP(F8,Подбор!$A:$S,4,0) -> 1213390
A9: 32 | B9: 3CXNAB32M12 | C9: =VLOOKUP(B9,Подбор!$A:$S,4,0) -> 821700 | D9: 3CXNAP32M12 | E9: =VLOOKUP(D9,Подбор!$A:$S,4,0) -> 1094180 | F9: 3CXNAE32M12 | G9: =VLOOKUP(F9,Подбор!$A:$S,4,0) -> 1456060
A10: 48 | B10: 3CXNAB48M12 | C10: =VLOOKUP(B10,Подбор!$A:$S,4,0) -> 1213390 | D10: 3CXNAP48M12 | E10: =VLOOKUP(D10,Подбор!$A:$S,4,0) -> 1617850 | F10: 3CXNAE48M12 | G10: =VLOOKUP(F10,Подбор!$A:$S,4,0) -> 2022310
A11: 64 | B11: 3CXNAB64M12 | C11: =VLOOKUP(B11,Подбор!$A:$S,4,0) -> 1639140 | D11: 3CXNAP64M12 | E11: =VLOOKUP(D11,Подбор!$A:$S,4,0) -> 2184100 | F11: 3CXNAE64M12 | G11: =VLOOKUP(F11,Подбор!$A:$S,4,0) -> 2618360
A12: 96 | B12: 3CXNAB96M12 | C12: =VLOOKUP(B12,Подбор!$A:$S,4,0) -> 2426770 | D12: 3CXNAP96M12 | E12: =VLOOKUP(D12,Подбор!$A:$S,4,0) -> 3235700 | F12: 3CXNAE96M12 | G12: =VLOOKUP(F12,Подбор!$A:$S,4,0) -> 3882840
A13: 128 | B13: 3CXNAB128M12 | C13: =VLOOKUP(B13,Подбор!$A:$S,4,0) -> 3337880 | D13: 3CXNAP128M12 | E13: =VLOOKUP(D13,Подбор!$A:$S,4,0) -> 4449090 | F13: 3CXNAE128M12 | G13: =VLOOKUP(F13,Подбор!$A:$S,4,0) -> 5338900
A14: 192 | B14: 3CXNAB192M12 | C14: =VLOOKUP(B14,Подбор!$A:$S,4,0) -> 5011080 | D14: 3CXNAP192M12 | E14: =VLOOKUP(D14,Подбор!$A:$S,4,0) -> 6675760 | F14: 3CXNAE192M12 | G14: =VLOOKUP(F14,Подбор!$A:$S,4,0) -> 8008350
A15: 256 | B15: 3CXNAB256M12 | C15: =VLOOKUP(B15,Подбор!$A:$S,4,0) -> 6675760 | D15: 3CXNAP256M12 | E15: =VLOOKUP(D15,Подбор!$A:$S,4,0) -> 8898170 | F15: 3CXNAE256M12 | G15: =VLOOKUP(F15,Подбор!$A:$S,4,0) -> 10677810
A16: 512 | B16: 3CXNAB512M12 | C16: =VLOOKUP(B16,Подбор!$A:$S,4,0) -> 10920480 | D16: 3CXNAP512M12 | E16: =VLOOKUP(D16,Подбор!$A:$S,4,0) -> 14560640 | F16: 3CXNAE512M12 | G16: =VLOOKUP(F16,Подбор!$A:$S,4,0) -> 17472770
A17: 1024 | B17: 3CXNAB1024M12 | C17: =VLOOKUP(B17,Подбор!$A:$S,4,0) -> 20023010 | D17: 3CXNAP1024M12 | E17: =VLOOKUP(D17,Подбор!$A:$S,4,0) -> 26694510 | F17: 3CXNAE1024M12 | G17: =VLOOKUP(F17,Подбор!$A:$S,4,0) -> 32033420
C18: Enterprise Plus 8SC (годовая) | F18: 3CXNAEP8M12 | G18: =VLOOKUP(F18,Подбор!$A:$S,4,0) -> 608820
E19: Enterprise Plus 16SC (годовая) | F19: 3CXNAEP16M12 | G19: =VLOOKUP(F19,Подбор!$A:$S,4,0) -> 1132490
A21: Скидки согласно партнёрского статуса:
A22: Affiliate 10%
A23: Bronze 15%
A24: Silver 20%
A25: Gold 25%
A27: Условия и положения
A28: Рекомендовання розничная цена включает НДС 12% и Роялти 15%. Доставка программного обеспечения происходит электронным способом через сеть Интернет. Программное обеспечение активируется с помощью электронного лицензионного ключа.
A30: Референтная ссылка от IPmatika:
A31: https://www.3cx.com/partners/apply/?distributorID=240660

Sheet Подбор
A1: Артикул | B1: Номенклатура.Производитель (бренд) | C1: Номенклатура на 6 января 2026 г. | D1: KZ РРЦ | E1: KZ Дилер | F1: % | G1: ALM а 23 февраля 2026 г. | H1: AlmRes | I1: AlmAway | J1: Ast | K1: AstRes | L1: AstAway | M1: Alm2 | N1: Msk ст на 26 мая 2025 г. | O1: MskRes | P1: MskAway | Q1: Pic | R1: URL | S1: Status | W1: KZ РРЦ | X1: KZ Дилер | Y1: % | Z1: =Z5 -> 0 | AA1: AlmRes | AB1: AlmAway | AC1: Ast | AD1: AstRes | AE1: AstAway | AF1: Alm2 | AG1: Msk ст на 26 мая 2025 г. | AH1: MskRes | AI1: MskAway | AJ1: Pic | AK1: URL | AL1: Status
A2: 3cx | W2: =IFERROR(VLOOKUP(Подбор[[#This Row],[Артикул]],[1]Подбор!$CJ:$CW,3,0),"") | X2: =IFERROR(VLOOKUP(Подбор[[#This Row],[Артикул]],[1]Подбор!$CJ:$CW,3,0),"") | Y2: =IFERROR(VLOOKUP(Подбор[[#This Row],[Артикул]],[1]Подбор!$CJ:$CW,4,0),"") | Z2: =IFERROR(VLOOKUP(Подбор[[#This Row],[Артикул]],[1]Подбор!$CJ:$CW,5,0),"") | AA2: =IFERROR(VLOOKUP(Подбор[[#This Row],[Артикул]],[1]Подбор!$CJ:$CW,6,0),"") | AB2: =IFERROR(VLOOKUP(Подбор[[#This Row],[Артикул]],[1]Подбор!$CJ:$CW,7,0),"") | AC2: =IFERROR(VLOOKUP(Подбор[[#This Row],[Артикул]],[1]Подбор!$CJ:$CW,8,0),"") | AD2: =IFERROR(VLOOKUP(Подбор[[#This Row],[Артикул]],[1]Подбор!$CJ:$CW,9,0),"") | AE2: =IFERROR(VLOOKUP(Подбор[[#This Row],[Артикул]],[1]Подбор!$CJ:$CW,10,0),"") | AF2: =IFERROR(VLOOKUP(Подбор[[#This Row],[Артикул]],[1]Подбор!$CJ:$CW,11,0),"") | AG2: =IFERROR(VLOOKUP(Подбор[[#This Row],[Артикул]],[1]Подбор!$CJ:$CW,12,0),"") | AH2: =IFERROR(VLOOKUP(Подбор[[#This Row],[Артикул]],[1]Подбор!$CJ:$CW,13,0),"") | AI2: =IFERROR(VLOOKUP(Подбор[[#This Row],[Артикул]],[1]Подбор!$CJ:$CW,14,0),"")
A3: dect | W3: =IFERROR(VLOOKUP(Подбор[[#This Row],[Артикул]],[1]Подбор!$CJ:$CW,3,0),"") | X3: =IFERROR(VLOOKUP(Подбор[[#This Row],[Артикул]],[1]Подбор!$CJ:$CW,3,0),"") | Y3: =IFERROR(VLOOKUP(Подбор[[#This Row],[Артикул]],[1]Подбор!$CJ:$CW,4,0),"") | Z3: =IFERROR(VLOOKUP(Подбор[[#This Row],[Артикул]],[1]Подбор!$CJ:$CW,5,0),"") | AA3: =IFERROR(VLOOKUP(Подбор[[#This Row],[Артикул]],[1]Подбор!$CJ:$CW,6,0),"") | AB3: =IFERROR(VLOOKUP(Подбор[[#This Row],[Артикул]],[1]Подбор!$CJ:$CW,7,0),"") | AC3: =IFERROR(VLOOKUP(Подбор[[#This Row],[Артикул]],[1]Подбор!$CJ:$CW,8,0),"") | AD3: =IFERROR(VLOOKUP(Подбор[[#This Row],[Артикул]],[1]Подбор!$CJ:$CW,9,0),"") | AE3: =IFERROR(VLOOKUP(Подбор[[#This Row],[Артикул]],[1]Подбор!$CJ:$CW,10,0),"") | AF3: =IFERROR(VLOOKUP(Подбор[[#This Row],[Артикул]],[1]Подбор!$CJ:$CW,11,0),"") | AG3: =IFERROR(VLOOKUP(Подбор[[#This Row],[Артикул]],[1]Подбор!$CJ:$CW,12,0),"") | AH3: =IFERROR(VLOOKUP(Подбор[[#This Row],[Артикул]],[1]Подбор!$CJ:$CW,13,0),"") | AI3: =IFERROR(VLOOKUP(Подбор[[#This Row],[Артикул]],[1]Подбор!$CJ:$CW,14,0),"")
D4: 85 | E4: 65 | G4: ALM а 23 февраля 2026 г. | H4: 0 | I4: 0 | J4: 0 | K4: 0 | L4: 0 | M4: 0 | N4: 11 | O4: 10 | P4: 12 | Q4: 0 | S4: 66 | W4: =IFERROR(VLOOKUP(Подбор[[#This Row],[Артикул]],[1]Подбор!$CJ:$CW,2,0),"") -> 0 | X4: =IFERROR(VLOOKUP(Подбор[[#This Row],[Артикул]],[1]Подбор!$CJ:$CW,3,0),"") -> 0 | Y4: =IFERROR(VLOOKUP(Подбор[[#This Row],[Артикул]],[1]Подбор!$CJ:$CW,4,0),"") -> 0 | Z4: =IFERROR(VLOOKUP(Подбор[[#This Row],[Артикул]],[1]Подбор!$CJ:$CW,5,0),"") -> 0 | AA4: =IFERROR(VLOOKUP(Подбор[[#This Row],[Артикул]],[1]Подбор!$CJ:$CW,6,0),"") -> 0 | AB4: =IFERROR(VLOOKUP(Подбор[[#This Row],[Артикул]],[1]Подбор!$CJ:$CW,7,0),"") -> 0 | AC4: =IFERROR(VLOOKUP(Подбор[[#This Row],[Артикул]],[1]Подбор!$CJ:$CW,8,0),"") -> 0 | AD4: =IFERROR(VLOOKUP(Подбор[[#This Row],[Артикул]],[1]Подбор!$CJ:$CW,9,0),"") -> 0 | AE4: =IFERROR(VLOOKUP(Подбор[[#This Row],[Артикул]],[1]Подбор!$CJ:$CW,10,0),"") -> 0 | AF4: =IFERROR(VLOOKUP(Подбор[[#This Row],[Артикул]],[1]Подбор!$CJ:$CW,11,0),"") -> 0 | AG4: =IFERROR(VLOOKUP(Подбор[[#This Row],[Артикул]],[1]Подбор!$CJ:$CW,12,0),"") -> 0 | AH4: =IFERROR(VLOOKUP(Подбор[[#This Row],[Артикул]],[1]Подбор!$CJ:$CW,13,0),"") -> 0 | AI4: =IFERROR(VLOOKUP(Подбор[[#This Row],[Артикул]],[1]Подбор!$CJ:$CW,14,0),"") -> 0 | AJ4: =IFERROR(VLOOKUP(Подбор[[#This Row],[Артикул]],[1]Подбор!$CJ:$DA,15,0),"") -> 0 | AK4: =IFERROR(VLOOKUP(Подбор[[#This Row],[Артикул]],[1]Подбор!$CJ:$DA,16,0),"") -> 0 | AL4: =IFERROR(VLOOKUP(Подбор[[#This Row],[Артикул]],[1]Подбор!$CJ:$DA,17,0),"") -> 0
B5: STSS | C5: Контроллер RAID LSI MegaRAID SAS 9341-4i 4-internal channel SAS/SATA PCI-E x8 и кабель HD SAS | D5: 85 | E5: 65 | G5: ALM а 23 февраля 2026 г. | H5: 0 | I5: 0 | J5: 0 | K5: 0 | L5: 0 | M5: 0 | N5: 11 | O5: 10 | P5: 12 | Q5: 0 | S5: 66 | W5: =IFERROR(VLOOKUP(Подбор[[#This Row],[Артикул]],[1]Подбор!$CJ:$CW,2,0),"") -> 0 | X5: =IFERROR(VLOOKUP(Подбор[[#This Row],[Артикул]],[1]Подбор!$CJ:$CW,3,0),"") -> 0 | Y5: =IFERROR(VLOOKUP(Подбор[[#This Row],[Артикул]],[1]Подбор!$CJ:$CW,4,0),"") -> 0 | Z5: =IFERROR(VLOOKUP(Подбор[[#This Row],[Артикул]],[1]Подбор!$CJ:$CW,5,0),"") -> 0 | AA5: =IFERROR(VLOOKUP(Подбор[[#This Row],[Артикул]],[1]Подбор!$CJ:$CW,6,0),"") -> 0 | AB5: =IFERROR(VLOOKUP(Подбор[[#This Row],[Артикул]],[1]Подбор!$CJ:$CW,7,0),"") -> 0 | AC5: =IFERROR(VLOOKUP(Подбор[[#This Row],[Артикул]],[1]Подбор!$CJ:$CW,8,0),"") -> 0 | AD5: =IFERROR(VLOOKUP(Подбор[[#This Row],[Артикул]],[1]Подбор!$CJ:$CW,9,0),"") -> 0 | AE5: =IFERROR(VLOOKUP(Подбор[[#This Row],[Артикул]],[1]Подбор!$CJ:$CW,10,0),"") -> 0 | AF5: =IFERROR(VLOOKUP(Подбор[[#This Row],[Артикул]],[1]Подбор!$CJ:$CW,11,0),"") -> 0 | AG5: =IFERROR(VLOOKUP(Подбор[[#This Row],[Артикул]],[1]Подбор!$CJ:$CW,12,0),"") -> 0 | AH5: =IFERROR(VLOOKUP(Подбор[[#This Row],[Артикул]],[1]Подбор!$CJ:$CW,13,0),"") -> 0 | AI5: =IFERROR(VLOOKUP(Подбор[[#This Row],[Артикул]],[1]Подбор!$CJ:$CW,14,0),"") -> 0 | AJ5: =IFERROR(VLOOKUP(Подбор[[#This Row],[Артикул]],[1]Подбор!$CJ:$DA,15,0),"") -> 0 | AK5: =IFERROR(VLOOKUP(Подбор[[#This Row],[Артикул]],[1]Подбор!$CJ:$DA,16,0),"") -> 0 | AL5: =IFERROR(VLOOKUP(Подбор[[#This Row],[Артикул]],[1]Подбор!$CJ:$DA,17,0),"") -> 0
A6: S100 | B6: Yeastar | C6: S100, 100 (до 200) абонентов и 30 (до 60) вызовов, поддержка FXO, FXS, GSM, BRI | D6: 691820 | E6: 520920 | F6: -24.702957 | G6: 3 | H6: 0 | I6: 0 | J6: 1 | K6: 0 | L6: 0 | M6: 0 | N6: 0 | O6: 0 | P6: 0 | R6: https://www.ipmatika.kz/products/ip-ats-yeastar-serii-s-sredney-yemkosti/yeastar-s100/ | S6: EOL | W6: =IFERROR(VLOOKUP(Подбор[[#This Row],[Артикул]],[1]Подбор!$CJ:$CW,2,0),"") -> 691820 | X6: =IFERROR(VLOOKUP(Подбор[[#This Row],[Артикул]],[1]Подбор!$CJ:$CW,3,0),"") -> 520920 | Y6: =IFERROR(VLOOKUP(Подбор[[#This Row],[Артикул]],[1]Подбор!$CJ:$CW,4,0),"") -> -24.702957 | Z6: =IFERROR(VLOOKUP(Подбор[[#This Row],[Артикул]],[1]Подбор!$CJ:$CW,5,0),"") -> 3 | AA6: =IFERROR(VLOOKUP(Подбор[[#This Row],[Артикул]],[1]Подбор!$CJ:$CW,6,0),"") -> 0 | AB6: =IFERROR(VLOOKUP(Подбор[[#This Row],[Артикул]],[1]Подбор!$CJ:$CW,7,0),"") -> 0 | AC6: =IFERROR(VLOOKUP(Подбор[[#This Row],[Артикул]],[1]Подбор!$CJ:$CW,8,0),"") -> 1 | AD6: =IFERROR(VLOOKUP(Подбор[[#This Row],[Артикул]],[1]Подбор!$CJ:$CW,9,0),"") -> 0 | AE6: =IFERROR(VLOOKUP(Подбор[[#This Row],[Артикул]],[1]Подбор!$CJ:$CW,10,0),"") -> 0 | AF6: =IFERROR(VLOOKUP(Подбор[[#This Row],[Артикул]],[1]Подбор!$CJ:$CW,11,0),"") -> 0 | AG6: =IFERROR(VLOOKUP(Подбор[[#This Row],[Артикул]],[1]Подбор!$CJ:$CW,12,0),"") -> 0 | AH6: =IFERROR(VLOOKUP(Подбор[[#This Row],[Артикул]],[1]Подбор!$CJ:$CW,13,0),"") -> 0 | AI6: =IFERROR(VLOOKUP(Подбор[[#This Row],[Артикул]],[1]Подбор!$CJ:$CW,14,0),"") -> 0 | AJ6: =IFERROR(VLOOKUP(Подбор[[#This Row],[Артикул]],[1]Подбор!$CJ:$DA,15,0),"") | AK6: =IFERROR(VLOOKUP(Подбор[[#This Row],[Артикул]],[1]Подбор!$CJ:$DA,16,0),"") -> https://www.ipmatika.kz/products/ip-ats-yeastar-serii-s-sredney-yemkosti/yeastar-s100/ | AL6: =IFERROR(VLOOKUP(Подбор[[#This Row],[Артикул]],[1]Подбор!$CJ:$DA,17,0),"") -> EOL
A7: EHS36 sale | B7: Yealink | C7: EHS36 адаптер для беспроводных гарнитур для телефонов T4S/T40G(P)/T29G/T27G | D7: 53210 | E7: 15290 | F7: -71.2648 | G7: 1 | H7: 0 | I7: 0 | J7: 0 | K7: 0 | L7: 0 | M7: 0 | N7: 0 | O7: 0 | P7: 0 | W7: =IFERROR(VLOOKUP(Подбор[[#This Row],[Артикул]],[1]Подбор!$CJ:$CW,2,0),"") -> 53210 | X7: =IFERROR(VLOOKUP(Подбор[[#This Row],[Артикул]],[1]Подбор!$CJ:$CW,3,0),"") -> 15290 | Y7: =IFERROR(VLOOKUP(Подбор[[#This Row],[Артикул]],[1]Подбор!$CJ:$CW,4,0),"") -> -71.2648 | Z7: =IFERROR(VLOOKUP(Подбор[[#This Row],[Артикул]],[1]Подбор!$CJ:$CW,5,0),"") -> 1 | AA7: =IFERROR(VLOOKUP(Подбор[[#This Row],[Артикул]],[1]Подбор!$CJ:$CW,6,0),"") -> 0 | AB7: =IFERROR(VLOOKUP(Подбор[[#This Row],[Артикул]],[1]Подбор!$CJ:$CW,7,0),"") -> 0 | AC7: =IFERROR(VLOOKUP(Подбор[[#This Row],[Артикул]],[1]Подбор!$CJ:$CW,8,0),"") -> 0 | AD7: =IFERROR(VLOOKUP(Подбор[[#This Row],[Артикул]],[1]Подбор!$CJ:$CW,9,0),"") -> 0 | AE7: =IFERROR(VLOOKUP(Подбор[[#This Row],[Артикул]],[1]Подбор!$CJ:$CW,10,0),"") -> 0 | AF7: =IFERROR(VLOOKUP(Подбор[[#This Row],[Артикул]],[1]Подбор!$CJ:$CW,11,0),"") -> 0 | AG7: =IFERROR(VLOOKUP(Подбор[[#This Row],[Артикул]],[1]Подбор!$CJ:$CW,12,0),"") -> 0 | AH7: =IFERROR(VLOOKUP(Подбор[[#This Row],[Артикул]],[1]Подбор!$CJ:$CW,13,0),"") -> 0 | AI7: =IFERROR(VLOOKUP(Подбор[[#This Row],[Артикул]],[1]Подбор!$CJ:$CW,14,0),"") -> 0 | AJ7: =IFERROR(VLOOKUP(Подбор[[#This Row],[Артикул]],[1]Подбор!$CJ:$DA,15,0),"") | AK7: =IFERROR(VLOOKUP(Подбор[[#This Row],[Артикул]],[1]Подбор!$CJ:$DA,16,0),"") | AL7: =IFERROR(VLOOKUP(Подбор[[#This Row],[Артикул]],[1]Подбор!$CJ:$DA,17,0),"")
A8: RT10 sale | B8: Yealink | C8: RT10 DECT-репитер для SIP-телефона W52P | D8: 75510 | E8: 65280 | F8: -13.547874 | G8: 1 | H8: 0 | I8: 0 | J8: 0 | K8: 0 | L8: 0 | M8: 0 | N8: 0 | O8: 0 | P8: 0 | W8: =IFERROR(VLOOKUP(Подбор[[#This Row],[Артикул]],[1]Подбор!$CJ:$CW,2,0),"") -> 75510 | X8: =IFERROR(VLOOKUP(Подбор[[#This Row],[Артикул]],[1]Подбор!$CJ:$CW,3,0),"") -> 65280 | Y8: =IFERROR(VLOOKUP(Подбор[[#This Row],[Артикул]],[1]Подбор!$CJ:$CW,4,0),"") -> -13.547874 | Z8: =IFERROR(VLOOKUP(Подбор[[#This Row],[Артикул]],[1]Подбор!$CJ:$CW,5,0),"") -> 1 | AA8: =IFERROR(VLOOKUP(Подбор[[#This Row],[Артикул]],[1]Подбор!$CJ:$CW,6,0),"") -> 0 | AB8: =IFERROR(VLOOKUP(Подбор[[#This Row],[Артикул]],[1]Подбор!$CJ:$CW,7,0),"") -> 0 | AC8: =IFERROR(VLOOKUP(Подбор[[#This Row],[Артикул]],[1]Подбор!$CJ:$CW,8,0),"") -> 0 | AD8: =IFERROR(VLOOKUP(Подбор[[#This Row],[Артикул]],[1]Подбор!$CJ:$CW,9,0),"") -> 0 | AE8: =IFERROR(VLOOKUP(Подбор[[#This Row],[Артикул]],[1]Подбор!$CJ:$CW,10,0),"") -> 0 | AF8: =IFERROR(VLOOKUP(Подбор[[#This Row],[Артикул]],[1]Подбор!$CJ:$CW,11,0),"") -> 0 | AG8: =IFERROR(VLOOKUP(Подбор[[#This Row],[Артикул]],[1]Подбор!$CJ:$CW,12,0),"") -> 0 | AH8: =IFERROR(VLOOKUP(Подбор[[#This Row],[Артикул]],[1]Подбор!$CJ:$CW,13,0),"") -> 0 | AI8: =IFERROR(VLOOKUP(Подбор[[#This Row],[Артикул]],[1]Подбор!$CJ:$CW,14,0),"") -> 0 | AJ8: =IFERROR(VLOOKUP(Подбор[[#This Row],[Артикул]],[1]Подбор!$CJ:$DA,15,0),"") | AK8: =IFERROR(VLOOKUP(Подбор[[#This Row],[Артикул]],[1]Подбор!$CJ:$DA,16,0),"") | AL8: =IFERROR(VLOOKUP(Подбор[[#This Row],[Артикул]],[1]Подбор!$CJ:$DA,17,0),"")
A9: WF50 sale | B9: Yealink | C9: WF50 USB WiFi-адаптер для SIP-T27G/T41S/T42S/T43U/T46U(S)/T48U(S)/T53 | D9: 29990 | E9: 13060 | F9: -56.452151 | G9: 1 | H9: 0 | I9: 0 | J9: 0 | K9: 0 | L9: 0 | M9: 0 | N9: 0 | O9: 0 | P9: 0 | W9: =IFERROR(VLOOKUP(Подбор[[#This Row],[Артикул]],[1]Подбор!$CJ:$CW,2,0),"") -> 29990 | X9: =IFERROR(VLOOKUP(Подбор[[#This Row],[Артикул]],[1]Подбор!$CJ:$CW,3,0),"") -> 13060 | Y9: =IFERROR(VLOOKUP(Подбор[[#This Row],[Артикул]],[1]Подбор!$CJ:$CW,4,0),"") -> -56.452151 | Z9: =IFERROR(VLOOKUP(Подбор[[#This Row],[Артикул]],[1]Подбор!$CJ:$CW,5,0),"") -> 1 | AA9: =IFERROR(VLOOKUP(Подбор[[#This Row],[Артикул]],[1]Подбор!$CJ:$CW,6,0),"") -> 0 | AB9: =IFERROR(VLOOKUP(Подбор[[#This Row],[Артикул]],[1]Подбор!$CJ:$CW,7,0),"") -> 0 | AC9: =IFERROR(VLOOKUP(Подбор[[#This Row],[Артикул]],[1]Подбор!$CJ:$CW,8,0),"") -> 0 | AD9: =IFERROR(VLOOKUP(Подбор[[#This Row],[Артикул]],[1]Подбор!$CJ:$CW,9,0),"") -> 0 | AE9: =IFERROR(VLOOKUP(Подбор[[#This Row],[Артикул]],[1]Подбор!$CJ:$CW,10,0),"") -> 0 | AF9: =IFERROR(VLOOKUP(Подбор[[#This Row],[Артикул]],[1]Подбор!$CJ:$CW,11,0),"") -> 0 | AG9: =IFERROR(VLOOKUP(Подбор[[#This Row],[Артикул]],[1]Подбор!$CJ:$CW,12,0),"") -> 0 | AH9: =IFERROR(VLOOKUP(Подбор[[#This Row],[Артикул]],[1]Подбор!$CJ:$CW,13,0),"") -> 0 | AI9: =IFERROR(VLOOKUP(Подбор[[#This Row],[Артикул]],[1]Подбор!$CJ:$CW,14,0),"") -> 0 | AJ9: =IFERROR(VLOOKUP(Подбор[[#This Row],[Артикул]],[1]Подбор!$CJ:$DA,15,0),"") | AK9: =IFERROR(VLOOKUP(Подбор[[#This Row],[Артикул]],[1]Подбор!$CJ:$DA,16,0),"") | AL9: =IFERROR(VLOOKUP(Подбор[[#This Row],[Артикул]],[1]Подбор!$CJ:$DA,17,0),"")
A10: SIP-T42G sale | B10: Yealink | C10: SIP-T42G,3 аккаунта,BLF,PoE, GigE, без БП | D10: 63420 | E10: 54060 | F10: -14.758751 | G10: 1 | H10: 0 | I10: 0 | J10: 0 | K10: 0 | L10: 0 | M10: 0 | N10: 0 | O10: 0 | P10: 0 | W10: =IFERROR(VLOOKUP(Подбор[[#This Row],[Артикул]],[1]Подбор!$CJ:$CW,2,0),"") -> 63420 | X10: =IFERROR(VLOOKUP(Подбор[[#This Row],[Артикул]],[1]Подбор!$CJ:$CW,3,0),"") -> 54060 | Y10: =IFERROR(VLOOKUP(Подбор[[#This Row],[Артикул]],[1]Подбор!$CJ:$CW,4,0),"") -> -14.758751 | Z10: =IFERROR(VLOOKUP(Подбор[[#This Row],[Артикул]],[1]Подбор!$CJ:$CW,5,0),"") -> 1 | AA10: =IFERROR(VLOOKUP(Подбор[[#This Row],[Артикул]],[1]Подбор!$CJ:$CW,6,0),"") -> 0 | AB10: =IFERROR(VLOOKUP(Подбор[[#This Row],[Артикул]],[1]Подбор!$CJ:$CW,7,0),"") -> 0 | AC10: =IFERROR(VLOOKUP(Подбор[[#This Row],[Артикул]],[1]Подбор!$CJ:$CW,8,0),"") -> 0 | AD10: =IFERROR(VLOOKUP(Подбор[[#This Row],[Артикул]],[1]Подбор!$CJ:$CW,9,0),"") -> 0 | AE10: =IFERROR(VLOOKUP(Подбор[[#This Row],[Артикул]],[1]Подбор!$CJ:$CW,10,0),"") -> 0 | AF10: =IFERROR(VLOOKUP(Подбор[[#This Row],[Артикул]],[1]Подбор!$CJ:$CW,11,0),"") -> 0 | AG10: =IFERROR(VLOOKUP(Подбор[[#This Row],[Артикул]],[1]Подбор!$CJ:$CW,12,0),"") -> 0 | AH10: =IFERROR(VLOOKUP(Подбор[[#This Row],[Артикул]],[1]Подбор!$CJ:$CW,13,0),"") -> 0 | AI10: =IFERROR(VLOOKUP(Подбор[[#This Row],[Артикул]],[1]Подбор!$CJ:$CW,14,0),"") -> 0 | AJ10: =IFERROR(VLOOKUP(Подбор[[#This Row],[Артикул]],[1]Подбор!$CJ:$DA,15,0),"") | AK10: =IFERROR(VLOOKUP(Подбор[[#This Row],[Артикул]],[1]Подбор!$CJ:$DA,16,0),"") | AL10: =IFERROR(VLOOKUP(Подбор[[#This Row],[Артикул]],[1]Подбор!$CJ:$DA,17,0),"")
A11: FH3PB sale | B11: Fanvil | C11: H3 отельный, 2 аккаунта, без экрана, PoE, б/п | G11: 1 | H11: 0 | I11: 0 | J11: 0 | K11: 0 | L11: 0 | M11: 0 | N11: 0 | O11: 0 | P11: 0 | W11: =IFERROR(VLOOKUP(Подбор[[#This Row],[Артикул]],[1]Подбор!$CJ:$CW,2,0),"") | X11: =IFERROR(VLOOKUP(Подбор[[#This Row],[Артикул]],[1]Подбор!$CJ:$CW,3,0),"") | Y11: =IFERROR(VLOOKUP(Подбор[[#This Row],[Артикул]],[1]Подбор!$CJ:$CW,4,0),"") | Z11: =IFERROR(VLOOKUP(Подбор[[#This Row],[Артикул]],[1]Подбор!$CJ:$CW,5,0),"") -> 1 | AA11: =IFERROR(VLOOKUP(Подбор[[#This Row],[Артикул]],[1]Подбор!$CJ:$CW,6,0),"") -> 0 | AB11: =IFERROR(VLOOKUP(Подбор[[#This Row],[Артикул]],[1]Подбор!$CJ:$CW,7,0),"") -> 0 | AC11: =IFERROR(VLOOKUP(Подбор[[#This Row],[Артикул]],[1]Подбор!$CJ:$CW,8,0),"") -> 0 | AD11: =IFERROR(VLOOKUP(Подбор[[#This Row],[Артикул]],[1]Подбор!$CJ:$CW,9,0),"") -> 0 | AE11: =IFERROR(VLOOKUP(Подбор[[#This Row],[Артикул]],[1]Подбор!$CJ:$CW,10,0),"") -> 0 | AF11: =IFERROR(VLOOKUP(Подбор[[#This Row],[Артикул]],[1]Подбор!$CJ:$CW,11,0),"") -> 0 | AG11: =IFERROR(VLOOKUP(Подбор[[#This Row],[Артикул]],[1]Подбор!$CJ:$CW,12,0),"") -> 0 | AH11: =IFERROR(VLOOKUP(Подбор[[#This Row],[Артикул]],[1]Подбор!$CJ:$CW,13,0),"") -> 0 | AI11: =IFERROR(VLOOKUP(Подбор[[#This Row],[Артикул]],[1]Подбор!$CJ:$CW,14,0),"") -> 0 | AJ11: =IFERROR(VLOOKUP(Подбор[[#This Row],[Артикул]],[1]Подбор!$CJ:$DA,15,0),"") | AK11: =IFERROR(VLOOKUP(Подбор[[#This Row],[Артикул]],[1]Подбор!$CJ:$DA,16,0),"") | AL11: =IFERROR(VLOOKUP(Подбор[[#This Row],[Артикул]],[1]Подбор!$CJ:$DA,17,0),"")
A12: FH5PB sale | B12: Fanvil | C12: H5 отельный, 2 аккаунта, цветной ЖК экран, PoE, б/п | G12: 1 | H12: 0 | I12: 0 | J12: 0 | K12: 0 | L12: 0 | M12: 0 | N12: 0 | O12: 0 | P12: 0 | W12: =IFERROR(VLOOKUP(Подбор[[#This Row],[Артикул]],[1]Подбор!$CJ:$CW,2,0),"") | X12: =IFERROR(VLOOKUP(Подбор[[#This Row],[Артикул]],[1]Подбор!$CJ:$CW,3,0),"") | Y12: =IFERROR(VLOOKUP(Подбор[[#This Row],[Артикул]],[1]Подбор!$CJ:$CW,4,0),"") | Z12: =IFERROR(VLOOKUP(Подбор[[#This Row],[Артикул]],[1]Подбор!$CJ:$CW,5,0),"") -> 1 | AA12: =IFERROR(VLOOKUP(Подбор[[#This Row],[Артикул]],[1]Подбор!$CJ:$CW,6,0),"") -> 0 | AB12: =IFERROR(VLOOKUP(Подбор[[#This Row],[Артикул]],[1]Подбор!$CJ:$CW,7,0),"") -> 0 | AC12: =IFERROR(VLOOKUP(Подбор[[#This Row],[Артикул]],[1]Подбор!$CJ:$CW,8,0),"") -> 0 | AD12: =IFERROR(VLOOKUP(Подбор[[#This Row],[Артикул]],[1]Подбор!$CJ:$CW,9,0),"") -> 0 | AE12: =IFERROR(VLOOKUP(Подбор[[#This Row],[Артикул]],[1]Подбор!$CJ:$CW,10,0),"") -> 0 | AF12: =IFERROR(VLOOKUP(Подбор[[#This Row],[Артикул]],[1]Подбор!$CJ:$CW,11,0),"") -> 0 | AG12: =IFERROR(VLOOKUP(Подбор[[#This Row],[Артикул]],[1]Подбор!$CJ:$CW,12,0),"") -> 0 | AH12: =IFERROR(VLOOKUP(Подбор[[#This Row],[Артикул]],[1]Подбор!$CJ:$CW,13,0),"") -> 0 | AI12: =IFERROR(VLOOKUP(Подбор[[#This Row],[Артикул]],[1]Подбор!$CJ:$CW,14,0),"") -> 0 | AJ12: =IFERROR(VLOOKUP(Подбор[[#This Row],[Артикул]],[1]Подбор!$CJ:$DA,15,0),"") | AK12: =IFERROR(VLOOKUP(Подбор[[#This Row],[Артикул]],[1]Подбор!$CJ:$DA,16,0),"") | AL12: =IFERROR(VLOOKUP(Подбор[[#This Row],[Артикул]],[1]Подбор!$CJ:$DA,17,0),"")
A13: VCC22 | B13: Yealink | C13: VCC22 (Видеокамера FHD 12Х PTZ для VC800/880, AMS 2 года) | D13: 658000 | E13: 501630 | F13: -23.764438 | G13: 2 | H13: 0 | I13: 0 | J13: 0 | K13: 0 | L13: 0 | M13: 0 | N13: 1 | O13: 0 | P13: 0 | R13: https://ipmatika.kz/products/vcs-accessories/yealink-vcc22/ | S13: EOL | W13: =IFERROR(VLOOKUP(Подбор[[#This Row],[Артикул]],[1]Подбор!$CJ:$CW,2,0),"") -> 658000 | X13: =IFERROR(VLOOKUP(Подбор[[#This Row],[Артикул]],[1]Подбор!$CJ:$CW,3,0),"") -> 501630 | Y13: =IFERROR(VLOOKUP(Подбор[[#This Row],[Артикул]],[1]Подбор!$CJ:$CW,4,0),"") -> -23.764438 | Z13: =IFERROR(VLOOKUP(Подбор[[#This Row],[Артикул]],[1]Подбор!$CJ:$CW,5,0),"") -> 2 | AA13: =IFERROR(VLOOKUP(Подбор[[#This Row],[Артикул]],[1]Подбор!$CJ:$CW,6,0),"") -> 0 | AB13: =IFERROR(VLOOKUP(Подбор[[#This Row],[Артикул]],[1]Подбор!$CJ:$CW,7,0),"") -> 0 | AC13: =IFERROR(VLOOKUP(Подбор[[#This Row],[Артикул]],[1]Подбор!$CJ:$CW,8,0),"") -> 0 | AD13: =IFERROR(VLOOKUP(Подбор[[#This Row],[Артикул]],[1]Подбор!$CJ:$CW,9,0),"") -> 0 | AE13: =IFERROR(VLOOKUP(Подбор[[#This Row],[Артикул]],[1]Подбор!$CJ:$CW,10,0),"") -> 0 | AF13: =IFERROR(VLOOKUP(Подбор[[#This Row],[Артикул]],[1]Подбор!$CJ:$CW,11,0),"") -> 0 | AG13: =IFERROR(VLOOKUP(Подбор[[#This Row],[Артикул]],[1]Подбор!$CJ:$CW,12,0),"") -> 1 | AH13: =IFERROR(VLOOKUP(Подбор[[#This Row],[Артикул]],[1]Подбор!$CJ:$CW,13,0),"") -> 0 | AI13: =IFERROR(VLOOKUP(Подбор[[#This Row],[Артикул]],[1]Подбор!$CJ:$CW,14,0),"") -> 0 | AJ13: =IFERROR(VLOOKUP(Подбор[[#This Row],[Артикул]],[1]Подбор!$CJ:$DA,15,0),"") | AK13: =IFERROR(VLOOKUP(Подбор[[#This Row],[Артикул]],[1]Подбор!$CJ:$DA,16,0),"") -> https://ipmatika.kz/products/vcs-accessories/yealink-vcc22/ | AL13: =IFERROR(VLOOKUP(Подбор[[#This Row],[Артикул]],[1]Подбор!$CJ:$DA,17,0),"") -> EOL
A14: VT1000-D RJ9(03) old | B14: VT | C14: VT1000 RJ9(03), Моно, Узкополосный звук, SE, усовершенствованный микрофон | G14: 0 | H14: 0 | I14: 0 | J14: 0 | K14: 0 | L14: 0 | M14: 0 | N14: 0 | O14: 0 | P14: 0 | W14: =IFERROR(VLOOKUP(Подбор[[#This Row],[Артикул]],[1]Подбор!$CJ:$CW,2,0),"") | X14: =IFERROR(VLOOKUP(Подбор[[#This Row],[Артикул]],[1]Подбор!$CJ:$CW,3,0),"") | Y14: =IFERROR(VLOOKUP(Подбор[[#This Row],[Артикул]],[1]Подбор!$CJ:$CW,4,0),"") | Z14: =IFERROR(VLOOKUP(Подбор[[#This Row],[Артикул]],[1]Подбор!$CJ:$CW,5,0),"") -> 0 | AA14: =IFERROR(VLOOKUP(Подбор[[#This Row],[Артикул]],[1]Подбор!$CJ:$CW,6,0),"") -> 0 | AB14: =IFERROR(VLOOKUP(Подбор[[#This Row],[Артикул]],[1]Подбор!$CJ:$CW,7,0),"") -> 0 | AC14: =IFERROR(VLOOKUP(Подбор[[#This Row],[Артикул]],[1]Подбор!$CJ:$CW,8,0),"") -> 0 | AD14: =IFERROR(VLOOKUP(Подбор[[#This Row],[Артикул]],[1]Подбор!$CJ:$CW,9,0),"") -> 0 | AE14: =IFERROR(VLOOKUP(Подбор[[#This Row],[Артикул]],[1]Подбор!$CJ:$CW,10,0),"") -> 0 | AF14: =IFERROR(VLOOKUP(Подбор[[#This Row],[Артикул]],[1]Подбор!$CJ:$CW,11,0),"") -> 0 | AG14: =IFERROR(VLOOKUP(Подбор[[#This Row],[Артикул]],[1]Подбор!$CJ:$CW,12,0),"") -> 0 | AH14: =IFERROR(VLOOKUP(Подбор[[#This Row],[Артикул]],[1]Подбор!$CJ:$CW,13,0),"") -> 0 | AI14: =IFERROR(VLOOKUP(Подбор[[#This Row],[Артикул]],[1]Подбор!$CJ:$CW,14,0),"") -> 0 | AJ14: =IFERROR(VLOOKUP(Подбор[[#This Row],[Артикул]],[1]Подбор!$CJ:$DA,15,0),"") | AK14: =IFERROR(VLOOKUP(Подбор[[#This Row],[Артикул]],[1]Подбор!$CJ:$DA,16,0),"") | AL14: =IFERROR(VLOOKUP(Подбор[[#This Row],[Артикул]],[1]Подбор!$CJ:$DA,17,0),"")
A15: VT1000 USB old | B15: VT | C15: VT1000 USB, Моно, Узкополосный звук, SE, усовершенствованный | D15: 11440 | E15: 9480 | F15: -17.132867 | G15: 0 | H15: 0 | I15: 0 | J15: 0 | K15: 0 | L15: 0 | M15: 0 | N15: 0 | O15: 0 | P15: 0 | W15: =IFERROR(VLOOKUP(Подбор[[#This Row],[Артикул]],[1]Подбор!$CJ:$CW,2,0),"") -> 11440 | X15: =IFERROR(VLOOKUP(Подбор[[#This Row],[Артикул]],[1]Подбор!$CJ:$CW,3,0),"") -> 9480 | Y15: =IFERROR(VLOOKUP(Подбор[[#This Row],[Артикул]],[1]Подбор!$CJ:$CW,4,0),"") -> -17.132867 | Z15: =IFERROR(VLOOKUP(Подбор[[#This Row],[Артикул]],[1]Подбор!$CJ:$CW,5,0),"") -> 0 | AA15: =IFERROR(VLOOKUP(Подбор[[#This Row],[Артикул]],[1]Подбор!$CJ:$CW,6,0),"") -> 0 | AB15: =IFERROR(VLOOKUP(Подбор[[#This Row],[Артикул]],[1]Подбор!$CJ:$CW,7,0),"") -> 0 | AC15: =IFERROR(VLOOKUP(Подбор[[#This Row],[Артикул]],[1]Подбор!$CJ:$CW,8,0),"") -> 0 | AD15: =IFERROR(VLOOKUP(Подбор[[#This Row],[Артикул]],[1]Подбор!$CJ:$CW,9,0),"") -> 0 | AE15: =IFERROR(VLOOKUP(Подбор[[#This Row],[Артикул]],[1]Подбор!$CJ:$CW,10,0),"") -> 0 | AF15: =IFERROR(VLOOKUP(Подбор[[#This Row],[Артикул]],[1]Подбор!$CJ:$CW,11,0),"") -> 0 | AG15: =IFERROR(VLOOKUP(Подбор[[#This Row],[Артикул]],[1]Подбор!$CJ:$CW,12,0),"") -> 0 | AH15: =IFERROR(VLOOKUP(Подбор[[#This Row],[Артикул]],[1]Подбор!$CJ:$CW,13,0),"") -> 0 | AI15: =IFERROR(VLOOKUP(Подбор[[#This Row],[Артикул]],[1]Подбор!$CJ:$CW,14,0),"") -> 0 | AJ15: =IFERROR(VLOOKUP(Подбор[[#This Row],[Артикул]],[1]Подбор!$CJ:$DA,15,0),"") | AK15: =IFERROR(VLOOKUP(Подбор[[#This Row],[Артикул]],[1]Подбор!$CJ:$DA,16,0),"") | AL15: =IFERROR(VLOOKUP(Подбор[[#This Row],[Артикул]],[1]Подбор!$CJ:$DA,17,0),"")
A16: VT6200-D QD(P)-RJ9(03) | B16: VT | C16: VT6200-D QD(P)-RJ9(03), Дуо, HD звук, QD, переходник QD-RJ09(03) | D16: 22370 | E16: 16470 | F16: -26.374609 | G16: 24 | H16: 0 | I16: 0 | J16: 5 | K16: 0 | L16: 0 | M16: 0 | N16: 50+ | O16: 0 | P16: 50+ | Q16: http://ipmatika.ru/upload/iblock/0b2/bo7u1f0lk4swaqeijiuvo2jnumi82s0t/VT6200D_USB_04.jpg | R16: https://ipmatika.kz/products/provodnye/VT-VT6200-D-QD%28P%29-RJ9%2803%29/ | W16: =IFERROR(VLOOKUP(Подбор[[#This Row],[Артикул]],[1]Подбор!$CJ:$CW,2,0),"") -> 22370 | X16: =IFERROR(VLOOKUP(Подбор[[#This Row],[Артикул]],[1]Подбор!$CJ:$CW,3,0),"") -> 16470 | Y16: =IFERROR(VLOOKUP(Подбор[[#This Row],[Артикул]],[1]Подбор!$CJ:$CW,4,0),"") -> -26.374609 | Z16: =IFERROR(VLOOKUP(Подбор[[#This Row],[Артикул]],[1]Подбор!$CJ:$CW,5,0),"") -> 24 | AA16: =IFERROR(VLOOKUP(Подбор[[#This Row],[Артикул]],[1]Подбор!$CJ:$CW,6,0),"") -> 0 | AB16: =IFERROR(VLOOKUP(Подбор[[#This Row],[Артикул]],[1]Подбор!$CJ:$CW,7,0),"") -> 0 | AC16: =IFERROR(VLOOKUP(Подбор[[#This Row],[Артикул]],[1]Подбор!$CJ:$CW,8,0),"") -> 5 | AD16: =IFERROR(VLOOKUP(Подбор[[#This Row],[Артикул]],[1]Подбор!$CJ:$CW,9,0),"") -> 0 | AE16: =IFERROR(VLOOKUP(Подбор[[#This Row],[Артикул]],[1]Подбор!$CJ:$CW,10,0),"") -> 0 | AF16: =IFERROR(VLOOKUP(Подбор[[#This Row],[Артикул]],[1]Подбор!$CJ:$CW,11,0),"") -> 0 | AG16: =IFERROR(VLOOKUP(Подбор[[#This Row],[Артикул]],[1]Подбор!$CJ:$CW,12,0),"") -> 50+ | AH16: =IFERROR(VLOOKUP(Подбор[[#This Row],[Артикул]],[1]Подбор!$CJ:$CW,13,0),"") -> 0 | AI16: =IFERROR(VLOOKUP(Подбор[[#This Row],[Артикул]],[1]Подбор!$CJ:$CW,14,0),"") -> 50+ | AJ16: =IFERROR(VLOOKUP(Подбор[[#This Row],[Артикул]],[1]Подбор!$CJ:$DA,15,0),"") -> http://ipmatika.ru/upload/iblock/0b2/bo7u1f0lk4swaqeijiuvo2jnumi82s0t/VT6200D_USB_04.jpg | AK16: =IFERROR(VLOOKUP(Подбор[[#This Row],[Артикул]],[1]Подбор!$CJ:$DA,16,0),"") -> https://ipmatika.kz/products/provodnye/VT-VT6200-D-QD%28P%29-RJ9%2803%29/ | AL16: =IFERROR(VLOOKUP(Подбор[[#This Row],[Артикул]],[1]Подбор!$CJ:$DA,17,0),"")
A17: VT6300-D USB | B17: VT | C17: VT6300-D USB, Дуо, HD звук, микрофон с шумоподавлением | D17: 26850 | E17: 18860 | F17: -29.757914 | G17: 50+ | H17: 0 | I17: 0 | J17: 10 | K17: 0 | L17: 0 | M17: 0 | N17: 0 | O17: 0 | P17: 0 | Q17: http://ipmatika.ru/upload/iblock/ed7/2si7d12nzmk00joxthvb75cm48w0eig3/6300D_USB_01.jpg | R17: https://ipmatika.kz/products/provodnye/VT6300-D/ | W17: =IFERROR(VLOOKUP(Подбор[[#This Row],[Артикул]],[1]Подбор!$CJ:$CW,2,0),"") -> 26850 | X17: =IFERROR(VLOOKUP(Подбор[[#This Row],[Артикул]],[1]Подбор!$CJ:$CW,3,0),"") -> 18860 | Y17: =IFERROR(VLOOKUP(Подбор[[#This Row],[Артикул]],[1]Подбор!$CJ:$CW,4,0),"") -> -29.757914 | Z17: =IFERROR(VLOOKUP(Подбор[[#This Row],[Артикул]],[1]Подбор!$CJ:$CW,5,0),"") -> 50+ | AA17: =IFERROR(VLOOKUP(Подбор[[#This Row],[Артикул]],[1]Подбор!$CJ:$CW,6,0),"") -> 0 | AB17: =IFERROR(VLOOKUP(Подбор[[#This Row],[Артикул]],[1]Подбор!$CJ:$CW,7,0),"") -> 0 | AC17: =IFERROR(VLOOKUP(Подбор[[#This Row],[Артикул]],[1]Подбор!$CJ:$CW,8,0),"") -> 10 | AD17: =IFERROR(VLOOKUP(Подбор[[#This Row],[Артикул]],[1]Подбор!$CJ:$CW,9,0),"") -> 0 | AE17: =IFERROR(VLOOKUP(Подбор[[#This Row],[Артикул]],[1]Подбор!$CJ:$CW,10,0),"") -> 0 | AF17: =IFERROR(VLOOKUP(Подбор[[#This Row],[Артикул]],[1]Подбор!$CJ:$CW,11,0),"") -> 0 | AG17: =IFERROR(VLOOKUP(Подбор[[#This Row],[Артикул]],[1]Подбор!$CJ:$CW,12,0),"") -> 0 | AH17: =IFERROR(VLOOKUP(Подбор[[#This Row],[Артикул]],[1]Подбор!$CJ:$CW,13,0),"") -> 0 | AI17: =IFERROR(VLOOKUP(Подбор[[#This Row],[Артикул]],[1]Подбор!$CJ:$CW,14,0),"") -> 0 | AJ17: =IFERROR(VLOOKUP(Подбор[[#This Row],[Артикул]],[1]Подбор!$CJ:$DA,15,0),"") -> http://ipmatika.ru/upload/iblock/ed7/2si7d12nzmk00joxthvb75cm48w0eig3/6300D_USB_01.jpg | AK17: =IFERROR(VLOOKUP(Подбор[[#This Row],[Артикул]],[1]Подбор!$CJ:$DA,16,0),"") -> https://ipmatika.kz/products/provodnye/VT6300-D/ | AL17: =IFERROR(VLOOKUP(Подбор[[#This Row],[Артикул]],[1]Подбор!$CJ:$DA,17,0),"")
A18: i20S | B18: Fanvil | C18: Fanvil i20S IP-домофон, накладной, внешний, IP65, клавиатура | G18: 2 | H18: 0 | I18: 0 | J18: 0 | K18: 0 | L18: 0 | M18: 0 | N18: 0 | O18: 0 | P18: 0 | W18: =IFERROR(VLOOKUP(Подбор[[#This Row],[Артикул]],[1]Подбор!$CJ:$CW,2,0),"") | X18: =IFERROR(VLOOKUP(Подбор[[#This Row],[Артикул]],[1]Подбор!$CJ:$CW,3,0),"") | Y18: =IFERROR(VLOOKUP(Подбор[[#This Row],[Артикул]],[1]Подбор!$CJ:$CW,4,0),"") | Z18: =IFERROR(VLOOKUP(Подбор[[#This Row],[Артикул]],[1]Подбор!$CJ:$CW,5,0),"") -> 2 | AA18: =IFERROR(VLOOKUP(Подбор[[#This Row],[Артикул]],[1]Подбор!$CJ:$CW,6,0),"") -> 0 | AB18: =IFERROR(VLOOKUP(Подбор[[#This Row],[Артикул]],[1]Подбор!$CJ:$CW,7,0),"") -> 0 | AC18: =IFERROR(VLOOKUP(Подбор[[#This Row],[Артикул]],[1]Подбор!$CJ:$CW,8,0),"") -> 0 | AD18: =IFERROR(VLOOKUP(Подбор[[#This Row],[Артикул]],[1]Подбор!$CJ:$CW,9,0),"") -> 0 | AE18: =IFERROR(VLOOKUP(Подбор[[#This Row],[Артикул]],[1]Подбор!$CJ:$CW,10,0),"") -> 0 | AF18: =IFERROR(VLOOKUP(Подбор[[#This Row],[Артикул]],[1]Подбор!$CJ:$CW,11,0),"") -> 0 | AG18: =IFERROR(VLOOKUP(Подбор[[#This Row],[Артикул]],[1]Подбор!$CJ:$CW,12,0),"") -> 0 | AH18: =IFERROR(VLOOKUP(Подбор[[#This Row],[Артикул]],[1]Подбор!$CJ:$CW,13,0),"") -> 0 | AI18: =IFERROR(VLOOKUP(Подбор[[#This Row],[Артикул]],[1]Подбор!$CJ:$CW,14,0),"") -> 0 | AJ18: =IFERROR(VLOOKUP(Подбор[[#This Row],[Артикул]],[1]Подбор!$CJ:$DA,15,0),"") | AK18: =IFERROR(VLOOKUP(Подбор[[#This Row],[Артикул]],[1]Подбор!$CJ:$DA,16,0),"") | AL18: =IFERROR(VLOOKUP(Подбор[[#This Row],[Артикул]],[1]Подбор!$CJ:$DA,17,0),"")
A19: i52W | B19: Fanvil | C19: Fanvil i52W, WiFi, без БП, ответная часть для SIP-домофона | D19: 22250 | E19: 17800 | F19: -20 | G19: 1 | H19: 0 | I19: 0 | J19: 0 | K19: 0 | L19: 0 | M19: 0 | N19: 0 | O19: 0 | P19: 0 | Q19: http://ipmatika.ru/upload/iblock/eff/pa8woC_ZiXo.jpg | R19: https://ipmatika.kz/products/vnutrennie-sip-paneli/Fanvil-i52W/ | S19: EOL | W19: =IFERROR(VLOOKUP(Подбор[[#This Row],[Артикул]],[1]Подбор!$CJ:$CW,2,0),"") -> 22250 | X19: =IFERROR(VLOOKUP(Подбор[[#This Row],[Артикул]],[1]Подбор!$CJ:$CW,3,0),"") -> 17800 | Y19: =IFERROR(VLOOKUP(Подбор[[#This Row],[Артикул]],[1]Подбор!$CJ:$CW,4,0),"") -> -20 | Z19: =IFERROR(VLOOKUP(Подбор[[#This Row],[Артикул]],[1]Подбор!$CJ:$CW,5,0),"") -> 1 | AA19: =IFERROR(VLOOKUP(Подбор[[#This Row],[Артикул]],[1]Подбор!$CJ:$CW,6,0),"") -> 0 | AB19: =IFERROR(VLOOKUP(Подбор[[#This Row],[Артикул]],[1]Подбор!$CJ:$CW,7,0),"") -> 0 | AC19: =IFERROR(VLOOKUP(Подбор[[#This Row],[Артикул]],[1]Подбор!$CJ:$CW,8,0),"") -> 0 | AD19: =IFERROR(VLOOKUP(Подбор[[#This Row],[Артикул]],[1]Подбор!$CJ:$CW,9,0),"") -> 0 | AE19: =IFERROR(VLOOKUP(Подбор[[#This Row],[Артикул]],[1]Подбор!$CJ:$CW,10,0),"") -> 0 | AF19: =IFERROR(VLOOKUP(Подбор[[#This Row],[Артикул]],[1]Подбор!$CJ:$CW,11,0),"") -> 0 | AG19: =IFERROR(VLOOKUP(Подбор[[#This Row],[Артикул]],[1]Подбор!$CJ:$CW,12,0),"") -> 0 | AH19: =IFERROR(VLOOKUP(Подбор[[#This Row],[Артикул]],[1]Подбор!$CJ:$CW,13,0),"") -> 0 | AI19: =IFERROR(VLOOKUP(Подбор[[#This Row],[Артикул]],[1]Подбор!$CJ:$CW,14,0),"") -> 0 | AJ19: =IFERROR(VLOOKUP(Подбор[[#This Row],[Артикул]],[1]Подбор!$CJ:$DA,15,0),"") -> http://ipmatika.ru/upload/iblock/eff/pa8woC_ZiXo.jpg | AK19: =IFERROR(VLOOKUP(Подбор[[#This Row],[Артикул]],[1]Подбор!$CJ:$DA,16,0),"") -> https://ipmatika.kz/products/vnutrennie-sip-paneli/Fanvil-i52W/ | AL19: =IFERROR(VLOOKUP(Подбор[[#This Row],[Артикул]],[1]Подбор!$CJ:$DA,17,0),"") -> EOL
A20: WI-CPE513P-KIT v3 | B20: Wi-Tek | C20: WI-CPE513P-KIT комплект из двух преднастроенных точек доступа 802.11a/n, 5ГГц, 2 LAN, PoE, Cloud | D20: 91530 | E20: 73226.45 | F20: -19.997323 | G20: 0 | H20: 0 | I20: 0 | J20: 0 | K20: 0 | L20: 0 | M20: 0 | N20: 0 | O20: 0 | P20: 50+ | Q20: http://ipmatika.ru/upload/iblock/499/d2022061515203235.png | R20: https://ipmatika.kz/products/wifi-mosty/wi-tek-wi-cpe513p-kit-v3/ | W20: =IFERROR(VLOOKUP(Подбор[[#This Row],[Артикул]],[1]Подбор!$CJ:$CW,2,0),"") -> 91530 | X20: =IFERROR(VLOOKUP(Подбор[[#This Row],[Артикул]],[1]Подбор!$CJ:$CW,3,0),"") -> 73226.45 | Y20: =IFERROR(VLOOKUP(Подбор[[#This Row],[Артикул]],[1]Подбор!$CJ:$CW,4,0),"") -> -19.997323 | Z20: =IFERROR(VLOOKUP(Подбор[[#This Row],[Артикул]],[1]Подбор!$CJ:$CW,5,0),"") -> 0 | AA20: =IFERROR(VLOOKUP(Подбор[[#This Row],[Артикул]],[1]Подбор!$CJ:$CW,6,0),"") -> 0 | AB20: =IFERROR(VLOOKUP(Подбор[[#This Row],[Артикул]],[1]Подбор!$CJ:$CW,7,0),"") -> 0 | AC20: =IFERROR(VLOOKUP(Подбор[[#This Row],[Артикул]],[1]Подбор!$CJ:$CW,8,0),"") -> 0 | AD20: =IFERROR(VLOOKUP(Подбор[[#This Row],[Артикул]],[1]Подбор!$CJ:$CW,9,0),"") -> 0 | AE20: =IFERROR(VLOOKUP(Подбор[[#This Row],[Артикул]],[1]Подбор!$CJ:$CW,10,0),"") -> 0 | AF20: =IFERROR(VLOOKUP(Подбор[[#This Row],[Артикул]],[1]Подбор!$CJ:$CW,11,0),"") -> 0 | AG20: =IFERROR(VLOOKUP(Подбор[[#This Row],[Артикул]],[1]Подбор!$CJ:$CW,12,0),"") -> 0 | AH20: =IFERROR(VLOOKUP(Подбор[[#This Row],[Артикул]],[1]Подбор!$CJ:$CW,13,0),"") -> 0 | AI20: =IFERROR(VLOOKUP(Подбор[[#This Row],[Артикул]],[1]Подбор!$CJ:$CW,14,0),"") -> 50+ | AJ20: =IFERROR(VLOOKUP(Подбор[[#This Row],[Артикул]],[1]Подбор!$CJ:$DA,15,0),"") -> http://ipmatika.ru/upload/iblock/499/d2022061515203235.png | AK20: =IFERROR(VLOOKUP(Подбор[[#This Row],[Артикул]],[1]Подбор!$CJ:$DA,16,0),"") -> https://ipmatika.kz/products/wifi-mosty/wi-tek-wi-cpe513p-kit-v3/ | AL20: =IFERROR(VLOOKUP(Подбор[[#This Row],[Артикул]],[1]Подбор!$CJ:$DA,17,0),"")
A21: WI-AP510 | B21: Wi-Tek | C21: WI-AP510 AC1200 Внешняя двухдиапазонная точка доступа c поддержкой PoE, Wi-Fi 5 (802.11AC Wave2) | D21: 248270 | E21: 198617.38 | F21: -19.999446 | G21: 1 | H21: 0 | I21: 0 | J21: 0 | K21: 0 | L21: 0 | M21: 0 | N21: 17 | O21: 0 | P21: 0 | Q21: http://ipmatika.ru/upload/iblock/e13/mq6z4j7ux55nc7b7qm1v50lrlb65yvt1/AP510-4.jpg | R21: https://ipmatika.kz/products/wifi-smb/wi-tek-wi-ap510/ | S21: EOL | W21: =IFERROR(VLOOKUP(Подбор[[#This Row],[Артикул]],[1]Подбор!$CJ:$CW,2,0),"") -> 248270 | X21: =IFERROR(VLOOKUP(Подбор[[#This Row],[Артикул]],[1]Подбор!$CJ:$CW,3,0),"") -> 198617.38 | Y21: =IFERROR(VLOOKUP(Подбор[[#This Row],[Артикул]],[1]Подбор!$CJ:$CW,4,0),"") -> -19.999446 | Z21: =IFERROR(VLOOKUP(Подбор[[#This Row],[Артикул]],[1]Подбор!$CJ:$CW,5,0),"") -> 1 | AA21: =IFERROR(VLOOKUP(Подбор[[#This Row],[Артикул]],[1]Подбор!$CJ:$CW,6,0),"") -> 0 | AB21: =IFERROR(VLOOKUP(Подбор[[#This Row],[Артикул]],[1]Подбор!$CJ:$CW,7,0),"") -> 0 | AC21: =IFERROR(VLOOKUP(Подбор[[#This Row],[Артикул]],[1]Подбор!$CJ:$CW,8,0),"") -> 0 | AD21: =IFERROR(VLOOKUP(Подбор[[#This Row],[Артикул]],[1]Подбор!$CJ:$CW,9,0),"") -> 0 | AE21: =IFERROR(VLOOKUP(Подбор[[#This Row],[Артикул]],[1]Подбор!$CJ:$CW,10,0),"") -> 0 | AF21: =IFERROR(VLOOKUP(Подбор[[#This Row],[Артикул]],[1]Подбор!$CJ:$CW,11,0),"") -> 0 | AG21: =IFERROR(VLOOKUP(Подбор[[#This Row],[Артикул]],[1]Подбор!$CJ:$CW,12,0),"") -> 17 | AH21: =IFERROR(VLOOKUP(Подбор[[#This Row],[Артикул]],[1]Подбор!$CJ:$CW,13,0),"") -> 0 | AI21: =IFERROR(VLOOKUP(Подбор[[#This Row],[Артикул]],[1]Подбор!$CJ:$CW,14,0),"") -> 0 | AJ21: =IFERROR(VLOOKUP(Подбор[[#This Row],[Артикул]],[1]Подбор!$CJ:$DA,15,0),"") -> http://ipmatika.ru/upload/iblock/e13/mq6z4j7ux55nc7b7qm1v50lrlb65yvt1/AP510-4.jpg | AK21: =IFERROR(VLOOKUP(Подбор[[#This Row],[Артикул]],[1]Подбор!$CJ:$DA,16,0),"") -> https://ipmatika.kz/products/wifi-smb/wi-tek-wi-ap510/ | AL21: =IFERROR(VLOOKUP(Подбор[[#This Row],[Артикул]],[1]Подбор!$CJ:$DA,17,0),"") -> EOL
A22: SFP+-10GE-LX-SM1310 | B22: TG-NET | C22: МодульTG-NET SFP-10GE-LX-SM1310 (1шт) | D22: 25990 | E22: 20790 | F22: -20.007695 | G22: 2 | H22: 0 | I22: 0 | J22: 0 | K22: 0 | L22: 0 | M22: 0 | N22: 0 | O22: 0 | P22: 0 | W22: =IFERROR(VLOOKUP(Подбор[[#This Row],[Артикул]],[1]Подбор!$CJ:$CW,2,0),"") -> 25990 | X22: =IFERROR(VLOOKUP(Подбор[[#This Row],[Артикул]],[1]Подбор!$CJ:$CW,3,0),"") -> 20790 | Y22: =IFERROR(VLOOKUP(Подбор[[#This Row],[Артикул]],[1]Подбор!$CJ:$CW,4,0),"") -> -20.007695 | Z22: =IFERROR(VLOOKUP(Подбор[[#This Row],[Артикул]],[1]Подбор!$CJ:$CW,5,0),"") -> 2 | AA22: =IFERROR(VLOOKUP(Подбор[[#This Row],[Артикул]],[1]Подбор!$CJ:$CW,6,0),"") -> 0 | AB22: =IFERROR(VLOOKUP(Подбор[[#This Row],[Артикул]],[1]Подбор!$CJ:$CW,7,0),"") -> 0 | AC22: =IFERROR(VLOOKUP(Подбор[[#This Row],[Артикул]],[1]Подбор!$CJ:$CW,8,0),"") -> 0 | AD22: =IFERROR(VLOOKUP(Подбор[[#This Row],[Артикул]],[1]Подбор!$CJ:$CW,9,0),"") -> 0 | AE22: =IFERROR(VLOOKUP(Подбор[[#This Row],[Артикул]],[1]Подбор!$CJ:$CW,10,0),"") -> 0 | AF22: =IFERROR(VLOOKUP(Подбор[[#This Row],[Артикул]],[1]Подбор!$CJ:$CW,11,0),"") -> 0 | AG22: =IFERROR(VLOOKUP(Подбор[[#This Row],[Артикул]],[1]Подбор!$CJ:$CW,12,0),"") -> 0 | AH22: =IFERROR(VLOOKUP(Подбор[[#This Row],[Артикул]],[1]Подбор!$CJ:$CW,13,0),"") -> 0 | AI22: =IFERROR(VLOOKUP(Подбор[[#This Row],[Артикул]],[1]Подбор!$CJ:$CW,14,0),"") -> 0 | AJ22: =IFERROR(VLOOKUP(Подбор[[#This Row],[Артикул]],[1]Подбор!$CJ:$DA,15,0),"") | AK22: =IFERROR(VLOOKUP(Подбор[[#This Row],[Артикул]],[1]Подбор!$CJ:$DA,16,0),"") | AL22: =IFERROR(VLOOKUP(Подбор[[#This Row],[Артикул]],[1]Подбор!$CJ:$DA,17,0),"")
A23: WI-PMS320GF | B23: Wi-Tek | C23: WI-PMS320GF Коммутатор управляемый L2 PoE 350Вт, порты 16 PoE GE + 2SFP | D23: 245420 | E23: 196336.52 | F23: -19.999786 | G23: 2 | H23: 0 | I23: 0 | J23: 0 | K23: 0 | L23: 0 | M23: 0 | N23: 0 | O23: 0 | P23: 0 | R23: https://ipmatika.kz/products/managed-l2/wi-tek-wi-pms320gf/ | S23: EOL | W23: =IFERROR(VLOOKUP(Подбор[[#This Row],[Артикул]],[1]Подбор!$CJ:$CW,2,0),"") -> 245420 | X23: =IFERROR(VLOOKUP(Подбор[[#This Row],[Артикул]],[1]Подбор!$CJ:$CW,3,0),"") -> 196336.52 | Y23: =IFERROR(VLOOKUP(Подбор[[#This Row],[Артикул]],[1]Подбор!$CJ:$CW,4,0),"") -> -19.999786 | Z23: =IFERROR(VLOOKUP(Подбор[[#This Row],[Артикул]],[1]Подбор!$CJ:$CW,5,0),"") -> 2 | AA23: =IFERROR(VLOOKUP(Подбор[[#This Row],[Артикул]],[1]Подбор!$CJ:$CW,6,0),"") -> 0 | AB23: =IFERROR(VLOOKUP(Подбор[[#This Row],[Артикул]],[1]Подбор!$CJ:$CW,7,0),"") -> 0 | AC23: =IFERROR(VLOOKUP(Подбор[[#This Row],[Артикул]],[1]Подбор!$CJ:$CW,8,0),"") -> 0 | AD23: =IFERROR(VLOOKUP(Подбор[[#This Row],[Артикул]],[1]Подбор!$CJ:$CW,9,0),"") -> 0 | AE23: =IFERROR(VLOOKUP(Подбор[[#This Row],[Артикул]],[1]Подбор!$CJ:$CW,10,0),"") -> 0 | AF23: =IFERROR(VLOOKUP(Подбор[[#This Row],[Артикул]],[1]Подбор!$CJ:$CW,11,0),"") -> 0 | AG23: =IFERROR(VLOOKUP(Подбор[[#This Row],[Артикул]],[1]Подбор!$CJ:$CW,12,0),"") -> 0 | AH23: =IFERROR(VLOOKUP(Подбор[[#This Row],[Артикул]],[1]Подбор!$CJ:$CW,13,0),"") -> 0 | AI23: =IFERROR(VLOOKUP(Подбор[[#This Row],[Артикул]],[1]Подбор!$CJ:$CW,14,0),"") -> 0 | AJ23: =IFERROR(VLOOKUP(Подбор[[#This Row],[Артикул]],[1]Подбор!$CJ:$DA,15,0),"") | AK23: =IFERROR(VLOOKUP(Подбор[[#This Row],[Артикул]],[1]Подбор!$CJ:$DA,16,0),"") -> https://ipmatika.kz/products/managed-l2/wi-tek-wi-pms320gf/ | AL23: =IFERROR(VLOOKUP(Подбор[[#This Row],[Артикул]],[1]Подбор!$CJ:$DA,17,0),"") -> EOL
A24: Gigaset PRO | G24: 0 | H24: 0 | I24: 0 | J24: 0 | K24: 0 | L24: 0 | M24: 0 | N24: 0 | O24: 0 | P24: 0 | W24: =IFERROR(VLOOKUP(Подбор[[#This Row],[Артикул]],[1]Подбор!$CJ:$CW,2,0),"") | X24: =IFERROR(VLOOKUP(Подбор[[#This Row],[Артикул]],[1]Подбор!$CJ:$CW,3,0),"") | Y24: =IFERROR(VLOOKUP(Подбор[[#This Row],[Артикул]],[1]Подбор!$CJ:$CW,4,0),"") | Z24: =IFERROR(VLOOKUP(Подбор[[#This Row],[Артикул]],[1]Подбор!$CJ:$CW,5,0),"") -> 0 | AA24: =IFERROR(VLOOKUP(Подбор[[#This Row],[Артикул]],[1]Подбор!$CJ:$CW,6,0),"") -> 0 | AB24: =IFERROR(VLOOKUP(Подбор[[#This Row],[Артикул]],[1]Подбор!$CJ:$CW,7,0),"") -> 0 | AC24: =IFERROR(VLOOKUP(Подбор[[#This Row],[Артикул]],[1]Подбор!$CJ:$CW,8,0),"") -> 0 | AD24: =IFERROR(VLOOKUP(Подбор[[#This Row],[Артикул]],[1]Подбор!$CJ:$CW,9,0),"") -> 0 | AE24: =IFERROR(VLOOKUP(Подбор[[#This Row],[Артикул]],[1]Подбор!$CJ:$CW,10,0),"") -> 0 | AF24: =IFERROR(VLOOKUP(Подбор[[#This Row],[Артикул]],[1]Подбор!$CJ:$CW,11,0),"") -> 0 | AG24: =IFERROR(VLOOKUP(Подбор[[#This Row],[Артикул]],[1]Подбор!$CJ:$CW,12,0),"") -> 0 | AH24: =IFERROR(VLOOKUP(Подбор[[#This Row],[Артикул]],[1]Подбор!$CJ:$CW,13,0),"") -> 0 | AI24: =IFERROR(VLOOKUP(Подбор[[#This Row],[Артикул]],[1]Подбор!$CJ:$CW,14,0),"") -> 0 | AJ24: =IFERROR(VLOOKUP(Подбор[[#This Row],[Артикул]],[1]Подбор!$CJ:$DA,15,0),"") | AK24: =IFERROR(VLOOKUP(Подбор[[#This Row],[Артикул]],[1]Подбор!$CJ:$DA,16,0),"") | AL24: =IFERROR(VLOOKUP(Подбор[[#This Row],[Артикул]],[1]Подбор!$CJ:$DA,17,0),"")
A25: Базовые станции/базы GIGASET | G25: 0 | H25: 0 | I25: 0 | J25: 0 | K25: 0 | L25: 0 | M25: 0 | N25: 0 | O25: 0 | P25: 0 | W25: =IFERROR(VLOOKUP(Подбор[[#This Row],[Артикул]],[1]Подбор!$CJ:$CW,2,0),"") | X25: =IFERROR(VLOOKUP(Подбор[[#This Row],[Артикул]],[1]Подбор!$CJ:$CW,3,0),"") | Y25: =IFERROR(VLOOKUP(Подбор[[#This Row],[Артикул]],[1]Подбор!$CJ:$CW,4,0),"") | Z25: =IFERROR(VLOOKUP(Подбор[[#This Row],[Артикул]],[1]Подбор!$CJ:$CW,5,0),"") -> 0 | AA25: =IFERROR(VLOOKUP(Подбор[[#This Row],[Артикул]],[1]Подбор!$CJ:$CW,6,0),"") -> 0 | AB25: =IFERROR(VLOOKUP(Подбор[[#This Row],[Артикул]],[1]Подбор!$CJ:$CW,7,0),"") -> 0 | AC25: =IFERROR(VLOOKUP(Подбор[[#This Row],[Артикул]],[1]Подбор!$CJ:$CW,8,0),"") -> 0 | AD25: =IFERROR(VLOOKUP(Подбор[[#This Row],[Артикул]],[1]Подбор!$CJ:$CW,9,0),"") -> 0 | AE25: =IFERROR(VLOOKUP(Подбор[[#This Row],[Артикул]],[1]Подбор!$CJ:$CW,10,0),"") -> 0 | AF25: =IFERROR(VLOOKUP(Подбор[[#This Row],[Артикул]],[1]Подбор!$CJ:$CW,11,0),"") -> 0 | AG25: =IFERROR(VLOOKUP(Подбор[[#This Row],[Артикул]],[1]Подбор!$CJ:$CW,12,0),"") -> 0 | AH25: =IFERROR(VLOOKUP(Подбор[[#This Row],[Артикул]],[1]Подбор!$CJ:$CW,13,0),"") -> 0 | AI25: =IFERROR(VLOOKUP(Подбор[[#This Row],[Артикул]],[1]Подбор!$CJ:$CW,14,0),"") -> 0 | AJ25: =IFERROR(VLOOKUP(Подбор[[#This Row],[Артикул]],[1]Подбор!$CJ:$DA,15,0),"") | AK25: =IFERROR(VLOOKUP(Подбор[[#This Row],[Артикул]],[1]Подбор!$CJ:$DA,16,0),"") | AL25: =IFERROR(VLOOKUP(Подбор[[#This Row],[Артикул]],[1]Подбор!$CJ:$DA,17,0),"")
A26: S30852-H2714-R101 | B26: Gigaset | C26: N670IP PRO, базовая станция, синглсота DECT, Мини-мультисота DECT - до 3 БС, до 20 трубок. POE | D26: 234230 | E26: 175678.88 | F26: -24.997276 | G26: 0 | H26: 0 | I26: 0 | J26: 0 | K26: 0 | L26: 0 | M26: 0 | N26: 0 | O26: 0 | P26: 0 | R26: https://ipmatika.kz/products/dect-network/Gigaset-N670IP-PRO/ | W26: =IFERROR(VLOOKUP(Подбор[[#This Row],[Артикул]],[1]Подбор!$CJ:$CW,2,0),"") -> 234230 | X26: =IFERROR(VLOOKUP(Подбор[[#This Row],[Артикул]],[1]Подбор!$CJ:$CW,3,0),"") -> 175678.88 | Y26: =IFERROR(VLOOKUP(Подбор[[#This Row],[Артикул]],[1]Подбор!$CJ:$CW,4,0),"") -> -24.997276 | Z26: =IFERROR(VLOOKUP(Подбор[[#This Row],[Артикул]],[1]Подбор!$CJ:$CW,5,0),"") -> 0 | AA26: =IFERROR(VLOOKUP(Подбор[[#This Row],[Артикул]],[1]Подбор!$CJ:$CW,6,0),"") -> 0 | AB26: =IFERROR(VLOOKUP(Подбор[[#This Row],[Артикул]],[1]Подбор!$CJ:$CW,7,0),"") -> 0 | AC26: =IFERROR(VLOOKUP(Подбор[[#This Row],[Артикул]],[1]Подбор!$CJ:$CW,8,0),"") -> 0 | AD26: =IFERROR(VLOOKUP(Подбор[[#This Row],[Артикул]],[1]Подбор!$CJ:$CW,9,0),"") -> 0 | AE26: =IFERROR(VLOOKUP(Подбор[[#This Row],[Артикул]],[1]Подбор!$CJ:$CW,10,0),"") -> 0 | AF26: =IFERROR(VLOOKUP(Подбор[[#This Row],[Артикул]],[1]Подбор!$CJ:$CW,11,0),"") -> 0 | AG26: =IFERROR(VLOOKUP(Подбор[[#This Row],[Артикул]],[1]Подбор!$CJ:$CW,12,0),"") -> 0 | AH26: =IFERROR(VLOOKUP(Подбор[[#This Row],[Артикул]],[1]Подбор!$CJ:$CW,13,0),"") -> 0 | AI26: =IFERROR(VLOOKUP(Подбор[[#This Row],[Артикул]],[1]Подбор!$CJ:$CW,14,0),"") -> 0 | AJ26: =IFERROR(VLOOKUP(Подбор[[#This Row],[Артикул]],[1]Подбор!$CJ:$DA,15,0),"") | AK26: =IFERROR(VLOOKUP(Подбор[[#This Row],[Артикул]],[1]Подбор!$CJ:$DA,16,0),"") -> https://ipmatika.kz/products/dect-network/Gigaset-N670IP-PRO/ | AL26: =IFERROR(VLOOKUP(Подбор[[#This Row],[Артикул]],[1]Подбор!$CJ:$DA,17,0),"")
A27: S30852-H2315-R101 | B27: Gigaset | C27: N720 DM PRO SYS IM, контроллер, микросота DECT, до 30 баз, до 100 трубок, POE | D27: 148720 | E27: 111540 | F27: -25 | G27: 0 | H27: 0 | I27: 0 | J27: 0 | K27: 0 | L27: 0 | M27: 0 | N27: 0 | O27: 1 | P27: 0 | R27: https://ipmatika.kz/products/dect-network/Gigaset-N720DM/ | W27: =IFERROR(VLOOKUP(Подбор[[#This Row],[Артикул]],[1]Подбор!$CJ:$CW,2,0),"") -> 148720 | X27: =IFERROR(VLOOKUP(Подбор[[#This Row],[Артикул]],[1]Подбор!$CJ:$CW,3,0),"") -> 111540 | Y27: =IFERROR(VLOOKUP(Подбор[[#This Row],[Артикул]],[1]Подбор!$CJ:$CW,4,0),"") -> -25 | Z27: =IFERROR(VLOOKUP(Подбор[[#This Row],[Артикул]],[1]Подбор!$CJ:$CW,5,0),"") -> 0 | AA27: =IFERROR(VLOOKUP(Подбор[[#This Row],[Артикул]],[1]Подбор!$CJ:$CW,6,0),"") -> 0 | AB27: =IFERROR(VLOOKUP(Подбор[[#This Row],[Артикул]],[1]Подбор!$CJ:$CW,7,0),"") -> 0 | AC27: =IFERROR(VLOOKUP(Подбор[[#This Row],[Артикул]],[1]Подбор!$CJ:$CW,8,0),"") -> 0 | AD27: =IFERROR(VLOOKUP(Подбор[[#This Row],[Артикул]],[1]Подбор!$CJ:$CW,9,0),"") -> 0 | AE27: =IFERROR(VLOOKUP(Подбор[[#This Row],[Артикул]],[1]Подбор!$CJ:$CW,10,0),"") -> 0 | AF27: =IFERROR(VLOOKUP(Подбор[[#This Row],[Артикул]],[1]Подбор!$CJ:$CW,11,0),"") -> 0 | AG27: =IFERROR(VLOOKUP(Подбор[[#This Row],[Артикул]],[1]Подбор!$CJ:$CW,12,0),"") -> 0 | AH27: =IFERROR(VLOOKUP(Подбор[[#This Row],[Артикул]],[1]Подбор!$CJ:$CW,13,0),"") -> 1 | AI27: =IFERROR(VLOOKUP(Подбор[[#This Row],[Артикул]],[1]Подбор!$CJ:$CW,14,0),"") -> 0 | AJ27: =IFERROR(VLOOKUP(Подбор[[#This Row],[Артикул]],[1]Подбор!$CJ:$DA,15,0),"") | AK27: =IFERROR(VLOOKUP(Подбор[[#This Row],[Артикул]],[1]Подбор!$CJ:$DA,16,0),"") -> https://ipmatika.kz/products/dect-network/Gigaset-N720DM/ | AL27: =IFERROR(VLOOKUP(Подбор[[#This Row],[Артикул]],[1]Подбор!$CJ:$DA,17,0),"")
A28: S30852-H2314-R101 | B28: Gigaset | C28: N720 IP PRO SYS IM, базовая станция, микросота DECT, POE | D28: 148720 | E28: 111540 | F28: -25 | G28: 0 | H28: 0 | I28: 0 | J28: 0 | K28: 0 | L28: 0 | M28: 0 | N28: 13 | O28: 0 | P28: 0 | R28: https://ipmatika.kz/products/dect-network/Gigaset-N720IP/ | W28: =IFERROR(VLOOKUP(Подбор[[#This Row],[Артикул]],[1]Подбор!$CJ:$CW,2,0),"") -> 148720 | X28: =IFERROR(VLOOKUP(Подбор[[#This Row],[Артикул]],[1]Подбор!$CJ:$CW,3,0),"") -> 111540 | Y28: =IFERROR(VLOOKUP(Подбор[[#This Row],[Артикул]],[1]Подбор!$CJ:$CW,4,0),"") -> -25 | Z28: =IFERROR(VLOOKUP(Подбор[[#This Row],[Артикул]],[1]Подбор!$CJ:$CW,5,0),"") -> 0 | AA28: =IFERROR(VLOOKUP(Подбор[[#This Row],[Артикул]],[1]Подбор!$CJ:$CW,6,0),"") -> 0 | AB28: =IFERROR(VLOOKUP(Подбор[[#This Row],[Артикул]],[1]Подбор!$CJ:$CW,7,0),"") -> 0 | AC28: =IFERROR(VLOOKUP(Подбор[[#This Row],[Артикул]],[1]Подбор!$CJ:$CW,8,0),"") -> 0 | AD28: =IFERROR(VLOOKUP(Подбор[[#This Row],[Артикул]],[1]Подбор!$CJ:$CW,9,0),"") -> 0 | AE28: =IFERROR(VLOOKUP(Подбор[[#This Row],[Артикул]],[1]Подбор!$CJ:$CW,10,0),"") -> 0 | AF28: =IFERROR(VLOOKUP(Подбор[[#This Row],[Артикул]],[1]Подбор!$CJ:$CW,11,0),"") -> 0 | AG28: =IFERROR(VLOOKUP(Подбор[[#This Row],[Артикул]],[1]Подбор!$CJ:$CW,12,0),"") -> 13 | AH28: =IFERROR(VLOOKUP(Подбор[[#This Row],[Артикул]],[1]Подбор!$CJ:$CW,13,0),"") -> 0 | AI28: =IFERROR(VLOOKUP(Подбор[[#This Row],[Артикул]],[1]Подбор!$CJ:$CW,14,0),"") -> 0 | AJ28: =IFERROR(VLOOKUP(Подбор[[#This Row],[Артикул]],[1]Подбор!$CJ:$DA,15,0),"") | AK28: =IFERROR(VLOOKUP(Подбор[[#This Row],[Артикул]],[1]Подбор!$CJ:$DA,16,0),"") -> https://ipmatika.kz/products/dect-network/Gigaset-N720IP/ | AL28: =IFERROR(VLOOKUP(Подбор[[#This Row],[Артикул]],[1]Подбор!$CJ:$DA,17,0),"")
A29: S30852-H2716-R101 | B29: Gigaset | C29: N870 IP PRO, базовая станция/DM, микросота DECT,1 DM- до 60 баз, до 250 трубок. POE, | D29: 644650 | E29: 483495.48 | F29: -24.998762 | G29: 0 | H29: 0 | I29: 0 | J29: 0 | K29: 0 | L29: 0 | M29: 0 | N29: 0 | O29: 7 | P29: 28 | R29: https://ipmatika.kz/products/dect-network/Gigaset-N870IP/ | W29: =IFERROR(VLOOKUP(Подбор[[#This Row],[Артикул]],[1]Подбор!$CJ:$CW,2,0),"") -> 644650 | X29: =IFERROR(VLOOKUP(Подбор[[#This Row],[Артикул]],[1]Подбор!$CJ:$CW,3,0),"") -> 483495.48 | Y29: =IFERROR(VLOOKUP(Подбор[[#This Row],[Артикул]],[1]Подбор!$CJ:$CW,4,0),"") -> -24.998762 | Z29: =IFERROR(VLOOKUP(Подбор[[#This Row],[Артикул]],[1]Подбор!$CJ:$CW,5,0),"") -> 0 | AA29: =IFERROR(VLOOKUP(Подбор[[#This Row],[Артикул]],[1]Подбор!$CJ:$CW,6,0),"") -> 0 | AB29: =IFERROR(VLOOKUP(Подбор[[#This Row],[Артикул]],[1]Подбор!$CJ:$CW,7,0),"") -> 0 | AC29: =IFERROR(VLOOKUP(Подбор[[#This Row],[Артикул]],[1]Подбор!$CJ:$CW,8,0),"") -> 0 | AD29: =IFERROR(VLOOKUP(Подбор[[#This Row],[Артикул]],[1]Подбор!$CJ:$CW,9,0),"") -> 0 | AE29: =IFERROR(VLOOKUP(Подбор[[#This Row],[Артикул]],[1]Подбор!$CJ:$CW,10,0),"") -> 0 | AF29: =IFERROR(VLOOKUP(Подбор[[#This Row],[Артикул]],[1]Подбор!$CJ:$CW,11,0),"") -> 0 | AG29: =IFERROR(VLOOKUP(Подбор[[#This Row],[Артикул]],[1]Подбор!$CJ:$CW,12,0),"") -> 0 | AH29: =IFERROR(VLOOKUP(Подбор[[#This Row],[Артикул]],[1]Подбор!$CJ:$CW,13,0),"") -> 7 | AI29: =IFERROR(VLOOKUP(Подбор[[#This Row],[Артикул]],[1]Подбор!$CJ:$CW,14,0),"") -> 28 | AJ29: =IFERROR(VLOOKUP(Подбор[[#This Row],[Артикул]],[1]Подбор!$CJ:$DA,15,0),"") | AK29: =IFERROR(VLOOKUP(Подбор[[#This Row],[Артикул]],[1]Подбор!$CJ:$DA,16,0),"") -> https://ipmatika.kz/products/dect-network/Gigaset-N870IP/ | AL29: =IFERROR(VLOOKUP(Подбор[[#This Row],[Артикул]],[1]Подбор!$CJ:$DA,17,0),"")
A30: S30852-H2718-R101 | B30: Gigaset | C30: N870E IP PRO, базовая станция/DM,съемные вне. антенны, 1 DM - до 60 баз, до 250 трубок. POE | D30: 715480 | E30: 536608.8 | F30: -25.000168 | G30: 0 | H30: 0 | I30: 0 | J30: 0 | K30: 0 | L30: 0 | M30: 0 | N30: 0 | O30: 0 | P30: 6 | R30: https://ipmatika.kz/products/dect-network/gigaset-n870e-ip-pro/ | W30: =IFERROR(VLOOKUP(Подбор[[#This Row],[Артикул]],[1]Подбор!$CJ:$CW,2,0),"") -> 715480 | X30: =IFERROR(VLOOKUP(Подбор[[#This Row],[Артикул]],[1]Подбор!$CJ:$CW,3,0),"") -> 536608.8 | Y30: =IFERROR(VLOOKUP(Подбор[[#This Row],[Артикул]],[1]Подбор!$CJ:$CW,4,0),"") -> -25.000168 | Z30: =IFERROR(VLOOKUP(Подбор[[#This Row],[Артикул]],[1]Подбор!$CJ:$CW,5,0),"") -> 0 | AA30: =IFERROR(VLOOKUP(Подбор[[#This Row],[Артикул]],[1]Подбор!$CJ:$CW,6,0),"") -> 0 | AB30: =IFERROR(VLOOKUP(Подбор[[#This Row],[Артикул]],[1]Подбор!$CJ:$CW,7,0),"") -> 0 | AC30: =IFERROR(VLOOKUP(Подбор[[#This Row],[Артикул]],[1]Подбор!$CJ:$CW,8,0),"") -> 0 | AD30: =IFERROR(VLOOKUP(Подбор[[#This Row],[Артикул]],[1]Подбор!$CJ:$CW,9,0),"") -> 0 | AE30: =IFERROR(VLOOKUP(Подбор[[#This Row],[Артикул]],[1]Подбор!$CJ:$CW,10,0),"") -> 0 | AF30: =IFERROR(VLOOKUP(Подбор[[#This Row],[Артикул]],[1]Подбор!$CJ:$CW,11,0),"") -> 0 | AG30: =IFERROR(VLOOKUP(Подбор[[#This Row],[Артикул]],[1]Подбор!$CJ:$CW,12,0),"") -> 0 | AH30: =IFERROR(VLOOKUP(Подбор[[#This Row],[Артикул]],[1]Подбор!$CJ:$CW,13,0),"") -> 0 | AI30: =IFERROR(VLOOKUP(Подбор[[#This Row],[Артикул]],[1]Подбор!$CJ:$CW,14,0),"") -> 6 | AJ30: =IFERROR(VLOOKUP(Подбор[[#This Row],[Артикул]],[1]Подбор!$CJ:$DA,15,0),"") | AK30: =IFERROR(VLOOKUP(Подбор[[#This Row],[Артикул]],[1]Подбор!$CJ:$DA,16,0),"") -> https://ipmatika.kz/products/dect-network/gigaset-n870e-ip-pro/ | AL30: =IFERROR(VLOOKUP(Подбор[[#This Row],[Артикул]],[1]Подбор!$CJ:$DA,17,0),"")
A31: Лицензии GIGASET | G31: 0 | H31: 0 | I31: 0 | J31: 0 | K31: 0 | L31: 0 | M31: 0 | N31: 0 | O31: 0 | P31: 0 | W31: =IFERROR(VLOOKUP(Подбор[[#This Row],[Артикул]],[1]Подбор!$CJ:$CW,2,0),"") | X31: =IFERROR(VLOOKUP(Подбор[[#This Row],[Артикул]],[1]Подбор!$CJ:$CW,3,0),"") | Y31: =IFERROR(VLOOKUP(Подбор[[#This Row],[Артикул]],[1]Подбор!$CJ:$CW,4,0),"") | Z31: =IFERROR(VLOOKUP(Подбор[[#This Row],[Артикул]],[1]Подбор!$CJ:$CW,5,0),"") -> 0 | AA31: =IFERROR(VLOOKUP(Подбор[[#This Row],[Артикул]],[1]Подбор!$CJ:$CW,6,0),"") -> 0 | AB31: =IFERROR(VLOOKUP(Подбор[[#This Row],[Артикул]],[1]Подбор!$CJ:$CW,7,0),"") -> 0 | AC31: =IFERROR(VLOOKUP(Подбор[[#This Row],[Артикул]],[1]Подбор!$CJ:$CW,8,0),"") -> 0 | AD31: =IFERROR(VLOOKUP(Подбор[[#This Row],[Артикул]],[1]Подбор!$CJ:$CW,9,0),"") -> 0 | AE31: =IFERROR(VLOOKUP(Подбор[[#This Row],[Артикул]],[1]Подбор!$CJ:$CW,10,0),"") -> 0 | AF31: =IFERROR(VLOOKUP(Подбор[[#This Row],[Артикул]],[1]Подбор!$CJ:$CW,11,0),"") -> 0 | AG31: =IFERROR(VLOOKUP(Подбор[[#This Row],[Артикул]],[1]Подбор!$CJ:$CW,12,0),"") -> 0 | AH31: =IFERROR(VLOOKUP(Подбор[[#This Row],[Артикул]],[1]Подбор!$CJ:$CW,13,0),"") -> 0 | AI31: =IFERROR(VLOOKUP(Подбор[[#This Row],[Артикул]],[1]Подбор!$CJ:$CW,14,0),"") -> 0 | AJ31: =IFERROR(VLOOKUP(Подбор[[#This Row],[Артикул]],[1]Подбор!$CJ:$DA,15,0),"") | AK31: =IFERROR(VLOOKUP(Подбор[[#This Row],[Артикул]],[1]Подбор!$CJ:$DA,16,0),"") | AL31: =IFERROR(VLOOKUP(Подбор[[#This Row],[Артикул]],[1]Подбор!$CJ:$DA,17,0),"")
A32: S30852-H2716-X1 | B32: Gigaset | C32: Лицензия Integrator для N870/N670 IP PRO | D32: 710950 | E32: 604310 | F32: -14.999648 | G32: 0 | H32: 0 | I32: 0 | J32: 0 | K32: 0 | L32: 0 | M32: 0 | N32: 0 | O32: 0 | P32: 0 | R32: https://ipmatika.kz/products/dect-network/Gigaset_Integrator_License/ | W32: =IFERROR(VLOOKUP(Подбор[[#This Row],[Артикул]],[1]Подбор!$CJ:$CW,2,0),"") -> 710950 | X32: =IFERROR(VLOOKUP(Подбор[[#This Row],[Артикул]],[1]Подбор!$CJ:$CW,3,0),"") -> 604310 | Y32: =IFERROR(VLOOKUP(Подбор[[#This Row],[Артикул]],[1]Подбор!$CJ:$CW,4,0),"") -> -14.999648 | Z32: =IFERROR(VLOOKUP(Подбор[[#This Row],[Артикул]],[1]Подбор!$CJ:$CW,5,0),"") -> 0 | AA32: =IFERROR(VLOOKUP(Подбор[[#This Row],[Артикул]],[1]Подбор!$CJ:$CW,6,0),"") -> 0 | AB32: =IFERROR(VLOOKUP(Подбор[[#This Row],[Артикул]],[1]Подбор!$CJ:$CW,7,0),"") -> 0 | AC32: =IFERROR(VLOOKUP(Подбор[[#This Row],[Артикул]],[1]Подбор!$CJ:$CW,8,0),"") -> 0 | AD32: =IFERROR(VLOOKUP(Подбор[[#This Row],[Артикул]],[1]Подбор!$CJ:$CW,9,0),"") -> 0 | AE32: =IFERROR(VLOOKUP(Подбор[[#This Row],[Артикул]],[1]Подбор!$CJ:$CW,10,0),"") -> 0 | AF32: =IFERROR(VLOOKUP(Подбор[[#This Row],[Артикул]],[1]Подбор!$CJ:$CW,11,0),"") -> 0 | AG32: =IFERROR(VLOOKUP(Подбор[[#This Row],[Артикул]],[1]Подбор!$CJ:$CW,12,0),"") -> 0 | AH32: =IFERROR(VLOOKUP(Подбор[[#This Row],[Артикул]],[1]Подбор!$CJ:$CW,13,0),"") -> 0 | AI32: =IFERROR(VLOOKUP(Подбор[[#This Row],[Артикул]],[1]Подбор!$CJ:$CW,14,0),"") -> 0 | AJ32: =IFERROR(VLOOKUP(Подбор[[#This Row],[Артикул]],[1]Подбор!$CJ:$DA,15,0),"") | AK32: =IFERROR(VLOOKUP(Подбор[[#This Row],[Артикул]],[1]Подбор!$CJ:$DA,16,0),"") -> https://ipmatika.kz/products/dect-network/Gigaset_Integrator_License/ | AL32: =IFERROR(VLOOKUP(Подбор[[#This Row],[Артикул]],[1]Подбор!$CJ:$DA,17,0),"")
A33: S30852-H2714-X3 | B33: Gigaset | C33: Лицензия апгрейда N670 IP PRO до N870 IP PRO | D33: 516510 | E33: 439040 | F33: -14.998742 | G33: 0 | H33: 0 | I33: 0 | J33: 0 | K33: 0 | L33: 0 | M33: 0 | N33: 0 | O33: 0 | P33: 0 | R33: https://ipmatika.kz/products/dect-network/N670_upgrade_license/ | W33: =IFERROR(VLOOKUP(Подбор[[#This Row],[Артикул]],[1]Подбор!$CJ:$CW,2,0),"") -> 516510 | X33: =IFERROR(VLOOKUP(Подбор[[#This Row],[Артикул]],[1]Подбор!$CJ:$CW,3,0),"") -> 439040 | Y33: =IFERROR(VLOOKUP(Подбор[[#This Row],[Артикул]],[1]Подбор!$CJ:$CW,4,0),"") -> -14.998742 | Z33: =IFERROR(VLOOKUP(Подбор[[#This Row],[Артикул]],[1]Подбор!$CJ:$CW,5,0),"") -> 0 | AA33: =IFERROR(VLOOKUP(Подбор[[#This Row],[Артикул]],[1]Подбор!$CJ:$CW,6,0),"") -> 0 | AB33: =IFERROR(VLOOKUP(Подбор[[#This Row],[Артикул]],[1]Подбор!$CJ:$CW,7,0),"") -> 0 | AC33: =IFERROR(VLOOKUP(Подбор[[#This Row],[Артикул]],[1]Подбор!$CJ:$CW,8,0),"") -> 0 | AD33: =IFERROR(VLOOKUP(Подбор[[#This Row],[Артикул]],[1]Подбор!$CJ:$CW,9,0),"") -> 0 | AE33: =IFERROR(VLOOKUP(Подбор[[#This Row],[Артикул]],[1]Подбор!$CJ:$CW,10,0),"") -> 0 | AF33: =IFERROR(VLOOKUP(Подбор[[#This Row],[Артикул]],[1]Подбор!$CJ:$CW,11,0),"") -> 0 | AG33: =IFERROR(VLOOKUP(Подбор[[#This Row],[Артикул]],[1]Подбор!$CJ:$CW,12,0),"") -> 0 | AH33: =IFERROR(VLOOKUP(Подбор[[#This Row],[Артикул]],[1]Подбор!$CJ:$CW,13,0),"") -> 0 | AI33: =IFERROR(VLOOKUP(Подбор[[#This Row],[Артикул]],[1]Подбор!$CJ:$CW,14,0),"") -> 0 | AJ33: =IFERROR(VLOOKUP(Подбор[[#This Row],[Артикул]],[1]Подбор!$CJ:$DA,15,0),"") | AK33: =IFERROR(VLOOKUP(Подбор[[#This Row],[Артикул]],[1]Подбор!$CJ:$DA,16,0),"") -> https://ipmatika.kz/products/dect-network/N670_upgrade_license/ | AL33: =IFERROR(VLOOKUP(Подбор[[#This Row],[Артикул]],[1]Подбор!$CJ:$DA,17,0),"")
A34: S30852-H2714-X2 | B34: Gigaset | C34: Лицензия для дект менеджера GIGASET N670 IP PRO | D34: 171650 | E34: 145900 | F34: -15.001456 | G34: 0 | H34: 0 | I34: 0 | J34: 0 | K34: 0 | L34: 0 | M34: 0 | N34: 0 | O34: 0 | P34: 0 | R34: https://ipmatika.kz/products/dect-network/DM_N670_License/ | W34: =IFERROR(VLOOKUP(Подбор[[#This Row],[Артикул]],[1]Подбор!$CJ:$CW,2,0),"") -> 171650 | X34: =IFERROR(VLOOKUP(Подбор[[#This Row],[Артикул]],[1]Подбор!$CJ:$CW,3,0),"") -> 145900 | Y34: =IFERROR(VLOOKUP(Подбор[[#This Row],[Артикул]],[1]Подбор!$CJ:$CW,4,0),"") -> -15.001456 | Z34: =IFERROR(VLOOKUP(Подбор[[#This Row],[Артикул]],[1]Подбор!$CJ:$CW,5,0),"") -> 0 | AA34: =IFERROR(VLOOKUP(Подбор[[#This Row],[Артикул]],[1]Подбор!$CJ:$CW,6,0),"") -> 0 | AB34: =IFERROR(VLOOKUP(Подбор[[#This Row],[Артикул]],[1]Подбор!$CJ:$CW,7,0),"") -> 0 | AC34: =IFERROR(VLOOKUP(Подбор[[#This Row],[Артикул]],[1]Подбор!$CJ:$CW,8,0),"") -> 0 | AD34: =IFERROR(VLOOKUP(Подбор[[#This Row],[Артикул]],[1]Подбор!$CJ:$CW,9,0),"") -> 0 | AE34: =IFERROR(VLOOKUP(Подбор[[#This Row],[Артикул]],[1]Подбор!$CJ:$CW,10,0),"") -> 0 | AF34: =IFERROR(VLOOKUP(Подбор[[#This Row],[Артикул]],[1]Подбор!$CJ:$CW,11,0),"") -> 0 | AG34: =IFERROR(VLOOKUP(Подбор[[#This Row],[Артикул]],[1]Подбор!$CJ:$CW,12,0),"") -> 0 | AH34: =IFERROR(VLOOKUP(Подбор[[#This Row],[Артикул]],[1]Подбор!$CJ:$CW,13,0),"") -> 0 | AI34: =IFERROR(VLOOKUP(Подбор[[#This Row],[Артикул]],[1]Подбор!$CJ:$CW,14,0),"") -> 0 | AJ34: =IFERROR(VLOOKUP(Подбор[[#This Row],[Артикул]],[1]Подбор!$CJ:$DA,15,0),"") | AK34: =IFERROR(VLOOKUP(Подбор[[#This Row],[Артикул]],[1]Подбор!$CJ:$DA,16,0),"") -> https://ipmatika.kz/products/dect-network/DM_N670_License/ | AL34: =IFERROR(VLOOKUP(Подбор[[#This Row],[Артикул]],[1]Подбор!$CJ:$DA,17,0),"")
A35: S30852-H2716-X2 | B35: Gigaset | C35: Лицензия для дект менеджера GIGASET N870 IP PRO | D35: 498060 | E35: 423360 | F35: -14.998193 | G35: 0 | H35: 0 | I35: 0 | J35: 0 | K35: 0 | L35: 0 | M35: 0 | N35: 0 | O35: 0 | P35: 0 | R35: https://ipmatika.kz/products/dect-network/N870_License/ | W35: =IFERROR(VLOOKUP(Подбор[[#This Row],[Артикул]],[1]Подбор!$CJ:$CW,2,0),"") -> 498060 | X35: =IFERROR(VLOOKUP(Подбор[[#This Row],[Артикул]],[1]Подбор!$CJ:$CW,3,0),"") -> 423360 | Y35: =IFERROR(VLOOKUP(Подбор[[#This Row],[Артикул]],[1]Подбор!$CJ:$CW,4,0),"") -> -14.998193 | Z35: =IFERROR(VLOOKUP(Подбор[[#This Row],[Артикул]],[1]Подбор!$CJ:$CW,5,0),"") -> 0 | AA35: =IFERROR(VLOOKUP(Подбор[[#This Row],[Артикул]],[1]Подбор!$CJ:$CW,6,0),"") -> 0 | AB35: =IFERROR(VLOOKUP(Подбор[[#This Row],[Артикул]],[1]Подбор!$CJ:$CW,7,0),"") -> 0 | AC35: =IFERROR(VLOOKUP(Подбор[[#This Row],[Артикул]],[1]Подбор!$CJ:$CW,8,0),"") -> 0 | AD35: =IFERROR(VLOOKUP(Подбор[[#This Row],[Артикул]],[1]Подбор!$CJ:$CW,9,0),"") -> 0 | AE35: =IFERROR(VLOOKUP(Подбор[[#This Row],[Артикул]],[1]Подбор!$CJ:$CW,10,0),"") -> 0 | AF35: =IFERROR(VLOOKUP(Подбор[[#This Row],[Артикул]],[1]Подбор!$CJ:$CW,11,0),"") -> 0 | AG35: =IFERROR(VLOOKUP(Подбор[[#This Row],[Артикул]],[1]Подбор!$CJ:$CW,12,0),"") -> 0 | AH35: =IFERROR(VLOOKUP(Подбор[[#This Row],[Артикул]],[1]Подбор!$CJ:$CW,13,0),"") -> 0 | AI35: =IFERROR(VLOOKUP(Подбор[[#This Row],[Артикул]],[1]Подбор!$CJ:$CW,14,0),"") -> 0 | AJ35: =IFERROR(VLOOKUP(Подбор[[#This Row],[Артикул]],[1]Подбор!$CJ:$DA,15,0),"") | AK35: =IFERROR(VLOOKUP(Подбор[[#This Row],[Артикул]],[1]Подбор!$CJ:$DA,16,0),"") -> https://ipmatika.kz/products/dect-network/N870_License/ | AL35: =IFERROR(VLOOKUP(Подбор[[#This Row],[Артикул]],[1]Подбор!$CJ:$DA,17,0),"")
A36: Прочее GIGASET | G36: 0 | H36: 0 | I36: 0 | J36: 0 | K36: 0 | L36: 0 | M36: 0 | N36: 0 | O36: 0 | P36: 0 | W36: =IFERROR(VLOOKUP(Подбор[[#This Row],[Артикул]],[1]Подбор!$CJ:$CW,2,0),"") | X36: =IFERROR(VLOOKUP(Подбор[[#This Row],[Артикул]],[1]Подбор!$CJ:$CW,3,0),"") | Y36: =IFERROR(VLOOKUP(Подбор[[#This Row],[Артикул]],[1]Подбор!$CJ:$CW,4,0),"") | Z36: =IFERROR(VLOOKUP(Подбор[[#This Row],[Артикул]],[1]Подбор!$CJ:$CW,5,0),"") -> 0 | AA36: =IFERROR(VLOOKUP(Подбор[[#This Row],[Артикул]],[1]Подбор!$CJ:$CW,6,0),"") -> 0 | AB36: =IFERROR(VLOOKUP(Подбор[[#This Row],[Артикул]],[1]Подбор!$CJ:$CW,7,0),"") -> 0 | AC36: =IFERROR(VLOOKUP(Подбор[[#This Row],[Артикул]],[1]Подбор!$CJ:$CW,8,0),"") -> 0 | AD36: =IFERROR(VLOOKUP(Подбор[[#This Row],[Артикул]],[1]Подбор!$CJ:$CW,9,0),"") -> 0 | AE36: =IFERROR(VLOOKUP(Подбор[[#This Row],[Артикул]],[1]Подбор!$CJ:$CW,10,0),"") -> 0 | AF36: =IFERROR(VLOOKUP(Подбор[[#This Row],[Артикул]],[1]Подбор!$CJ:$CW,11,0),"") -> 0 | AG36: =IFERROR(VLOOKUP(Подбор[[#This Row],[Артикул]],[1]Подбор!$CJ:$CW,12,0),"") -> 0 | AH36: =IFERROR(VLOOKUP(Подбор[[#This Row],[Артикул]],[1]Подбор!$CJ:$CW,13,0),"") -> 0 | AI36: =IFERROR(VLOOKUP(Подбор[[#This Row],[Артикул]],[1]Подбор!$CJ:$CW,14,0),"") -> 0 | AJ36: =IFERROR(VLOOKUP(Подбор[[#This Row],[Артикул]],[1]Подбор!$CJ:$DA,15,0),"") | AK36: =IFERROR(VLOOKUP(Подбор[[#This Row],[Артикул]],[1]Подбор!$CJ:$DA,16,0),"") | AL36: =IFERROR(VLOOKUP(Подбор[[#This Row],[Артикул]],[1]Подбор!$CJ:$DA,17,0),"")
A37: S30853-H4061-S301 | B37: Gigaset | C37: Gigaset Exp module, модуль расширения для телефонов Maxwell 3, Basic | D37: 65440 | G37: 0 | H37: 0 | I37: 0 | J37: 0 | K37: 0 | L37: 0 | M37: 0 | N37: 0 | O37: 0 | P37: 0 | W37: =IFERROR(VLOOKUP(Подбор[[#This Row],[Артикул]],[1]Подбор!$CJ:$CW,2,0),"") -> 65440 | X37: =IFERROR(VLOOKUP(Подбор[[#This Row],[Артикул]],[1]Подбор!$CJ:$CW,3,0),"") | Y37: =IFERROR(VLOOKUP(Подбор[[#This Row],[Артикул]],[1]Подбор!$CJ:$CW,4,0),"") | Z37: =IFERROR(VLOOKUP(Подбор[[#This Row],[Артикул]],[1]Подбор!$CJ:$CW,5,0),"") -> 0 | AA37: =IFERROR(VLOOKUP(Подбор[[#This Row],[Артикул]],[1]Подбор!$CJ:$CW,6,0),"") -> 0 | AB37: =IFERROR(VLOOKUP(Подбор[[#This Row],[Артикул]],[1]Подбор!$CJ:$CW,7,0),"") -> 0 | AC37: =IFERROR(VLOOKUP(Подбор[[#This Row],[Артикул]],[1]Подбор!$CJ:$CW,8,0),"") -> 0 | AD37: =IFERROR(VLOOKUP(Подбор[[#This Row],[Артикул]],[1]Подбор!$CJ:$CW,9,0),"") -> 0 | AE37: =IFERROR(VLOOKUP(Подбор[[#This Row],[Артикул]],[1]Подбор!$CJ:$CW,10,0),"") -> 0 | AF37: =IFERROR(VLOOKUP(Подбор[[#This Row],[Артикул]],[1]Подбор!$CJ:$CW,11,0),"") -> 0 | AG37: =IFERROR(VLOOKUP(Подбор[[#This Row],[Артикул]],[1]Подбор!$CJ:$CW,12,0),"") -> 0 | AH37: =IFERROR(VLOOKUP(Подбор[[#This Row],[Артикул]],[1]Подбор!$CJ:$CW,13,0),"") -> 0 | AI37: =IFERROR(VLOOKUP(Подбор[[#This Row],[Артикул]],[1]Подбор!$CJ:$CW,14,0),"") -> 0 | AJ37: =IFERROR(VLOOKUP(Подбор[[#This Row],[Артикул]],[1]Подбор!$CJ:$DA,15,0),"") | AK37: =IFERROR(VLOOKUP(Подбор[[#This Row],[Артикул]],[1]Подбор!$CJ:$DA,16,0),"") | AL37: =IFERROR(VLOOKUP(Подбор[[#This Row],[Артикул]],[1]Подбор!$CJ:$DA,17,0),"")
A38: S30853-H4006-R121 | B38: Gigaset | C38: Maxwell 10S, видеотелефон, DECT трубка, Android, Bluetooth, WIFI, GigE, c БП | D38: 761380 | G38: 0 | H38: 0 | I38: 0 | J38: 0 | K38: 0 | L38: 0 | M38: 0 | N38: 2 | O38: 0 | P38: 0 | R38: https://ipmatika.kz/products/videophones/gigaset-maxwell-10s/ | W38: =IFERROR(VLOOKUP(Подбор[[#This Row],[Артикул]],[1]Подбор!$CJ:$CW,2,0),"") -> 761380 | X38: =IFERROR(VLOOKUP(Подбор[[#This Row],[Артикул]],[1]Подбор!$CJ:$CW,3,0),"") | Y38: =IFERROR(VLOOKUP(Подбор[[#This Row],[Артикул]],[1]Подбор!$CJ:$CW,4,0),"") | Z38: =IFERROR(VLOOKUP(Подбор[[#This Row],[Артикул]],[1]Подбор!$CJ:$CW,5,0),"") -> 0 | AA38: =IFERROR(VLOOKUP(Подбор[[#This Row],[Артикул]],[1]Подбор!$CJ:$CW,6,0),"") -> 0 | AB38: =IFERROR(VLOOKUP(Подбор[[#This Row],[Артикул]],[1]Подбор!$CJ:$CW,7,0),"") -> 0 | AC38: =IFERROR(VLOOKUP(Подбор[[#This Row],[Артикул]],[1]Подбор!$CJ:$CW,8,0),"") -> 0 | AD38: =IFERROR(VLOOKUP(Подбор[[#This Row],[Артикул]],[1]Подбор!$CJ:$CW,9,0),"") -> 0 | AE38: =IFERROR(VLOOKUP(Подбор[[#This Row],[Артикул]],[1]Подбор!$CJ:$CW,10,0),"") -> 0 | AF38: =IFERROR(VLOOKUP(Подбор[[#This Row],[Артикул]],[1]Подбор!$CJ:$CW,11,0),"") -> 0 | AG38: =IFERROR(VLOOKUP(Подбор[[#This Row],[Артикул]],[1]Подбор!$CJ:$CW,12,0),"") -> 2 | AH38: =IFERROR(VLOOKUP(Подбор[[#This Row],[Артикул]],[1]Подбор!$CJ:$CW,13,0),"") -> 0 | AI38: =IFERROR(VLOOKUP(Подбор[[#This Row],[Артикул]],[1]Подбор!$CJ:$CW,14,0),"") -> 0 | AJ38: =IFERROR(VLOOKUP(Подбор[[#This Row],[Артикул]],[1]Подбор!$CJ:$DA,15,0),"") | AK38: =IFERROR(VLOOKUP(Подбор[[#This Row],[Артикул]],[1]Подбор!$CJ:$DA,16,0),"") -> https://ipmatika.kz/products/videophones/gigaset-maxwell-10s/ | AL38: =IFERROR(VLOOKUP(Подбор[[#This Row],[Артикул]],[1]Подбор!$CJ:$DA,17,0),"")
A39: S30852-H2316-R101 (test) | B39: Gigaset | C39: N720 SPK PRO, измерительный комплект (чемодан гигасет) | D39: 719880 | G39: 0 | H39: 0 | I39: 0 | J39: 0 | K39: 0 | L39: 0 | M39: 0 | N39: 0 | O39: 0 | P39: 0 | R39: https://ipmatika.kz/products/dect-network/N720_SPK_PRO/ | W39: =IFERROR(VLOOKUP(Подбор[[#This Row],[Артикул]],[1]Подбор!$CJ:$CW,2,0),"") -> 719880 | X39: =IFERROR(VLOOKUP(Подбор[[#This Row],[Артикул]],[1]Подбор!$CJ:$CW,3,0),"") | Y39: =IFERROR(VLOOKUP(Подбор[[#This Row],[Артикул]],[1]Подбор!$CJ:$CW,4,0),"") | Z39: =IFERROR(VLOOKUP(Подбор[[#This Row],[Артикул]],[1]Подбор!$CJ:$CW,5,0),"") -> 0 | AA39: =IFERROR(VLOOKUP(Подбор[[#This Row],[Артикул]],[1]Подбор!$CJ:$CW,6,0),"") -> 0 | AB39: =IFERROR(VLOOKUP(Подбор[[#This Row],[Артикул]],[1]Подбор!$CJ:$CW,7,0),"") -> 0 | AC39: =IFERROR(VLOOKUP(Подбор[[#This Row],[Артикул]],[1]Подбор!$CJ:$CW,8,0),"") -> 0 | AD39: =IFERROR(VLOOKUP(Подбор[[#This Row],[Артикул]],[1]Подбор!$CJ:$CW,9,0),"") -> 0 | AE39: =IFERROR(VLOOKUP(Подбор[[#This Row],[Артикул]],[1]Подбор!$CJ:$CW,10,0),"") -> 0 | AF39: =IFERROR(VLOOKUP(Подбор[[#This Row],[Артикул]],[1]Подбор!$CJ:$CW,11,0),"") -> 0 | AG39: =IFERROR(VLOOKUP(Подбор[[#This Row],[Артикул]],[1]Подбор!$CJ:$CW,12,0),"") -> 0 | AH39: =IFERROR(VLOOKUP(Подбор[[#This Row],[Артикул]],[1]Подбор!$CJ:$CW,13,0),"") -> 0 | AI39: =IFERROR(VLOOKUP(Подбор[[#This Row],[Артикул]],[1]Подбор!$CJ:$CW,14,0),"") -> 0 | AJ39: =IFERROR(VLOOKUP(Подбор[[#This Row],[Артикул]],[1]Подбор!$CJ:$DA,15,0),"") | AK39: =IFERROR(VLOOKUP(Подбор[[#This Row],[Артикул]],[1]Подбор!$CJ:$DA,16,0),"") -> https://ipmatika.kz/products/dect-network/N720_SPK_PRO/ | AL39: =IFERROR(VLOOKUP(Подбор[[#This Row],[Артикул]],[1]Подбор!$CJ:$DA,17,0),"")
A40: L36280-Z4-X765 | B40: Gigaset | C40: PSU, БП для N720 IP, N720 DM, Maxwell 10S | G40: 0 | H40: 0 | I40: 0 | J40: 0 | K40: 0 | L40: 0 | M40: 0 | N40: 1 | O40: 0 | P40: 0 | R40: https://ipmatika.kz/products/dect-network/%C1%EB%EE%EA_%EF%E8%F2%E0%ED%E8%FF_%E4%EB%FF_N720_IP%2C_N720_DM%2C_Maxwell_10S/ | W40: =IFERROR(VLOOKUP(Подбор[[#This Row],[Артикул]],[1]Подбор!$CJ:$CW,2,0),"") | X40: =IFERROR(VLOOKUP(Подбор[[#This Row],[Артикул]],[1]Подбор!$CJ:$CW,3,0),"") | Y40: =IFERROR(VLOOKUP(Подбор[[#This Row],[Артикул]],[1]Подбор!$CJ:$CW,4,0),"") | Z40: =IFERROR(VLOOKUP(Подбор[[#This Row],[Артикул]],[1]Подбор!$CJ:$CW,5,0),"") -> 0 | AA40: =IFERROR(VLOOKUP(Подбор[[#This Row],[Артикул]],[1]Подбор!$CJ:$CW,6,0),"") -> 0 | AB40: =IFERROR(VLOOKUP(Подбор[[#This Row],[Артикул]],[1]Подбор!$CJ:$CW,7,0),"") -> 0 | AC40: =IFERROR(VLOOKUP(Подбор[[#This Row],[Артикул]],[1]Подбор!$CJ:$CW,8,0),"") -> 0 | AD40: =IFERROR(VLOOKUP(Подбор[[#This Row],[Артикул]],[1]Подбор!$CJ:$CW,9,0),"") -> 0 | AE40: =IFERROR(VLOOKUP(Подбор[[#This Row],[Артикул]],[1]Подбор!$CJ:$CW,10,0),"") -> 0 | AF40: =IFERROR(VLOOKUP(Подбор[[#This Row],[Артикул]],[1]Подбор!$CJ:$CW,11,0),"") -> 0 | AG40: =IFERROR(VLOOKUP(Подбор[[#This Row],[Артикул]],[1]Подбор!$CJ:$CW,12,0),"") -> 1 | AH40: =IFERROR(VLOOKUP(Подбор[[#This Row],[Артикул]],[1]Подбор!$CJ:$CW,13,0),"") -> 0 | AI40: =IFERROR(VLOOKUP(Подбор[[#This Row],[Артикул]],[1]Подбор!$CJ:$CW,14,0),"") -> 0 | AJ40: =IFERROR(VLOOKUP(Подбор[[#This Row],[Артикул]],[1]Подбор!$CJ:$DA,15,0),"") | AK40: =IFERROR(VLOOKUP(Подбор[[#This Row],[Артикул]],[1]Подбор!$CJ:$DA,16,0),"") -> https://ipmatika.kz/products/dect-network/%C1%EB%EE%EA_%EF%E8%F2%E0%ED%E8%FF_%E4%EB%FF_N720_IP%2C_N720_DM%2C_Maxwell_10S/ | AL40: =IFERROR(VLOOKUP(Подбор[[#This Row],[Артикул]],[1]Подбор!$CJ:$DA,17,0),"")
A41: L36280-Z4-X706 | B41: Gigaset | C41: PSU, БП для N870 IP, N720 DM | D41: 19270 | E41: 14452.88 | F41: -24.998028 | G41: 0 | H41: 0 | I41: 0 | J41: 0 | K41: 0 | L41: 0 | M41: 0 | N41: 4 | O41: 0 | P41: 0 | R41: https://ipmatika.kz/products/dect-network/%C1%EB%EE%EA_%EF%E8%F2%E0%ED%E8%FF_%E4%EB%FF_N870_IP%2C_N720%20DM/ | W41: =IFERROR(VLOOKUP(Подбор[[#This Row],[Артикул]],[1]Подбор!$CJ:$CW,2,0),"") -> 19270 | X41: =IFERROR(VLOOKUP(Подбор[[#This Row],[Артикул]],[1]Подбор!$CJ:$CW,3,0),"") -> 14452.88 | Y41: =IFERROR(VLOOKUP(Подбор[[#This Row],[Артикул]],[1]Подбор!$CJ:$CW,4,0),"") -> -24.998028 | Z41: =IFERROR(VLOOKUP(Подбор[[#This Row],[Артикул]],[1]Подбор!$CJ:$CW,5,0),"") -> 0 | AA41: =IFERROR(VLOOKUP(Подбор[[#This Row],[Артикул]],[1]Подбор!$CJ:$CW,6,0),"") -> 0 | AB41: =IFERROR(VLOOKUP(Подбор[[#This Row],[Артикул]],[1]Подбор!$CJ:$CW,7,0),"") -> 0 | AC41: =IFERROR(VLOOKUP(Подбор[[#This Row],[Артикул]],[1]Подбор!$CJ:$CW,8,0),"") -> 0 | AD41: =IFERROR(VLOOKUP(Подбор[[#This Row],[Артикул]],[1]Подбор!$CJ:$CW,9,0),"") -> 0 | AE41: =IFERROR(VLOOKUP(Подбор[[#This Row],[Артикул]],[1]Подбор!$CJ:$CW,10,0),"") -> 0 | AF41: =IFERROR(VLOOKUP(Подбор[[#This Row],[Артикул]],[1]Подбор!$CJ:$CW,11,0),"") -> 0 | AG41: =IFERROR(VLOOKUP(Подбор[[#This Row],[Артикул]],[1]Подбор!$CJ:$CW,12,0),"") -> 4 | AH41: =IFERROR(VLOOKUP(Подбор[[#This Row],[Артикул]],[1]Подбор!$CJ:$CW,13,0),"") -> 0 | AI41: =IFERROR(VLOOKUP(Подбор[[#This Row],[Артикул]],[1]Подбор!$CJ:$CW,14,0),"") -> 0 | AJ41: =IFERROR(VLOOKUP(Подбор[[#This Row],[Артикул]],[1]Подбор!$CJ:$DA,15,0),"") | AK41: =IFERROR(VLOOKUP(Подбор[[#This Row],[Артикул]],[1]Подбор!$CJ:$DA,16,0),"") -> https://ipmatika.kz/products/dect-network/%C1%EB%EE%EA_%EF%E8%F2%E0%ED%E8%FF_%E4%EB%FF_N870_IP%2C_N720%20DM/ | AL41: =IFERROR(VLOOKUP(Подбор[[#This Row],[Артикул]],[1]Подбор!$CJ:$DA,17,0),"")
